Workbook
Name 索引: #REF!

Sheet 索引
A1: 中心经营口径报表索引
A2: 序号 | B2: 索引 | C2: 报表编制说明
A3: 1 | B3: 净利简表 | C3: 1、分部及区域的预算净利及实际净利，数据来源为本文件中分部利润表、区域利润表中的预算净利润和实际净利润； 2、总监费用，预算净利数据来源为2025年中心利润表中的预算净利润及预算销售费用；实际净利为2025年中心利润表中的实际销售费用+计入到美鑫的总监工资及社保公积金费用之和； 3、因为净利简表中加了总监在美鑫的费用，所以净利简表中的汇总金额和2025年销售1中心利润表汇总有差异，差额为额外增加的这部分。
A4: 2 | B4: 所得税分摊 | C4: 1、所得税以财务口径（出库签收收入）进行计提； 2、所得税分摊的前提是基于谁受益谁承担的原则，盈利才分摊，亏损不分摊； 3、锅圈应分摊的所得税由2中心承担； 4、所得税总额为宁波味觉账面当期所得税余额，2025年销售1中心利润表中的所得税扣除锅圈承担部分的余额，两个数据有差异； 5、所得税分摊，按照各分部、区域的利润表中的正利润总额及锅圈的盈利，分别占合计利润总额的比例来分摊。
A5: 3 | B5: 2025年销售1中心利润表 | C5: 1、为中心、分部、区域的合计； 2、所得税为扣除二中心承担的税费后的余额。
A6: 4 | B6: 2025年中心利润表 | C6: 1、销售费用中为总监的费用，差旅费、招待费、样品费等挂到中心的费用。
A7: 5 | B7: 2025年江苏分部利润表 | C7: 1、营业收入的取数来源为2025年1-12月销售明细表中的金额-2025年1-12月客户计提返利的金额； 2、营业成本的取数来源为2025年1-12月销售明细表中销售结算成本+运费核对表中的运费+销售的原材料的成本； 3、税金及附加核算的是城建税、教育费附加、印花税，城建和教育费附加为当月收入的0.85%，印花税为收入的0.03%； 4、销售费用为分部人员的费用及后台职能协助挂到分部的费用（如有）； 5、所得税与所得税分摊表中数据一致。
A8: 6 | B8: 2025年浙江分部利润表 | C8: 编制规则同江苏分部利润表
A9: 7 | B9: 2025年上海分部利润表 | C9: 编制规则同江苏分部利润表
A10: 8 | B10: 2025年赣皖区域利润表 | C10: 编制规则同江苏分部利润表
A11: 9 | B11: 2025年安徽省区利润表 | C11: 编制规则同江苏分部利润表
A12: 10 | B12: 2025年江西省区利润表 | C12: 编制规则同江苏分部利润表
A13: 11 | B13: 2025年1-12月客户计提返利 | C13: 1、返利范围为经销商或有返利的直销客户，当销售额达到返利条款约定的50%时，预计很有可能实现返利的当月，开始计提返利，后续每月根据最新的销售额变动； 2、合同期限内，如果未完成返利约定销售额，该预提返利费用将冲回；如果实现返利，则该返利费用实现。
A14: 12 | B14: 产品毛利 | C14: 取数来源为2025年1-12月销售明细表
... A26: 24 | B26: 毛利率低于15%客户调整明细 | C26: 1、取数来源为ERP销售出库单列表 2、客户毛利率低于或等于15%牛油系列产品，工厂与中心五五分成毛利，调整月份为2025年5月

Sheet 收入及净利简表
A1: 销售1中心2025年各分部及区域收入&净利简表
A2: 区域 | B2: 1月 | E2: 2月 | H2: 3月 | K2: 4月 | N2: 5月 | Q2: 6月 | T2: 7月 | W2: 8月 | Z2: 9月 | AC2: 10月 | AF2: 11月 | AI2: 12月 | AL2: 合计
B3: 预算收入 | C3: 24年同期实际 | D3: 实际收入 | E3: 预算收入 | F3: 24年同期实际 | G3: 实际收入 | H3: 预算收入 | I3: 24年同期实际 | J3: 实际收入 | K3: 预算收入 | L3: 24年同期实际 | M3: 实际收入 | N3: 预算收入 | O3: 24年同期实际 | P3: 实际收入 | Q3: 预算收入 | R3: 24年同期实际 | S3: 实际收入 | T3: 预算收入 | U3: 24年同期实际 | V3: 实际收入 | W3: 预算收入 | X3: 24年同期实际 | Y3: 实际收入 | Z3: 预算收入 | AA3: 24年同期实际 | AB3: 实际收入 | AC3: 预算收入 | AD3: 24年同期实际 | AE3: 实际收入 | AF3: 预算收入 | AG3: 24年同期实际 | AH3: 实际收入 | AI3: 预算收入 | AJ3: 24年同期实际 | AK3: 实际收入 | AL3: 预算收入 | AM3: 24年同期实际 | AN3: 实际收入
A4: 江苏分部 | B4: ='2025年江苏分部利润表'!C6 -> 685500 | C4: 2214348.4 | D4: ='2025年江苏分部利润表'!D6 -> 2304694.7 | E4: ='2025年江苏分部利润表'!E6 -> 816600 | F4: 293953.61 | G4: ='2025年江苏分部利润表'!F6 -> 1666193.9 | H4: ='2025年江苏分部利润表'!G6 -> 1474500 | I4: 1021703.3 | J4: ='2025年江苏分部利润表'!H6 -> 1529599.9 | K4: ='2025年江苏分部利润表'!I6 -> 1730500 | L4: 1191870.3 | M4: ='2025年江苏分部利润表'!J6 -> 2841384.8 | N4: ='2025年江苏分部利润表'!K6 -> 1505500 | O4: 1114968.9 | P4: ='2025年江苏分部利润表'!L6 -> 2071086.5 | Q4: ='2025年江苏分部利润表'!M6 -> 1836000 | R4: 1445393.3 | S4: ='2025年江苏分部利润表'!N6 -> 2606077.2 | T4: ='2025年江苏分部利润表'!O6 -> 1948250 | U4: 1325365.9 | V4: ='2025年江苏分部利润表'!P6 -> 2343337.7 | W4: ='2025年江苏分部利润表'!Q6 -> 1944090.7 | X4: 1659134.5 | Y4: ='2025年江苏分部利润表'!R6 -> 2089992.3 | Z4: ='2025年江苏分部利润表'!S6 -> 2672284.3 | AA4: 1986844.3 | AB4: ='2025年江苏分部利润表'!T6 -> 3180499.2 | AC4: ='2025年江苏分部利润表'!U6 -> 1776275 | AD4: 1512145.6 | AE4: ='2025年江苏分部利润表'!V6 -> 1991424.3 | AF4: ='2025年江苏分部利润表'!W6 -> 2043500 | AG4: 1635695.1 | AH4: ='2025年江苏分部利润表'!X6 -> 2165174.3 | AI4: ='2025年江苏分部利润表'!Y6 -> 3781275 | AJ4: 3653965 | AK4: ='2025年江苏分部利润表'!Z6 -> 3611166.2 | AL4: =SUMIF($B$3:AK3,AL$3,$B4:$AK4) -> 22214275 | AM4: =SUMIF($B$3:AK3,AM$3,$B4:$AK4) -> 19055388 | AN4: =SUMIF($B$3:AK3,AN$3,$B4:$AK4) -> 28400631
A5: 浙江分部 | B5: ='2025年浙江分部利润表'!C6 -> 1350000 | C5: 1845184.7 | D5: ='2025年浙江分部利润表'!D6 -> 2834280.9 | E5: ='2025年浙江分部利润表'!E6 -> 1450000 | F5: 762753.83 | G5: ='2025年浙江分部利润表'!F6 -> 1525913.7 | H5: ='2025年浙江分部利润表'!G6 -> 2550000 | I5: 1399119.7 | J5: ='2025年浙江分部利润表'!H6 -> 2030623 | K5: ='2025年浙江分部利润表'!I6 -> 2550000 | L5: 1978039.7 | M5: ='2025年浙江分部利润表'!J6 -> 2478134.3 | N5: ='2025年浙江分部利润表'!K6 -> 2750000 | O5: 1891001.2 | P5: ='2025年浙江分部利润表'!L6 -> 2181764 | Q5: ='2025年浙江分部利润表'!M6 -> 2850000 | R5: 1823975.1 | S5: ='2025年浙江分部利润表'!N6 -> 2540162 | T5: ='2025年浙江分部利润表'!O6 -> 2194950 | U5: 1388214 | V5: ='2025年浙江分部利润表'!P6 -> 2153150.8 | W5: ='2025年浙江分部利润表'!Q6 -> 3059696 | X5: 2780645.8 | Y5: ='2025年浙江分部利润表'!R6 -> 3020394.8 | Z5: ='2025年浙江分部利润表'!S6 -> 3664704 | AA5: 2729408.4 | AB5: ='2025年浙江分部利润表'!T6 -> 3721151.4 | AC5: ='2025年浙江分部利润表'!U6 -> 2686850 | AD5: 3041280.1 | AE5: ='2025年浙江分部利润表'!V6 -> 2340233.6 | AF5: ='2025年浙江分部利润表'!W6 -> 2979000 | AG5: 2600701.5 | AH5: ='2025年浙江分部利润表'!X6 -> 2814572.7 | AI5: ='2025年浙江分部利润表'!Y6 -> 5599350 | AJ5: 5570531.3 | AK5: ='2025年浙江分部利润表'!Z6 -> 4295169.2 | AL5: =SUMIF($B$3:AK4,AL$3,$B5:$AK5) -> 33684550 | AM5: =SUMIF($B$3:AK4,AM$3,$B5:$AK5) -> 27810855 | AN5: =SUMIF($B$3:AK4,AN$3,$B5:$AK5) -> 31935550
A6: 上海分部 | B6: ='2025年上海分部利润表'!C6 -> 1107000 | C6: 2942728 | D6: ='2025年上海分部利润表'!D6 -> 2193436.5 | E6: ='2025年上海分部利润表'!E6 -> 1826000 | F6: 939982.31 | G6: ='2025年上海分部利润表'!F6 -> 1523858.9 | H6: ='2025年上海分部利润表'!G6 -> 3300200 | I6: 2621394.6 | J6: ='2025年上海分部利润表'!H6 -> 3225443.7 | K6: ='2025年上海分部利润表'!I6 -> 4218200 | L6: 3768174.1 | M6: ='2025年上海分部利润表'!J6 -> 3850614.7 | N6: ='2025年上海分部利润表'!K6 -> 3815800 | O6: 3026870.2 | P6: ='2025年上海分部利润表'!L6 -> 1812935.8 | Q6: ='2025年上海分部利润表'!M6 -> 3800500 | R6: 3179086.7 | S6: ='2025年上海分部利润表'!N6 -> 2841582.4 | T6: ='2025年上海分部利润表'!O6 -> 3986520 | U6: 3484218.7 | V6: ='2025年上海分部利润表'!P6 -> 2029987.8 | W6: ='2025年上海分部利润表'!Q6 -> 4575627.8 | X6: 3621668.3 | Y6: ='2025年上海分部利润表'!R6 -> 2538407.1 | Z6: ='2025年上海分部利润表'!S6 -> 5227978.2 | AA6: 4068860.3 | AB6: ='2025年上海分部利润表'!T6 -> 4157487.4 | AC6: ='2025年上海分部利润表'!U6 -> 3221313 | AD6: 2096903 | AE6: ='2025年上海分部利润表'!V6 -> 2466210.1 | AF6: ='2025年上海分部利润表'!W6 -> 4178540 | AG6: 3130654.4 | AH6: ='2025年上海分部利润表'!X6 -> 2502821.6 | AI6: ='2025年上海分部利润表'!Y6 -> 6218296 | AJ6: 6584204.5 | AK6: ='2025年上海分部利润表'!Z6 -> 3686699 | AL6: =SUMIF($B$3:AK5,AL$3,$B6:$AK6) -> 45475975 | AM6: =SUMIF($B$3:AK5,AM$3,$B6:$AK6) -> 39464745 | AN6: =SUMIF($B$3:AK5,AN$3,$B6:$AK6) -> 32829485
A7: 赣皖区域 | B7: ='2025年赣皖区域利润表'!C6 -> 844206.84 | C7: 1798560.5 | D7: ='2025年赣皖区域利润表'!D6 -> 1347836.9 | E7: ='2025年赣皖区域利润表'!E6 -> 862515 | F7: 457734.38 | G7: ='2025年赣皖区域利润表'!F6 -> 709642.25 | H7: ='2025年赣皖区域利润表'!G6 -> 1375789.3 | I7: 1003077 | J7: ='2025年赣皖区域利润表'!H6 -> 748312.86 | K7: ='2025年赣皖区域利润表'!I6 -> 1738544 | L7: 1007138.9 | M7: ='2025年赣皖区域利润表'!J6 -> 1364551 | N7: ='2025年赣皖区域利润表'!K6 -> 1499640.5 | O7: 1087571 | P7: ='2025年赣皖区域利润表'!L6 -> 741495.78 | Q7: ='2025年赣皖区域利润表'!M6 -> 1695080.5 | R7: 1001681.3 | S7: ='2025年赣皖区域利润表'!N6 -> 1166717.6 | T7: ='2025年赣皖区域利润表'!O6 -> 1733323 | U7: 1233325.3 | V7: ='2025年赣皖区域利润表'!P6 -> 949145.46 | W7: ='2025年赣皖区域利润表'!Q6 -> 1740369.5 | X7: 1470447.3 | Y7: ='2025年赣皖区域利润表'!R6 -> 1278690.5 | Z7: ='2025年赣皖区域利润表'!S6 -> 2498710.1 | AA7: 1433756.1 | AB7: ='2025年赣皖区域利润表'!T6 -> 1409395 | AC7: ='2025年赣皖区域利润表'!U6 -> 1691063.6 | AD7: 1064738.6 | AE7: ='2025年赣皖区域利润表'!V6 -> 1190690.3 | AF7: ='2025年赣皖区域利润表'!W6 -> 2064346.3 | AG7: 1220051.4 | AH7: ='2025年赣皖区域利润表'!X6 -> 1012299.1 | AI7: ='2025年赣皖区域利润表'!Y6 -> 3005004.3 | AJ7: 2083895.6 | AK7: ='2025年赣皖区域利润表'!Z6 -> 1575318.9 | AL7: =SUMIF($B$3:AK6,AL$3,$B7:$AK7) -> 20748593 | AM7: =SUMIF($B$3:AK6,AM$3,$B7:$AK7) -> 14861978 | AN7: =SUMIF($B$3:AK6,AN$3,$B7:$AK7) -> 13494096
A8: 1中心总监费用 | B8: ='2025年中心利润表 '!C6 -> 0 | C8: 0 | D8: ='2025年中心利润表 '!D6 -> 81119.48 | E8: ='2025年中心利润表 '!E6 -> 0 | F8: 0 | G8: ='2025年中心利润表 '!F6 -> 10464.61 | H8: ='2025年中心利润表 '!G6 -> 0 | I8: 0 | J8: ='2025年中心利润表 '!H6 -> 20687.61 | K8: ='2025年中心利润表 '!I6 -> 0 | L8: 0 | M8: ='2025年中心利润表 '!J6 -> 29819.47 | N8: ='2025年中心利润表 '!K6 -> 0 | O8: 0 | P8: ='2025年中心利润表 '!L6 -> 12482.3 | Q8: ='2025年中心利润表 '!M6 -> 0 | R8: 0 | S8: ='2025年中心利润表 '!N6 -> 18622.78 | T8: ='2025年中心利润表 '!O6 -> 0 | U8: 22949.092 | V8: ='2025年中心利润表 '!P6 -> 12631.64 | W8: ='2025年中心利润表 '!Q6 -> 0 | X8: 12637.168 | Y8: ='2025年中心利润表 '!R6 -> 2849.56 | Z8: ='2025年中心利润表 '!S6 -> 0 | AA8: 17894.227 | AB8: ='2025年中心利润表 '!T6 -> 11571.24 | AC8: ='2025年中心利润表 '!U6 -> 0 | AD8: 0 | AE8: ='2025年中心利润表 '!V6 -> 0 | AF8: ='2025年中心利润表 '!W6 -> 0 | AG8: 0 | AH8: ='2025年中心利润表 '!X6 -> 12910.62 | AI8: ='2025年中心利润表 '!Y6 -> 0 | AJ8: 6639.027 | AK8: ='2025年中心利润表 '!Z6 -> 5973.45 | AL8: =SUMIF($B$3:AK7,AL$3,$B8:$AK8) -> 0 | AM8: =SUMIF($B$3:AK7,AM$3,$B8:$AK8) -> 60119.514 | AN8: =SUMIF($B$3:AK7,AN$3,$B8:$AK8) -> 219132.76
A9: 合计 | B9: =SUM(B4:B8) -> 3986706.8 | C9: =SUM(C4:C8) -> 8800821.6 | D9: =SUM(D4:D8) -> 8761368.5 | E9: =SUM(E4:E8) -> 4955115 | F9: =SUM(F4:F8) -> 2454424.1 | G9: =SUM(G4:G8) -> 5436073.3 | H9: =SUM(H4:H8) -> 8700489.3 | I9: =SUM(I4:I8) -> 6045294.6 | ... AK9: =SUM(AK4:AK8) -> 13174327 | AL9: =IF(ROUND(SUMIF($B3:AK$8,AL$3,$B9:$AK9),2)=ROUND(SUM(AL4:AL8),2),ROUND(SUMIF($B3:AK$8,AL$3,$B9:$AK9),2),"Check") -> 1.2212339e+08 | AM9: =IF(ROUND(SUMIF($B3:AK$8,AM$3,$B9:$AK9),2)=ROUND(SUM(AM4:AM8),2),ROUND(SUMIF($B3:AK$8,AM$3,$B9:$AK9),2),"Check") -> 1.0125309e+08 | AN9: =IF(ROUND(SUMIF($B3:AK$8,AN$3,$B9:$AK9),2)=ROUND(SUM(AN4:AN8),2),ROUND(SUMIF($B3:AK$8,AN$3,$B9:$AK9),2),"Check") -> 1.0687889e+08
A11: 区域 | B11: 1月 | E11: 2月 | H11: 3月 | K11: 4月 | N11: 5月 | Q11: 6月 | T11: 7月 | W11: 8月 | Z11: 9月 | AC11: 10月 | AF11: 11月 | AI11: 12月 | AL11: 合计
B12: 预算净利 | C12: 24年同期实际 | D12: 实际净利 | E12: 预算净利 | F12: 24年同期实际 | G12: 实际净利 | H12: 预算净利 | I12: 24年同期实际 | J12: 实际净利 | K12: 预算净利 | L12: 24年同期实际 | M12: 实际净利 | N12: 预算净利 | O12: 24年同期实际 | P12: 实际净利 | Q12: 预算净利 | R12: 24年同期实际 | S12: 实际净利 | T12: 预算净利 | U12: 24年同期实际 | V12: 实际净利 | W12: 预算净利 | X12: 24年同期实际 | Y12: 实际净利 | Z12: 预算净利 | AA12: 24年同期实际 | AB12: 实际净利 | AC12: 预算净利 | AD12: 24年同期实际 | AE12: 实际净利 | AF12: 预算净利 | AG12: 24年同期实际 | AH12: 实际净利 | AI12: 预算净利 | AJ12: 24年同期实际 | AK12: 实际净利 | AL12: 预算净利 | AM12: 24年同期实际 | AN12: 实际净利
A13: 江苏分部 | B13: ='2025年江苏分部利润表'!C263 -> -35998.906 | C13: 195425.55 | D13: ='2025年江苏分部利润表'!D263 -> 374793.67 | E13: ='2025年江苏分部利润表'!E263 -> 4922.012 | F13: 1758.5599 | G13: ='2025年江苏分部利润表'!F263 -> 210007.03 | H13: ='2025年江苏分部利润表'!G263 -> 68700.694 | I13: 74229.994 | J13: ='2025年江苏分部利润表'!H263 -> 191036.68 | K13: ='2025年江苏分部利润表'!I263 -> 115713.75 | L13: 67104.467 | M13: ='2025年江苏分部利润表'!J263 -> 308362.78 | N13: ='2025年江苏分部利润表'!K263 -> 88941.37 | O13: 104695.28 | P13: ='2025年江苏分部利润表'!L263 -> 215840.15 | Q13: ='2025年江苏分部利润表'!M263 -> 161021.46 | R13: 109033.75 | S13: ='2025年江苏分部利润表'!N263 -> 341174.48 | T13: ='2025年江苏分部利润表'!O263 -> 188428.17 | U13: 172924.77 | V13: ='2025年江苏分部利润表'!P263 -> 251237.75 | W13: ='2025年江苏分部利润表'!Q263 -> 150857.06 | X13: 220602.39 | Y13: ='2025年江苏分部利润表'!R263 -> 268253.22 | Z13: ='2025年江苏分部利润表'!S263 -> 234551.16 | AA13: 270301.82 | AB13: ='2025年江苏分部利润表'!T263 -> 460909 | AC13: ='2025年江苏分部利润表'!U263 -> 122217.84 | AD13: 147891.71 | AE13: ='2025年江苏分部利润表'!V263 -> 261060.5 | AF13: ='2025年江苏分部利润表'!W263 -> 190494.74 | AG13: 189470.49 | AH13: ='2025年江苏分部利润表'!X263 -> 298202.12 | AI13: ='2025年江苏分部利润表'!Y263 -> 525986.93 | AJ13: 490380.3 | AK13: ='2025年江苏分部利润表'!Z263 -> 590435.63 | AL13: =SUMIF($B$12:AK12,AL$12,$B13:$AK13) -> 1815836.3 | AM13: =SUMIF($B$12:AK12,AM$12,$B13:$AK13) -> 2043819.1 | AN13: =SUMIF($B$12:AK12,AN$12,$B13:$AK13) -> 3771313
A14: 浙江分部 | B14: ='2025年浙江分部利润表'!C263 -> -10700.666 | C14: 168110.41 | D14: ='2025年浙江分部利润表'!D263 -> 242231.09 | E14: ='2025年浙江分部利润表'!E263 -> 28309.249 | F14: 24020.712 | G14: ='2025年浙江分部利润表'!F263 -> 148009.2 | H14: ='2025年浙江分部利润表'!G263 -> 146442.68 | I14: 98486.204 | J14: ='2025年浙江分部利润表'!H263 -> 257658.82 | K14: ='2025年浙江分部利润表'!I263 -> 157069.51 | L14: 126772.95 | M14: ='2025年浙江分部利润表'!J263 -> 238152.41 | N14: ='2025年浙江分部利润表'!K263 -> 185095.24 | O14: 54806.128 | P14: ='2025年浙江分部利润表'!L263 -> 236799.47 | Q14: ='2025年浙江分部利润表'!M263 -> 199869.06 | R14: 148730.56 | S14: ='2025年浙江分部利润表'!N263 -> 293683.55 | T14: ='2025年浙江分部利润表'!O263 -> 52040.946 | U14: 128101.79 | V14: ='2025年浙江分部利润表'!P263 -> 202467.84 | W14: ='2025年浙江分部利润表'!Q263 -> 210383.21 | X14: 430278.5 | Y14: ='2025年浙江分部利润表'!R263 -> 321456.86 | Z14: ='2025年浙江分部利润表'!S263 -> 229663.48 | AA14: 341502.04 | AB14: ='2025年浙江分部利润表'!T263 -> 480667.58 | AC14: ='2025年浙江分部利润表'!U263 -> 149115.67 | AD14: 356255.91 | AE14: ='2025年浙江分部利润表'!V263 -> 356088.61 | AF14: ='2025年浙江分部利润表'!W263 -> 206122.96 | AG14: 262567.3 | AH14: ='2025年浙江分部利润表'!X263 -> 409662.21 | AI14: ='2025年浙江分部利润表'!Y263 -> 706966.16 | AJ14: 776097.07 | AK14: ='2025年浙江分部利润表'!Z263 -> 642245.05 | AL14: =SUMIF($B$12:AK13,AL$12,$B14:$AK14) -> 2260377.5 | AM14: =SUMIF($B$12:AK13,AM$12,$B14:$AK14) -> 2915729.6 | AN14: =SUMIF($B$12:AK13,AN$12,$B14:$AK14) -> 3829122.7
A15: 上海分部 | B15: ='2025年上海分部利润表'!C263 -> -107697.31 | C15: 338485.51 | D15: ='2025年上海分部利润表'!D263 -> 263950.01 | E15: ='2025年上海分部利润表'!E263 -> 78164.49 | F15: 34440.646 | G15: ='2025年上海分部利润表'!F263 -> 224899.54 | H15: ='2025年上海分部利润表'!G263 -> 267281.5 | I15: 248020.21 | J15: ='2025年上海分部利润表'!H263 -> 441132.29 | K15: ='2025年上海分部利润表'!I263 -> 476749.98 | L15: 412791.16 | M15: ='2025年上海分部利润表'!J263 -> 483311.62 | N15: ='2025年上海分部利润表'!K263 -> 373734.63 | O15: 330920.11 | P15: ='2025年上海分部利润表'!L263 -> 249248.8 | Q15: ='2025年上海分部利润表'!M263 -> 362498.94 | R15: 335690.99 | S15: ='2025年上海分部利润表'!N263 -> 438192.76 | T15: ='2025年上海分部利润表'!O263 -> 306559.91 | U15: 486536.23 | V15: ='2025年上海分部利润表'!P263 -> 325454.58 | W15: ='2025年上海分部利润表'!Q263 -> 458525.46 | X15: 530868.17 | Y15: ='2025年上海分部利润表'!R263 -> 488285.28 | Z15: ='2025年上海分部利润表'!S263 -> 568259.29 | AA15: 503556.66 | AB15: ='2025年上海分部利润表'!T263 -> 740815.08 | AC15: ='2025年上海分部利润表'!U263 -> 217650.09 | AD15: 332455.74 | AE15: ='2025年上海分部利润表'!V263 -> 387192.84 | AF15: ='2025年上海分部利润表'!W263 -> 417019.95 | AG15: 381189.7 | AH15: ='2025年上海分部利润表'!X263 -> 314474.28 | AI15: ='2025年上海分部利润表'!Y263 -> 786693.62 | AJ15: 1039667.2 | AK15: ='2025年上海分部利润表'!Z263 -> 620728.41 | AL15: =SUMIF($B$12:AK14,AL$12,$B15:$AK15) -> 4205440.5 | AM15: =SUMIF($B$12:AK14,AM$12,$B15:$AK15) -> 4974622.3 | AN15: =SUMIF($B$12:AK14,AN$12,$B15:$AK15) -> 4977685.5
A16: 赣皖区域 | B16: ='2025年赣皖区域利润表'!C263 -> 28385.02 | C16: 155935.15 | D16: ='2025年赣皖区域利润表'!D263 -> 203946.75 | E16: ='2025年赣皖区域利润表'!E263 -> 14933.286 | F16: -35150.085 | G16: ='2025年赣皖区域利润表'!F263 -> 66296.761 | H16: ='2025年赣皖区域利润表'!G263 -> 77576.08 | I16: -15348.141 | J16: ='2025年赣皖区域利润表'!H263 -> 6519.5442 | K16: ='2025年赣皖区域利润表'!I263 -> 167572.61 | L16: -11596.191 | M16: ='2025年赣皖区域利润表'!J263 -> 188278.89 | N16: ='2025年赣皖区域利润表'!K263 -> 122534.39 | O16: -27051.04 | P16: ='2025年赣皖区域利润表'!L263 -> 38301.917 | Q16: ='2025年赣皖区域利润表'!M263 -> 164008.1 | R16: -33985.336 | S16: ='2025年赣皖区域利润表'!N263 -> 175806.16 | T16: ='2025年赣皖区域利润表'!O263 -> 174993.24 | U16: 24834.659 | V16: ='2025年赣皖区域利润表'!P263 -> 150623.35 | W16: ='2025年赣皖区域利润表'!Q263 -> 167896.32 | X16: 111484.92 | Y16: ='2025年赣皖区域利润表'!R263 -> 195980.67 | Z16: ='2025年赣皖区域利润表'!S263 -> 282779.5 | AA16: 70491.287 | AB16: ='2025年赣皖区域利润表'!T263 -> 206798.58 | AC16: ='2025年赣皖区域利润表'!U263 -> 146567.41 | AD16: -10086.552 | AE16: ='2025年赣皖区域利润表'!V263 -> 214034.25 | AF16: ='2025年赣皖区域利润表'!W263 -> 244024.15 | AG16: 85390.763 | AH16: ='2025年赣皖区域利润表'!X263 -> 152165.2 | AI16: ='2025年赣皖区域利润表'!Y263 -> 432847.69 | AJ16: 272419.3 | AK16: ='2025年赣皖区域利润表'!Z263 -> 300126.77 | AL16: =SUMIF($B$12:AK15,AL$12,$B16:$AK16) -> 2024117.8 | AM16: =SUMIF($B$12:AK15,AM$12,$B16:$AK16) -> 587338.74 | AN16: =SUMIF($B$12:AK15,AN$12,$B16:$AK16) -> 1898878.8
A17: 1中心总监费用 | B17: ='2025年中心利润表 '!C263 -> -44818.64 | C17: -65461.455 | D17: ='2025年中心利润表 '!D263 -> -20457.675 | E17: ='2025年中心利润表 '!E263 -> -31652.8 | F17: -53686.084 | G17: ='2025年中心利润表 '!F263 -> -42905.844 | H17: ='2025年中心利润表 '!G263 -> -42310.19 | I17: -72907.66 | J17: ='2025年中心利润表 '!H263 -> 50374.048 | K17: ='2025年中心利润表 '!I263 -> -46685.83 | L17: -34657.503 | M17: ='2025年中心利润表 '!J263 -> -22108.105 | N17: ='2025年中心利润表 '!K263 -> -44255.84 | O17: -45424.378 | P17: ='2025年中心利润表 '!L263 -> -4723.9119 | Q17: ='2025年中心利润表 '!M263 -> -46437.06 | R17: -47604.856 | S17: ='2025年中心利润表 '!N263 -> -3145.9164 | T17: ='2025年中心利润表 '!O263 -> -48740.24 | U17: -47817.125 | V17: ='2025年中心利润表 '!P263 -> -8631.7206 | W17: ='2025年中心利润表 '!Q263 -> -52371.55 | X17: -52718.158 | Y17: ='2025年中心利润表 '!R265 -> -7390.9408 | Z17: ='2025年中心利润表 '!S263 -> -61330.37 | AA17: -45985.22 | AB17: ='2025年中心利润表 '!T263 -> -16701.197 | AC17: ='2025年中心利润表 '!U263 -> -52458.11 | AD17: -50854.778 | AE17: ='2025年中心利润表 '!V263 -> -8644.85 | AF17: ='2025年中心利润表 '!W263 -> -55890.62 | AG17: -59095.019 | AH17: ='2025年中心利润表 '!X263 -> -6380.4009 | AI17: ='2025年中心利润表 '!Y263 -> -72508.75 | AJ17: -52353.118 | AK17: ='2025年中心利润表 '!Z263 -> -18237.458 | AL17: =SUMIF($B$12:AK16,AL$12,$B17:$AK17) -> -599460 | AM17: =SUMIF($B$12:AK16,AM$12,$B17:$AK17) -> -628565.36 | AN17: =SUMIF($B$12:AK16,AN$12,$B17:$AK17) -> -108953.97
A18: 合计 | B18: =SUM(B13:B17) -> -170830.51 | C18: =SUM(C13:C17) -> 792495.17 | D18: =SUM(D13:D17) -> 1064463.9 | E18: =SUM(E13:E17) -> 94676.237 | F18: =SUM(F13:F17) -> -28616.251 | G18: =SUM(G13:G17) -> 606306.68 | H18: =SUM(H13:H17) -> 517690.76 | I18: =SUM(I13:I17) -> 332480.6 | ... AK18: =SUM(AK13:AK17) -> 2135298.4 | AL18: =IF(ROUND(SUMIF($B$12:AK17,AL$12,$B18:$AK18),2)=ROUND(SUM(AL13:AL17),2),ROUND(SUMIF($B$12:AK17,AL$12,$B18:$AK18),2),"Check") -> 9706312.1 | AM18: =IF(ROUND(SUMIF($B$12:AK17,AM$12,$B18:$AK18),2)=ROUND(SUM(AM13:AM17),2),ROUND(SUMIF($B$12:AK17,AM$12,$B18:$AK18),2),"Check") -> 9892944.3 | AN18: =IF(ROUND(SUMIF($B$12:AK17,AN$12,$B18:$AK18),2)=ROUND(SUM(AN13:AN17),2),ROUND(SUMIF($B$12:AK17,AN$12,$B18:$AK18),2),"Check") -> 14368046
A19: 备注：
A20: 本表收入为扣除返利后收入，利润为分红前利润，与销售1中心利润表中收入及净利润数据相等；
A21: 1中心总监费用：是指包含该总监报销与业务相关的差旅、招待、样品费等发生的一切费用，也包含其工资、社保及宁波味觉发生的残疾人工资及社保等；
A22: 目的：主要是表明该BU下总体净利完成情况（即该公司组织目标净利的完成情况）
A23: 编制说明： | B23: =索引!C3 -> 1、分部及区域的预算净利及实际净利，数据来源为本文件中分部利润表、区域利润表中的预算净利润和实际净利润； 2、总监费用，预算净利数据来源为2025年中心利润表中的预算净利润及预算销售费用；实际净利为2025年中心利润表中的实际销售费用+计入到美鑫的总监工资及社保公积金费用之和； 3、因为净利简表中加了总监在美鑫的费用，所以净利简表中的汇总金额和2025年销售1中心利润表汇总有差异，差额为额外增加的这部分。
W24: 0 | Y24: 0 | Z24: 0 | AB24: 0 | AC24: 0 | AE24: 0 | AF24: 0 | AH24: 0 | AI24: 0 | AK24: 0

Sheet 2025年销售1中心利润表
A1: 宁波味觉销售1中心利润表
A2: 46021 | AB2: 会企01表
A3: 编制单位：江苏美鑫食品科技有限公司 | AB3: 单位：元
A4: 项 目 | B4: 行次 | C4: 45658 | E4: 45689 | G4: 45717 | I4: 45748 | K4: 45778 | M4: 45809 | O4: 45839 | Q4: 45870 | S4: 45901 | U4: 45931 | W4: 45962 | Y4: 45992 | AA4: 2025年合计 | AD4: 2025年合计逆向验证 | AF4: 检验结果
C5: 预算数 | D5: 本月实际 | E5: 预算数 | F5: 本月实际 | G5: 预算数 | H5: 本月实际 | I5: 预算数 | J5: 本月实际 | K5: 预算数 | L5: 本月实际 | M5: 预算数 | N5: 本月实际 | O5: 预算数 | P5: 本月实际 | Q5: 预算数 | R5: 本月实际 | S5: 预算数 | T5: 本月实际 | U5: 预算数 | V5: 本月实际 | W5: 预算数 | X5: 本月实际 | Y5: 预算数 | Z5: 本月实际 | AA5: 预算数 | AB5: 本年实际 | AD5: 预算数 | AE5: 本月实际 | AF5: 预算数 | AG5: 本月实际
A6: 一、营业收入 | B6: 1 | C6: =SUM(C7:C13,C15,-C14) -> 3986706.8 | D6: =SUM(D7:D13,D15,-D14) -> 8761368.5 | E6: =SUM(E7:E13,E15,-E14) -> 4955115 | F6: =SUM(F7:F13,F15,-F14) -> 5436073.3 | G6: =SUM(G7:G13,G15,-G14) -> 8700489.3 | H6: =SUM(H7:H13,H15,-H14) -> 7554667 | I6: =SUM(I7:I13,I15,-I14) -> 10237244 | J6: =SUM(J7:J13,J15,-J14) -> 10564504 | ... Z6: =SUM(Z7:Z13,Z15,-Z14) -> 13174327 | AA6: =C6+E6+G6+I6+K6+M6+O6+Q6+S6+U6+W6+Y6 -> 1.2212339e+08 | AB6: =D6+F6+H6+J6+L6+N6+P6+R6+T6+V6+X6+Z6 -> 1.0687889e+08 | AD6: =SUMIF($C$5:$Z$5,$AD$5,C6:Z6) -> 1.2212339e+08 | AE6: =SUMIF($C$5:$Z$5,$AD$5,D6:AA6) -> 1.0687889e+08 | AF6: =AA6-AD6 -> 0 | AG6: =AB6-AE6 -> 0 | AH6: =SUM('[1]2024年全面预算利润表 (销售1中心)2.8亿'!E10:H10) -> 36318373
A7: 中式汤底 | C7: ='2025年中心利润表 '!C7+'2025年江苏分部利润表'!C7+'2025年浙江分部利润表'!C7+'2025年上海分部利润表'!C7+'2025年赣皖区域利润表'!C7 -> 0 | D7: ='2025年中心利润表 '!D7+'2025年江苏分部利润表'!D7+'2025年浙江分部利润表'!D7+'2025年上海分部利润表'!D7+'2025年赣皖区域利润表'!D7 -> 2200703.1 | E7: ='2025年中心利润表 '!E7+'2025年江苏分部利润表'!E7+'2025年浙江分部利润表'!E7+'2025年上海分部利润表'!E7+'2025年赣皖区域利润表'!E7 -> 0 | F7: ='2025年中心利润表 '!F7+'2025年江苏分部利润表'!F7+'2025年浙江分部利润表'!F7+'2025年上海分部利润表'!F7+'2025年赣皖区域利润表'!F7 -> 1492040.9 | G7: ='2025年中心利润表 '!G7+'2025年江苏分部利润表'!G7+'2025年浙江分部利润表'!G7+'2025年上海分部利润表'!G7+'2025年赣皖区域利润表'!G7 -> 0 | H7: ='2025年中心利润表 '!H7+'2025年江苏分部利润表'!H7+'2025年浙江分部利润表'!H7+'2025年上海分部利润表'!H7+'2025年赣皖区域利润表'!H7 -> 2480280.4 | I7: ='2025年中心利润表 '!I7+'2025年江苏分部利润表'!I7+'2025年浙江分部利润表'!I7+'2025年上海分部利润表'!I7+'2025年赣皖区域利润表'!I7 -> 0 | J7: ='2025年中心利润表 '!J7+'2025年江苏分部利润表'!J7+'2025年浙江分部利润表'!J7+'2025年上海分部利润表'!J7+'2025年赣皖区域利润表'!J7 -> 3379438.1 | ... Z7: ='2025年中心利润表 '!Z7+'2025年江苏分部利润表'!Z7+'2025年浙江分部利润表'!Z7+'2025年上海分部利润表'!Z7+'2025年赣皖区域利润表'!Z7 -> 3645704.4 | AA7: =C7+E7+G7+I7+K7+M7+O7+Q7+S7+U7+W7+Y7 -> 0 | AB7: =D7+F7+H7+J7+L7+N7+P7+R7+T7+V7+X7+Z7 -> 31715084 | AD7: =SUMIF($C$5:$Z$5,$AD$5,C7:Z7) -> 0 | AE7: =SUMIF($C$5:$Z$5,$AD$5,D7:AA7) -> 31715084 | AF7: =AA7-AD7 -> 0 | AG7: =AB7-AE7 -> 0 | AH7: =SUM('[1]2024年全面预算利润表 (销售1中心)2.8亿'!E11:H11) -> 0
A8: 酱料 | C8: ='2025年中心利润表 '!C8+'2025年江苏分部利润表'!C8+'2025年浙江分部利润表'!C8+'2025年上海分部利润表'!C8+'2025年赣皖区域利润表'!C8 -> 0 | D8: ='2025年中心利润表 '!D8+'2025年江苏分部利润表'!D8+'2025年浙江分部利润表'!D8+'2025年上海分部利润表'!D8+'2025年赣皖区域利润表'!D8 -> 3250736.1 | E8: ='2025年中心利润表 '!E8+'2025年江苏分部利润表'!E8+'2025年浙江分部利润表'!E8+'2025年上海分部利润表'!E8+'2025年赣皖区域利润表'!E8 -> 0 | F8: ='2025年中心利润表 '!F8+'2025年江苏分部利润表'!F8+'2025年浙江分部利润表'!F8+'2025年上海分部利润表'!F8+'2025年赣皖区域利润表'!F8 -> 2154126 | G8: ='2025年中心利润表 '!G8+'2025年江苏分部利润表'!G8+'2025年浙江分部利润表'!G8+'2025年上海分部利润表'!G8+'2025年赣皖区域利润表'!G8 -> 0 | H8: ='2025年中心利润表 '!H8+'2025年江苏分部利润表'!H8+'2025年浙江分部利润表'!H8+'2025年上海分部利润表'!H8+'2025年赣皖区域利润表'!H8 -> 3353359 | I8: ='2025年中心利润表 '!I8+'2025年江苏分部利润表'!I8+'2025年浙江分部利润表'!I8+'2025年上海分部利润表'!I8+'2025年赣皖区域利润表'!I8 -> 0 | J8: ='2025年中心利润表 '!J8+'2025年江苏分部利润表'!J8+'2025年浙江分部利润表'!J8+'2025年上海分部利润表'!J8+'2025年赣皖区域利润表'!J8 -> 3782684 | ... Z8: ='2025年中心利润表 '!Z8+'2025年江苏分部利润表'!Z8+'2025年浙江分部利润表'!Z8+'2025年上海分部利润表'!Z8+'2025年赣皖区域利润表'!Z8 -> 5165091 | AA8: =C8+E8+G8+I8+K8+M8+O8+Q8+S8+U8+W8+Y8 -> 0 | AB8: =D8+F8+H8+J8+L8+N8+P8+R8+T8+V8+X8+Z8 -> 40157217 | AD8: =SUMIF($C$5:$Z$5,$AD$5,C8:Z8) -> 0 | AE8: =SUMIF($C$5:$Z$5,$AD$5,D8:AA8) -> 40157217 | AF8: =AA8-AD8 -> 0 | AG8: =AB8-AE8 -> 0 | AH8: =SUM('[1]2024年全面预算利润表 (销售1中心)2.8亿'!E12:H12) -> 0
A9: 川味底料 | C9: ='2025年中心利润表 '!C9+'2025年江苏分部利润表'!C9+'2025年浙江分部利润表'!C9+'2025年上海分部利润表'!C9+'2025年赣皖区域利润表'!C9 -> 0 | D9: ='2025年中心利润表 '!D9+'2025年江苏分部利润表'!D9+'2025年浙江分部利润表'!D9+'2025年上海分部利润表'!D9+'2025年赣皖区域利润表'!D9 -> 2575914.4 | E9: ='2025年中心利润表 '!E9+'2025年江苏分部利润表'!E9+'2025年浙江分部利润表'!E9+'2025年上海分部利润表'!E9+'2025年赣皖区域利润表'!E9 -> 0 | F9: ='2025年中心利润表 '!F9+'2025年江苏分部利润表'!F9+'2025年浙江分部利润表'!F9+'2025年上海分部利润表'!F9+'2025年赣皖区域利润表'!F9 -> 1516933.9 | G9: ='2025年中心利润表 '!G9+'2025年江苏分部利润表'!G9+'2025年浙江分部利润表'!G9+'2025年上海分部利润表'!G9+'2025年赣皖区域利润表'!G9 -> 0 | H9: ='2025年中心利润表 '!H9+'2025年江苏分部利润表'!H9+'2025年浙江分部利润表'!H9+'2025年上海分部利润表'!H9+'2025年赣皖区域利润表'!H9 -> 1354693.2 | I9: ='2025年中心利润表 '!I9+'2025年江苏分部利润表'!I9+'2025年浙江分部利润表'!I9+'2025年上海分部利润表'!I9+'2025年赣皖区域利润表'!I9 -> 0 | J9: ='2025年中心利润表 '!J9+'2025年江苏分部利润表'!J9+'2025年浙江分部利润表'!J9+'2025年上海分部利润表'!J9+'2025年赣皖区域利润表'!J9 -> 2686716.9 | ... Z9: ='2025年中心利润表 '!Z9+'2025年江苏分部利润表'!Z9+'2025年浙江分部利润表'!Z9+'2025年上海分部利润表'!Z9+'2025年赣皖区域利润表'!Z9 -> 4042992.6 | AA9: =C9+E9+G9+I9+K9+M9+O9+Q9+S9+U9+W9+Y9 -> 0 | AB9: =D9+F9+H9+J9+L9+N9+P9+R9+T9+V9+X9+Z9 -> 29180682 | AD9: =SUMIF($C$5:$Z$5,$AD$5,C9:Z9) -> 0 | AE9: =SUMIF($C$5:$Z$5,$AD$5,D9:AA9) -> 29180682 | AF9: =AA9-AD9 -> 0 | AG9: =AB9-AE9 -> 0 | AH9: =SUM('[1]2024年全面预算利润表 (销售1中心)2.8亿'!E13:H13) -> 0
A10: 调味汁 | C10: ='2025年中心利润表 '!C10+'2025年江苏分部利润表'!C10+'2025年浙江分部利润表'!C10+'2025年上海分部利润表'!C10+'2025年赣皖区域利润表'!C10 -> 0 | D10: ='2025年中心利润表 '!D10+'2025年江苏分部利润表'!D10+'2025年浙江分部利润表'!D10+'2025年上海分部利润表'!D10+'2025年赣皖区域利润表'!D10 -> 385252.79 | E10: ='2025年中心利润表 '!E10+'2025年江苏分部利润表'!E10+'2025年浙江分部利润表'!E10+'2025年上海分部利润表'!E10+'2025年赣皖区域利润表'!E10 -> 0 | F10: ='2025年中心利润表 '!F10+'2025年江苏分部利润表'!F10+'2025年浙江分部利润表'!F10+'2025年上海分部利润表'!F10+'2025年赣皖区域利润表'!F10 -> 159188.91 | G10: ='2025年中心利润表 '!G10+'2025年江苏分部利润表'!G10+'2025年浙江分部利润表'!G10+'2025年上海分部利润表'!G10+'2025年赣皖区域利润表'!G10 -> 0 | H10: ='2025年中心利润表 '!H10+'2025年江苏分部利润表'!H10+'2025年浙江分部利润表'!H10+'2025年上海分部利润表'!H10+'2025年赣皖区域利润表'!H10 -> 223817.74 | I10: ='2025年中心利润表 '!I10+'2025年江苏分部利润表'!I10+'2025年浙江分部利润表'!I10+'2025年上海分部利润表'!I10+'2025年赣皖区域利润表'!I10 -> 0 | J10: ='2025年中心利润表 '!J10+'2025年江苏分部利润表'!J10+'2025年浙江分部利润表'!J10+'2025年上海分部利润表'!J10+'2025年赣皖区域利润表'!J10 -> 407827.34 | ... Z10: ='2025年中心利润表 '!Z10+'2025年江苏分部利润表'!Z10+'2025年浙江分部利润表'!Z10+'2025年上海分部利润表'!Z10+'2025年赣皖区域利润表'!Z10 -> 282549.15 | AA10: =C10+E10+G10+I10+K10+M10+O10+Q10+S10+U10+W10+Y10 -> 0 | AB10: =D10+F10+H10+J10+L10+N10+P10+R10+T10+V10+X10+Z10 -> 3882508.7 | AD10: =SUMIF($C$5:$Z$5,$AD$5,C10:Z10) -> 0 | AE10: =SUMIF($C$5:$Z$5,$AD$5,D10:AA10) -> 3882508.7 | AF10: =AA10-AD10 -> 0 | AG10: =AB10-AE10 -> 0 | AH10: =SUM('[1]2024年全面预算利润表 (销售1中心)2.8亿'!E14:H14) -> 36318373
A11: 复合调味粉 | C11: ='2025年中心利润表 '!C11+'2025年江苏分部利润表'!C11+'2025年浙江分部利润表'!C11+'2025年上海分部利润表'!C11+'2025年赣皖区域利润表'!C11 -> 0 | D11: ='2025年中心利润表 '!D11+'2025年江苏分部利润表'!D11+'2025年浙江分部利润表'!D11+'2025年上海分部利润表'!D11+'2025年赣皖区域利润表'!D11 -> 296240.26 | E11: ='2025年中心利润表 '!E11+'2025年江苏分部利润表'!E11+'2025年浙江分部利润表'!E11+'2025年上海分部利润表'!E11+'2025年赣皖区域利润表'!E11 -> 0 | F11: ='2025年中心利润表 '!F11+'2025年江苏分部利润表'!F11+'2025年浙江分部利润表'!F11+'2025年上海分部利润表'!F11+'2025年赣皖区域利润表'!F11 -> 88575.066 | G11: ='2025年中心利润表 '!G11+'2025年江苏分部利润表'!G11+'2025年浙江分部利润表'!G11+'2025年上海分部利润表'!G11+'2025年赣皖区域利润表'!G11 -> 0 | H11: ='2025年中心利润表 '!H11+'2025年江苏分部利润表'!H11+'2025年浙江分部利润表'!H11+'2025年上海分部利润表'!H11+'2025年赣皖区域利润表'!H11 -> 110596.07 | I11: ='2025年中心利润表 '!I11+'2025年江苏分部利润表'!I11+'2025年浙江分部利润表'!I11+'2025年上海分部利润表'!I11+'2025年赣皖区域利润表'!I11 -> 0 | J11: ='2025年中心利润表 '!J11+'2025年江苏分部利润表'!J11+'2025年浙江分部利润表'!J11+'2025年上海分部利润表'!J11+'2025年赣皖区域利润表'!J11 -> 370984.69 | ... Z11: ='2025年中心利润表 '!Z11+'2025年江苏分部利润表'!Z11+'2025年浙江分部利润表'!Z11+'2025年上海分部利润表'!Z11+'2025年赣皖区域利润表'!Z11 -> 106234.98 | AA11: =C11+E11+G11+I11+K11+M11+O11+Q11+S11+U11+W11+Y11 -> 0 | AB11: =D11+F11+H11+J11+L11+N11+P11+R11+T11+V11+X11+Z11 -> 2557362.6 | AD11: =SUMIF($C$5:$Z$5,$AD$5,C11:Z11) -> 0 | AE11: =SUMIF($C$5:$Z$5,$AD$5,D11:AA11) -> 2557362.6 | AF11: =AA11-AD11 -> 0 | AG11: =AB11-AE11 -> 0 | AH11: =SUM('[1]2024年全面预算利润表 (销售1中心)2.8亿'!E15:H15) -> 0
A12: 团餐 | C12: ='2025年中心利润表 '!C12+'2025年江苏分部利润表'!C12+'2025年浙江分部利润表'!C12+'2025年上海分部利润表'!C12+'2025年赣皖区域利润表'!C12 -> 0 | D12: ='2025年中心利润表 '!D12+'2025年江苏分部利润表'!D12+'2025年浙江分部利润表'!D12+'2025年上海分部利润表'!D12+'2025年赣皖区域利润表'!D12 -> 7176.7404 | E12: ='2025年中心利润表 '!E12+'2025年江苏分部利润表'!E12+'2025年浙江分部利润表'!E12+'2025年上海分部利润表'!E12+'2025年赣皖区域利润表'!E12 -> 0 | F12: ='2025年中心利润表 '!F12+'2025年江苏分部利润表'!F12+'2025年浙江分部利润表'!F12+'2025年上海分部利润表'!F12+'2025年赣皖区域利润表'!F12 -> 15717.434 | G12: ='2025年中心利润表 '!G12+'2025年江苏分部利润表'!G12+'2025年浙江分部利润表'!G12+'2025年上海分部利润表'!G12+'2025年赣皖区域利润表'!G12 -> 0 | H12: ='2025年中心利润表 '!H12+'2025年江苏分部利润表'!H12+'2025年浙江分部利润表'!H12+'2025年上海分部利润表'!H12+'2025年赣皖区域利润表'!H12 -> 11089.57 | I12: ='2025年中心利润表 '!I12+'2025年江苏分部利润表'!I12+'2025年浙江分部利润表'!I12+'2025年上海分部利润表'!I12+'2025年赣皖区域利润表'!I12 -> 0 | J12: ='2025年中心利润表 '!J12+'2025年江苏分部利润表'!J12+'2025年浙江分部利润表'!J12+'2025年上海分部利润表'!J12+'2025年赣皖区域利润表'!J12 -> 7029.5472 | ... Z12: ='2025年中心利润表 '!Z12+'2025年江苏分部利润表'!Z12+'2025年浙江分部利润表'!Z12+'2025年上海分部利润表'!Z12+'2025年赣皖区域利润表'!Z12 -> 10082.891 | AA12: =C12+E12+G12+I12+K12+M12+O12+Q12+S12+U12+W12+Y12 -> 0 | AB12: =D12+F12+H12+J12+L12+N12+P12+R12+T12+V12+X12+Z12 -> 70994.923 | AD12: =SUMIF($C$5:$Z$5,$AD$5,C12:Z12) -> 0 | AE12: =SUMIF($C$5:$Z$5,$AD$5,D12:AA12) -> 70994.923 | AF12: =AA12-AD12 -> 0 | AG12: =AB12-AE12 -> 0 | AH12: =SUM('[1]2024年全面预算利润表 (销售1中心)2.8亿'!E16:H16) -> 29585058
A13: 预制菜 | C13: ='2025年中心利润表 '!C13+'2025年江苏分部利润表'!C13+'2025年浙江分部利润表'!C13+'2025年上海分部利润表'!C13+'2025年赣皖区域利润表'!C13 -> 0 | D13: ='2025年中心利润表 '!D13+'2025年江苏分部利润表'!D13+'2025年浙江分部利润表'!D13+'2025年上海分部利润表'!D13+'2025年赣皖区域利润表'!D13 -> 44491.173 | E13: ='2025年中心利润表 '!E13+'2025年江苏分部利润表'!E13+'2025年浙江分部利润表'!E13+'2025年上海分部利润表'!E13+'2025年赣皖区域利润表'!E13 -> 0 | F13: ='2025年中心利润表 '!F13+'2025年江苏分部利润表'!F13+'2025年浙江分部利润表'!F13+'2025年上海分部利润表'!F13+'2025年赣皖区域利润表'!F13 -> 8960.19 | G13: ='2025年中心利润表 '!G13+'2025年江苏分部利润表'!G13+'2025年浙江分部利润表'!G13+'2025年上海分部利润表'!G13+'2025年赣皖区域利润表'!G13 -> 0 | H13: ='2025年中心利润表 '!H13+'2025年江苏分部利润表'!H13+'2025年浙江分部利润表'!H13+'2025年上海分部利润表'!H13+'2025年赣皖区域利润表'!H13 -> 20830.952 | I13: ='2025年中心利润表 '!I13+'2025年江苏分部利润表'!I13+'2025年浙江分部利润表'!I13+'2025年上海分部利润表'!I13+'2025年赣皖区域利润表'!I13 -> 0 | J13: ='2025年中心利润表 '!J13+'2025年江苏分部利润表'!J13+'2025年浙江分部利润表'!J13+'2025年上海分部利润表'!J13+'2025年赣皖区域利润表'!J13 -> 22105.362 | ... Z13: ='2025年中心利润表 '!Z13+'2025年江苏分部利润表'!Z13+'2025年浙江分部利润表'!Z13+'2025年上海分部利润表'!Z13+'2025年赣皖区域利润表'!Z13 -> 5973.45 | AA13: =C13+E13+G13+I13+K13+M13+O13+Q13+S13+U13+W13+Y13 -> 0 | AB13: =D13+F13+H13+J13+L13+N13+P13+R13+T13+V13+X13+Z13 -> 203664.82 | AD13: =SUMIF($C$5:$Z$5,$AD$5,C13:Z13) -> 0 | AE13: =SUMIF($C$5:$Z$5,$AD$5,D13:AA13) -> 203664.82 | AF13: =AA13-AD13 -> 0 | AG13: =AB13-AE13 -> 0 | AH13: =SUM('[1]2024年全面预算利润表 (销售1中心)2.8亿'!E17:H17) -> 0
A14: 返利 | C14: ='2025年中心利润表 '!C14+'2025年江苏分部利润表'!C14+'2025年浙江分部利润表'!C14+'2025年上海分部利润表'!C14+'2025年赣皖区域利润表'!C14 -> 0 | D14: ='2025年中心利润表 '!D14+'2025年江苏分部利润表'!D14+'2025年浙江分部利润表'!D14+'2025年上海分部利润表'!D14+'2025年赣皖区域利润表'!D14 -> 0 | E14: ='2025年中心利润表 '!E14+'2025年江苏分部利润表'!E14+'2025年浙江分部利润表'!E14+'2025年上海分部利润表'!E14+'2025年赣皖区域利润表'!E14 -> 0 | F14: ='2025年中心利润表 '!F14+'2025年江苏分部利润表'!F14+'2025年浙江分部利润表'!F14+'2025年上海分部利润表'!F14+'2025年赣皖区域利润表'!F14 -> 0 | G14: ='2025年中心利润表 '!G14+'2025年江苏分部利润表'!G14+'2025年浙江分部利润表'!G14+'2025年上海分部利润表'!G14+'2025年赣皖区域利润表'!G14 -> 0 | H14: ='2025年中心利润表 '!H14+'2025年江苏分部利润表'!H14+'2025年浙江分部利润表'!H14+'2025年上海分部利润表'!H14+'2025年赣皖区域利润表'!H14 -> 0 | I14: ='2025年中心利润表 '!I14+'2025年江苏分部利润表'!I14+'2025年浙江分部利润表'!I14+'2025年上海分部利润表'!I14+'2025年赣皖区域利润表'!I14 -> 0 | J14: ='2025年中心利润表 '!J14+'2025年江苏分部利润表'!J14+'2025年浙江分部利润表'!J14+'2025年上海分部利润表'!J14+'2025年赣皖区域利润表'!J14 -> 92281.51 | ... Z14: ='2025年中心利润表 '!Z14+'2025年江苏分部利润表'!Z14+'2025年浙江分部利润表'!Z14+'2025年上海分部利润表'!Z14+'2025年赣皖区域利润表'!Z14 -> 84301.617 | AA14: =C14+E14+G14+I14+K14+M14+O14+Q14+S14+U14+W14+Y14 -> 1220607 | AB14: =D14+F14+H14+J14+L14+N14+P14+R14+T14+V14+X14+Z14 -> 896264.16 | AD14: =SUMIF($C$5:$Z$5,$AD$5,C14:Z14) -> 1220607 | AE14: =SUMIF($C$5:$Z$5,$AD$5,D14:AA14) -> 896264.16 | AH14: =SUM('[1]2024年全面预算利润表 (销售1中心)2.8亿'!E18:H18) -> 0
A15: 其他 | C15: ='2025年中心利润表 '!C15+'2025年江苏分部利润表'!C15+'2025年浙江分部利润表'!C15+'2025年上海分部利润表'!C15+'2025年赣皖区域利润表'!C15 -> 3986706.8 | D15: ='2025年中心利润表 '!D15+'2025年江苏分部利润表'!D15+'2025年浙江分部利润表'!D15+'2025年上海分部利润表'!D15+'2025年赣皖区域利润表'!D15 -> 853.98 | E15: ='2025年中心利润表 '!E15+'2025年江苏分部利润表'!E15+'2025年浙江分部利润表'!E15+'2025年上海分部利润表'!E15+'2025年赣皖区域利润表'!E15 -> 4955115 | F15: ='2025年中心利润表 '!F15+'2025年江苏分部利润表'!F15+'2025年浙江分部利润表'!F15+'2025年上海分部利润表'!F15+'2025年赣皖区域利润表'!F15 -> 530.97 | G15: ='2025年中心利润表 '!G15+'2025年江苏分部利润表'!G15+'2025年浙江分部利润表'!G15+'2025年上海分部利润表'!G15+'2025年赣皖区域利润表'!G15 -> 8700489.3 | H15: ='2025年中心利润表 '!H15+'2025年江苏分部利润表'!H15+'2025年浙江分部利润表'!H15+'2025年上海分部利润表'!H15+'2025年赣皖区域利润表'!H15 -> 0 | I15: ='2025年中心利润表 '!I15+'2025年江苏分部利润表'!I15+'2025年浙江分部利润表'!I15+'2025年上海分部利润表'!I15+'2025年赣皖区域利润表'!I15 -> 10237244 | J15: ='2025年中心利润表 '!J15+'2025年江苏分部利润表'!J15+'2025年浙江分部利润表'!J15+'2025年上海分部利润表'!J15+'2025年赣皖区域利润表'!J15 -> 0 | ... Z15: ='2025年中心利润表 '!Z15+'2025年江苏分部利润表'!Z15+'2025年浙江分部利润表'!Z15+'2025年上海分部利润表'!Z15+'2025年赣皖区域利润表'!Z15 -> 0 | AA15: =C15+E15+G15+I15+K15+M15+O15+Q15+S15+U15+W15+Y15 -> 123344000 | AB15: =D15+F15+H15+J15+L15+N15+P15+R15+T15+V15+X15+Z15 -> 7646.04 | AD15: =SUMIF($C$5:$Z$5,$AD$5,C15:Z15) -> 123344000 | AE15: =SUMIF($C$5:$Z$5,$AD$5,D15:AA15) -> 7646.04 | AF15: =AA15-AD15 -> 0 | AG15: =AB15-AE15 -> 0 | AH15: =SUM('[1]2024年全面预算利润表 (销售1中心)2.8亿'!E18:H18) -> 0
A16: 减：营业成本 | B16: 2 | C16: =SUM(C17:C25) -> 3382585.8 | D16: =SUM(D17:D25) -> 6952652.5 | E16: =SUM(E17:E25) -> 4215074 | F16: =SUM(F17:F25) -> 4306755.5 | G16: =SUM(G17:G25) -> 7282520.4 | H16: =SUM(H17:H25) -> 6051909.8 | I16: =SUM(I17:I25) -> 8454862.9 | J16: =SUM(J17:J25) -> 8553557.4 | ... Z16: =SUM(Z17:Z25) -> 10405260 | AA16: =C16+E16+G16+I16+K16+M16+O16+Q16+S16+U16+W16+Y16 -> 1.0100001e+08 | AB16: =D16+F16+H16+J16+L16+N16+P16+R16+T16+V16+X16+Z16 -> 85057035 | AD16: =SUMIF($C$5:$Z$5,$AD$5,C16:Z16) -> 1.0100001e+08 | AE16: =SUMIF($C$5:$Z$5,$AD$5,D16:AA16) -> 85057035 | AF16: =AA16-AD16 -> 0 | AG16: =AB16-AE16 -> 0 | AH16: =SUM('[1]2024年全面预算利润表 (销售1中心)2.8亿'!$E$16:$H$16) -> 29585058
A17: 中式汤底 | C17: ='2025年中心利润表 '!C17+'2025年江苏分部利润表'!C17+'2025年浙江分部利润表'!C17+'2025年上海分部利润表'!C17+'2025年赣皖区域利润表'!C17 -> 0 | D17: ='2025年中心利润表 '!D17+'2025年江苏分部利润表'!D17+'2025年浙江分部利润表'!D17+'2025年上海分部利润表'!D17+'2025年赣皖区域利润表'!D17 -> 1473240.4 | E17: ='2025年中心利润表 '!E17+'2025年江苏分部利润表'!E17+'2025年浙江分部利润表'!E17+'2025年上海分部利润表'!E17+'2025年赣皖区域利润表'!E17 -> 0 | F17: ='2025年中心利润表 '!F17+'2025年江苏分部利润表'!F17+'2025年浙江分部利润表'!F17+'2025年上海分部利润表'!F17+'2025年赣皖区域利润表'!F17 -> 1039771.2 | G17: ='2025年中心利润表 '!G17+'2025年江苏分部利润表'!G17+'2025年浙江分部利润表'!G17+'2025年上海分部利润表'!G17+'2025年赣皖区域利润表'!G17 -> 0 | H17: ='2025年中心利润表 '!H17+'2025年江苏分部利润表'!H17+'2025年浙江分部利润表'!H17+'2025年上海分部利润表'!H17+'2025年赣皖区域利润表'!H17 -> 1819851.8 | I17: ='2025年中心利润表 '!I17+'2025年江苏分部利润表'!I17+'2025年浙江分部利润表'!I17+'2025年上海分部利润表'!I17+'2025年赣皖区域利润表'!I17 -> 0 | J17: ='2025年中心利润表 '!J17+'2025年江苏分部利润表'!J17+'2025年浙江分部利润表'!J17+'2025年上海分部利润表'!J17+'2025年赣皖区域利润表'!J17 -> 2455648.6 | ... Z17: ='2025年中心利润表 '!Z17+'2025年江苏分部利润表'!Z17+'2025年浙江分部利润表'!Z17+'2025年上海分部利润表'!Z17+'2025年赣皖区域利润表'!Z17 -> 2529444.9 | AA17: =C17+E17+G17+I17+K17+M17+O17+Q17+S17+U17+W17+Y17 -> 0 | AB17: =D17+F17+H17+J17+L17+N17+P17+R17+T17+V17+X17+Z17 -> 22115149 | AD17: =SUMIF($C$5:$Z$5,$AD$5,C17:Z17) -> 0 | AE17: =SUMIF($C$5:$Z$5,$AD$5,D17:AA17) -> 22115149 | AF17: =AA17-AD17 -> 0 | AG17: =AB17-AE17 -> 0 | AH17: =SUM('[1]2024年全面预算利润表 (销售1中心)2.8亿'!E20:H20) -> 29005401
A18: 酱料 | C18: ='2025年中心利润表 '!C18+'2025年江苏分部利润表'!C18+'2025年浙江分部利润表'!C18+'2025年上海分部利润表'!C18+'2025年赣皖区域利润表'!C18 -> 0 | D18: ='2025年中心利润表 '!D18+'2025年江苏分部利润表'!D18+'2025年浙江分部利润表'!D18+'2025年上海分部利润表'!D18+'2025年赣皖区域利润表'!D18 -> 2551677.7 | E18: ='2025年中心利润表 '!E18+'2025年江苏分部利润表'!E18+'2025年浙江分部利润表'!E18+'2025年上海分部利润表'!E18+'2025年赣皖区域利润表'!E18 -> 0 | F18: ='2025年中心利润表 '!F18+'2025年江苏分部利润表'!F18+'2025年浙江分部利润表'!F18+'2025年上海分部利润表'!F18+'2025年赣皖区域利润表'!F18 -> 1712611.2 | G18: ='2025年中心利润表 '!G18+'2025年江苏分部利润表'!G18+'2025年浙江分部利润表'!G18+'2025年上海分部利润表'!G18+'2025年赣皖区域利润表'!G18 -> 0 | H18: ='2025年中心利润表 '!H18+'2025年江苏分部利润表'!H18+'2025年浙江分部利润表'!H18+'2025年上海分部利润表'!H18+'2025年赣皖区域利润表'!H18 -> 2745204.7 | I18: ='2025年中心利润表 '!I18+'2025年江苏分部利润表'!I18+'2025年浙江分部利润表'!I18+'2025年上海分部利润表'!I18+'2025年赣皖区域利润表'!I18 -> 0 | J18: ='2025年中心利润表 '!J18+'2025年江苏分部利润表'!J18+'2025年浙江分部利润表'!J18+'2025年上海分部利润表'!J18+'2025年赣皖区域利润表'!J18 -> 3044693.7 | ... Z18: ='2025年中心利润表 '!Z18+'2025年江苏分部利润表'!Z18+'2025年浙江分部利润表'!Z18+'2025年上海分部利润表'!Z18+'2025年赣皖区域利润表'!Z18 -> 3986784.2 | AA18: =C18+E18+G18+I18+K18+M18+O18+Q18+S18+U18+W18+Y18 -> 0 | AB18: =D18+F18+H18+J18+L18+N18+P18+R18+T18+V18+X18+Z18 -> 31561282 | AD18: =SUMIF($C$5:$Z$5,$AD$5,C18:Z18) -> 0 | AE18: =SUMIF($C$5:$Z$5,$AD$5,D18:AA18) -> 31561282 | AF18: =AA18-AD18 -> 0 | AG18: =AB18-AE18 -> 0 | AH18: =SUM('[1]2024年全面预算利润表 (销售1中心)2.8亿'!E21:H21) -> 579657.07
A19: 川味底料 | C19: ='2025年中心利润表 '!C19+'2025年江苏分部利润表'!C19+'2025年浙江分部利润表'!C19+'2025年上海分部利润表'!C19+'2025年赣皖区域利润表'!C19 -> 0 | D19: ='2025年中心利润表 '!D19+'2025年江苏分部利润表'!D19+'2025年浙江分部利润表'!D19+'2025年上海分部利润表'!D19+'2025年赣皖区域利润表'!D19 -> 2170913.3 | E19: ='2025年中心利润表 '!E19+'2025年江苏分部利润表'!E19+'2025年浙江分部利润表'!E19+'2025年上海分部利润表'!E19+'2025年赣皖区域利润表'!E19 -> 0 | F19: ='2025年中心利润表 '!F19+'2025年江苏分部利润表'!F19+'2025年浙江分部利润表'!F19+'2025年上海分部利润表'!F19+'2025年赣皖区域利润表'!F19 -> 1248175.7 | G19: ='2025年中心利润表 '!G19+'2025年江苏分部利润表'!G19+'2025年浙江分部利润表'!G19+'2025年上海分部利润表'!G19+'2025年赣皖区域利润表'!G19 -> 0 | H19: ='2025年中心利润表 '!H19+'2025年江苏分部利润表'!H19+'2025年浙江分部利润表'!H19+'2025年上海分部利润表'!H19+'2025年赣皖区域利润表'!H19 -> 1071829.2 | I19: ='2025年中心利润表 '!I19+'2025年江苏分部利润表'!I19+'2025年浙江分部利润表'!I19+'2025年上海分部利润表'!I19+'2025年赣皖区域利润表'!I19 -> 0 | J19: ='2025年中心利润表 '!J19+'2025年江苏分部利润表'!J19+'2025年浙江分部利润表'!J19+'2025年上海分部利润表'!J19+'2025年赣皖区域利润表'!J19 -> 2226700.7 | ... Z19: ='2025年中心利润表 '!Z19+'2025年江苏分部利润表'!Z19+'2025年浙江分部利润表'!Z19+'2025年上海分部利润表'!Z19+'2025年赣皖区域利润表'!Z19 -> 3427706.8 | AA19: =C19+E19+G19+I19+K19+M19+O19+Q19+S19+U19+W19+Y19 -> 0 | AB19: =D19+F19+H19+J19+L19+N19+P19+R19+T19+V19+X19+Z19 -> 24113807 | AD19: =SUMIF($C$5:$Z$5,$AD$5,C19:Z19) -> 0 | AE19: =SUMIF($C$5:$Z$5,$AD$5,D19:AA19) -> 24113807 | AF19: =AA19-AD19 -> 0 | AG19: =AB19-AE19 -> 0 | AH19: =SUM('[1]2024年全面预算利润表 (销售1中心)2.8亿'!E22:H22) -> 0
A20: 调味汁 | C20: ='2025年中心利润表 '!C20+'2025年江苏分部利润表'!C20+'2025年浙江分部利润表'!C20+'2025年上海分部利润表'!C20+'2025年赣皖区域利润表'!C20 -> 0 | D20: ='2025年中心利润表 '!D20+'2025年江苏分部利润表'!D20+'2025年浙江分部利润表'!D20+'2025年上海分部利润表'!D20+'2025年赣皖区域利润表'!D20 -> 332705.46 | E20: ='2025年中心利润表 '!E20+'2025年江苏分部利润表'!E20+'2025年浙江分部利润表'!E20+'2025年上海分部利润表'!E20+'2025年赣皖区域利润表'!E20 -> 0 | F20: ='2025年中心利润表 '!F20+'2025年江苏分部利润表'!F20+'2025年浙江分部利润表'!F20+'2025年上海分部利润表'!F20+'2025年赣皖区域利润表'!F20 -> 132104.21 | G20: ='2025年中心利润表 '!G20+'2025年江苏分部利润表'!G20+'2025年浙江分部利润表'!G20+'2025年上海分部利润表'!G20+'2025年赣皖区域利润表'!G20 -> 0 | H20: ='2025年中心利润表 '!H20+'2025年江苏分部利润表'!H20+'2025年浙江分部利润表'!H20+'2025年上海分部利润表'!H20+'2025年赣皖区域利润表'!H20 -> 181666.72 | I20: ='2025年中心利润表 '!I20+'2025年江苏分部利润表'!I20+'2025年浙江分部利润表'!I20+'2025年上海分部利润表'!I20+'2025年赣皖区域利润表'!I20 -> 0 | J20: ='2025年中心利润表 '!J20+'2025年江苏分部利润表'!J20+'2025年浙江分部利润表'!J20+'2025年上海分部利润表'!J20+'2025年赣皖区域利润表'!J20 -> 340450.67 | ... Z20: ='2025年中心利润表 '!Z20+'2025年江苏分部利润表'!Z20+'2025年浙江分部利润表'!Z20+'2025年上海分部利润表'!Z20+'2025年赣皖区域利润表'!Z20 -> 212481.71 | AA20: =C20+E20+G20+I20+K20+M20+O20+Q20+S20+U20+W20+Y20 -> 0 | AB20: =D20+F20+H20+J20+L20+N20+P20+R20+T20+V20+X20+Z20 -> 3157689.2 | AD20: =SUMIF($C$5:$Z$5,$AD$5,C20:Z20) -> 0 | AE20: =SUMIF($C$5:$Z$5,$AD$5,D20:AA20) -> 3157689.2 | AF20: =AA20-AD20 -> 0 | AG20: =AB20-AE20 -> 0 | AH20: =SUM('[1]2024年全面预算利润表 (销售1中心)2.8亿'!E23:H23) -> 6733315
A21: 复合调味粉 | C21: ='2025年中心利润表 '!C21+'2025年江苏分部利润表'!C21+'2025年浙江分部利润表'!C21+'2025年上海分部利润表'!C21+'2025年赣皖区域利润表'!C21 -> 0 | D21: ='2025年中心利润表 '!D21+'2025年江苏分部利润表'!D21+'2025年浙江分部利润表'!D21+'2025年上海分部利润表'!D21+'2025年赣皖区域利润表'!D21 -> 217523.13 | E21: ='2025年中心利润表 '!E21+'2025年江苏分部利润表'!E21+'2025年浙江分部利润表'!E21+'2025年上海分部利润表'!E21+'2025年赣皖区域利润表'!E21 -> 0 | F21: ='2025年中心利润表 '!F21+'2025年江苏分部利润表'!F21+'2025年浙江分部利润表'!F21+'2025年上海分部利润表'!F21+'2025年赣皖区域利润表'!F21 -> 68380.712 | G21: ='2025年中心利润表 '!G21+'2025年江苏分部利润表'!G21+'2025年浙江分部利润表'!G21+'2025年上海分部利润表'!G21+'2025年赣皖区域利润表'!G21 -> 0 | H21: ='2025年中心利润表 '!H21+'2025年江苏分部利润表'!H21+'2025年浙江分部利润表'!H21+'2025年上海分部利润表'!H21+'2025年赣皖区域利润表'!H21 -> 78636.423 | I21: ='2025年中心利润表 '!I21+'2025年江苏分部利润表'!I21+'2025年浙江分部利润表'!I21+'2025年上海分部利润表'!I21+'2025年赣皖区域利润表'!I21 -> 0 | J21: ='2025年中心利润表 '!J21+'2025年江苏分部利润表'!J21+'2025年浙江分部利润表'!J21+'2025年上海分部利润表'!J21+'2025年赣皖区域利润表'!J21 -> 284751.35 | ... Z21: ='2025年中心利润表 '!Z21+'2025年江苏分部利润表'!Z21+'2025年浙江分部利润表'!Z21+'2025年上海分部利润表'!Z21+'2025年赣皖区域利润表'!Z21 -> 77007.812 | AA21: =C21+E21+G21+I21+K21+M21+O21+Q21+S21+U21+W21+Y21 -> 0 | AB21: =D21+F21+H21+J21+L21+N21+P21+R21+T21+V21+X21+Z21 -> 1829644 | AD21: =SUMIF($C$5:$Z$5,$AD$5,C21:Z21) -> 0 | AE21: =SUMIF($C$5:$Z$5,$AD$5,D21:AA21) -> 1829644 | AF21: =AA21-AD21 -> 0 | AG21: =AB21-AE21 -> 0 | AH21: =SUM('[1]2024年全面预算利润表 (销售1中心)2.8亿'!E24:H24) -> 0
A22: 团餐 | C22: ='2025年中心利润表 '!C22+'2025年江苏分部利润表'!C22+'2025年浙江分部利润表'!C22+'2025年上海分部利润表'!C22+'2025年赣皖区域利润表'!C22 -> 0 | D22: ='2025年中心利润表 '!D22+'2025年江苏分部利润表'!D22+'2025年浙江分部利润表'!D22+'2025年上海分部利润表'!D22+'2025年赣皖区域利润表'!D22 -> 4247.996 | E22: ='2025年中心利润表 '!E22+'2025年江苏分部利润表'!E22+'2025年浙江分部利润表'!E22+'2025年上海分部利润表'!E22+'2025年赣皖区域利润表'!E22 -> 0 | F22: ='2025年中心利润表 '!F22+'2025年江苏分部利润表'!F22+'2025年浙江分部利润表'!F22+'2025年上海分部利润表'!F22+'2025年赣皖区域利润表'!F22 -> 10651.326 | G22: ='2025年中心利润表 '!G22+'2025年江苏分部利润表'!G22+'2025年浙江分部利润表'!G22+'2025年上海分部利润表'!G22+'2025年赣皖区域利润表'!G22 -> 0 | H22: ='2025年中心利润表 '!H22+'2025年江苏分部利润表'!H22+'2025年浙江分部利润表'!H22+'2025年上海分部利润表'!H22+'2025年赣皖区域利润表'!H22 -> 6748.6152 | I22: ='2025年中心利润表 '!I22+'2025年江苏分部利润表'!I22+'2025年浙江分部利润表'!I22+'2025年上海分部利润表'!I22+'2025年赣皖区域利润表'!I22 -> 0 | J22: ='2025年中心利润表 '!J22+'2025年江苏分部利润表'!J22+'2025年浙江分部利润表'!J22+'2025年上海分部利润表'!J22+'2025年赣皖区域利润表'!J22 -> 4176.9 | ... Z22: ='2025年中心利润表 '!Z22+'2025年江苏分部利润表'!Z22+'2025年浙江分部利润表'!Z22+'2025年上海分部利润表'!Z22+'2025年赣皖区域利润表'!Z22 -> 6817.2 | AA22: =C22+E22+G22+I22+K22+M22+O22+Q22+S22+U22+W22+Y22 -> 0 | AB22: =D22+F22+H22+J22+L22+N22+P22+R22+T22+V22+X22+Z22 -> 44210.498 | AD22: =SUMIF($C$5:$Z$5,$AD$5,C22:Z22) -> 0 | AE22: =SUMIF($C$5:$Z$5,$AD$5,D22:AA22) -> 44210.498 | AF22: =AA22-AD22 -> 0 | AG22: =AB22-AE22 -> 0 | AH22: =SUM('[1]2024年全面预算利润表 (销售1中心)2.8亿'!E25:H25) -> 0
A23: 预制菜 | C23: ='2025年中心利润表 '!C23+'2025年江苏分部利润表'!C23+'2025年浙江分部利润表'!C23+'2025年上海分部利润表'!C23+'2025年赣皖区域利润表'!C23 -> 0 | D23: ='2025年中心利润表 '!D23+'2025年江苏分部利润表'!D23+'2025年浙江分部利润表'!D23+'2025年上海分部利润表'!D23+'2025年赣皖区域利润表'!D23 -> 30967.084 | E23: ='2025年中心利润表 '!E23+'2025年江苏分部利润表'!E23+'2025年浙江分部利润表'!E23+'2025年上海分部利润表'!E23+'2025年赣皖区域利润表'!E23 -> 0 | F23: ='2025年中心利润表 '!F23+'2025年江苏分部利润表'!F23+'2025年浙江分部利润表'!F23+'2025年上海分部利润表'!F23+'2025年赣皖区域利润表'!F23 -> 7925.4 | G23: ='2025年中心利润表 '!G23+'2025年江苏分部利润表'!G23+'2025年浙江分部利润表'!G23+'2025年上海分部利润表'!G23+'2025年赣皖区域利润表'!G23 -> 0 | H23: ='2025年中心利润表 '!H23+'2025年江苏分部利润表'!H23+'2025年浙江分部利润表'!H23+'2025年上海分部利润表'!H23+'2025年赣皖区域利润表'!H23 -> 19220.134 | I23: ='2025年中心利润表 '!I23+'2025年江苏分部利润表'!I23+'2025年浙江分部利润表'!I23+'2025年上海分部利润表'!I23+'2025年赣皖区域利润表'!I23 -> 0 | J23: ='2025年中心利润表 '!J23+'2025年江苏分部利润表'!J23+'2025年浙江分部利润表'!J23+'2025年上海分部利润表'!J23+'2025年赣皖区域利润表'!J23 -> 18814.096 | ... Z23: ='2025年中心利润表 '!Z23+'2025年江苏分部利润表'!Z23+'2025年浙江分部利润表'!Z23+'2025年上海分部利润表'!Z23+'2025年赣皖区域利润表'!Z23 -> 4735.24 | AA23: =C23+E23+G23+I23+K23+M23+O23+Q23+S23+U23+W23+Y23 -> 0 | AB23: =D23+F23+H23+J23+L23+N23+P23+R23+T23+V23+X23+Z23 -> 188485.86 | AD23: =SUMIF($C$5:$Z$5,$AD$5,C23:Z23) -> 0 | AE23: =SUMIF($C$5:$Z$5,$AD$5,D23:AA23) -> 188485.86 | AF23: =AA23-AD23 -> 0 | AG23: =AB23-AE23 -> 0 | AH23: =SUM('[1]2024年全面预算利润表 (销售1中心)2.8亿'!E26:H26) -> 0
A24: 其他 | C24: ='2025年中心利润表 '!C24+'2025年江苏分部利润表'!C24+'2025年浙江分部利润表'!C24+'2025年上海分部利润表'!C24+'2025年赣皖区域利润表'!C24 -> 3320260 | D24: ='2025年中心利润表 '!D24+'2025年江苏分部利润表'!D24+'2025年浙江分部利润表'!D24+'2025年上海分部利润表'!D24+'2025年赣皖区域利润表'!D24 -> 4386.36 | E24: ='2025年中心利润表 '!E24+'2025年江苏分部利润表'!E24+'2025年浙江分部利润表'!E24+'2025年上海分部利润表'!E24+'2025年赣皖区域利润表'!E24 -> 4133487.5 | F24: ='2025年中心利润表 '!F24+'2025年江苏分部利润表'!F24+'2025年浙江分部利润表'!F24+'2025年上海分部利润表'!F24+'2025年赣皖区域利润表'!F24 -> 477.67 | G24: ='2025年中心利润表 '!G24+'2025年江苏分部利润表'!G24+'2025年浙江分部利润表'!G24+'2025年上海分部利润表'!G24+'2025年赣皖区域利润表'!G24 -> 7138634.4 | H24: ='2025年中心利润表 '!H24+'2025年江苏分部利润表'!H24+'2025年浙江分部利润表'!H24+'2025年上海分部利润表'!H24+'2025年赣皖区域利润表'!H24 -> 0 | I24: ='2025年中心利润表 '!I24+'2025年江苏分部利润表'!I24+'2025年浙江分部利润表'!I24+'2025年上海分部利润表'!I24+'2025年赣皖区域利润表'!I24 -> 8286368.7 | J24: ='2025年中心利润表 '!J24+'2025年江苏分部利润表'!J24+'2025年浙江分部利润表'!J24+'2025年上海分部利润表'!J24+'2025年赣皖区域利润表'!J24 -> 0 | ... Z24: ='2025年中心利润表 '!Z24+'2025年江苏分部利润表'!Z24+'2025年浙江分部利润表'!Z24+'2025年上海分部利润表'!Z24+'2025年赣皖区域利润表'!Z24 -> -18076.911 | AA24: =C24+E24+G24+I24+K24+M24+O24+Q24+S24+U24+W24+Y24 -> 98966577 | AB24: =D24+F24+H24+J24+L24+N24+P24+R24+T24+V24+X24+Z24 -> 227027.38 | AD24: =SUMIF($C$5:$Z$5,$AD$5,C24:Z24) -> 98966577 | AE24: =SUMIF($C$5:$Z$5,$AD$5,D24:AA24) -> 227027.38 | AF24: =AA24-AD24 -> 0 | AG24: =AB24-AE24 -> 0 | AH24: =SUM('[1]2024年全面预算利润表 (销售1中心)2.8亿'!E27:H27) -> 7312972.1
A25: 运费 | C25: ='2025年中心利润表 '!C25+'2025年江苏分部利润表'!C25+'2025年浙江分部利润表'!C25+'2025年上海分部利润表'!C25+'2025年赣皖区域利润表'!C25 -> 62325.76 | D25: ='2025年中心利润表 '!D25+'2025年江苏分部利润表'!D25+'2025年浙江分部利润表'!D25+'2025年上海分部利润表'!D25+'2025年赣皖区域利润表'!D25 -> 166991.03 | E25: ='2025年中心利润表 '!E25+'2025年江苏分部利润表'!E25+'2025年浙江分部利润表'!E25+'2025年上海分部利润表'!E25+'2025年赣皖区域利润表'!E25 -> 81586.56 | F25: ='2025年中心利润表 '!F25+'2025年江苏分部利润表'!F25+'2025年浙江分部利润表'!F25+'2025年上海分部利润表'!F25+'2025年赣皖区域利润表'!F25 -> 86658.07 | G25: ='2025年中心利润表 '!G25+'2025年江苏分部利润表'!G25+'2025年浙江分部利润表'!G25+'2025年上海分部利润表'!G25+'2025年赣皖区域利润表'!G25 -> 143885.94 | H25: ='2025年中心利润表 '!H25+'2025年江苏分部利润表'!H25+'2025年浙江分部利润表'!H25+'2025年上海分部利润表'!H25+'2025年赣皖区域利润表'!H25 -> 128752.16 | I25: ='2025年中心利润表 '!I25+'2025年江苏分部利润表'!I25+'2025年浙江分部利润表'!I25+'2025年上海分部利润表'!I25+'2025年赣皖区域利润表'!I25 -> 168494.16 | J25: ='2025年中心利润表 '!J25+'2025年江苏分部利润表'!J25+'2025年浙江分部利润表'!J25+'2025年上海分部利润表'!J25+'2025年赣皖区域利润表'!J25 -> 178321.47 | ... Z25: ='2025年中心利润表 '!Z25+'2025年江苏分部利润表'!Z25+'2025年浙江分部利润表'!Z25+'2025年上海分部利润表'!Z25+'2025年赣皖区域利润表'!Z25 -> 178358.9 | AA25: =C25+E25+G25+I25+K25+M25+O25+Q25+S25+U25+W25+Y25 -> 2033432 | AB25: =D25+F25+H25+J25+L25+N25+P25+R25+T25+V25+X25+Z25 -> 1819739.1 | AD25: =SUMIF($C$5:$Z$5,$AD$5,C25:Z25) -> 2033432 | AE25: =SUMIF($C$5:$Z$5,$AD$5,D25:AA25) -> 1819739.1 | AF25: =AA25-AD25 -> 0 | AG25: =AB25-AE25 -> 0 | AH25: =SUM('[1]2024年全面预算利润表 (销售1中心)2.8亿'!E28:H28) -> 0.7299
A26: 毛利 | B26: 3 | C26: =C6-C16 -> 604121.05 | D26: =D6-D16 -> 1808716 | E26: =E6-E16 -> 740040.96 | F26: =F6-F16 -> 1129317.9 | G26: =G6-G16 -> 1417968.9 | H26: =H6-H16 -> 1502757.3 | I26: =I6-I16 -> 1782381.1 | J26: =J6-J16 -> 2010946.9 | ... Z26: =Z6-Z16 -> 2769067 | AA26: =C26+E26+G26+I26+K26+M26+O26+Q26+S26+U26+W26+Y26 -> 21123384 | AB26: =D26+F26+H26+J26+L26+N26+P26+R26+T26+V26+X26+Z26 -> 21821860 | AD26: =SUMIF($C$5:$Z$5,$AD$5,C26:Z26) -> 21123384 | AE26: =SUMIF($C$5:$Z$5,$AD$5,D26:AA26) -> 21821860 | AF26: =AD6-AD16-AA26 -> 0 | AG26: =AE6-AE16-AB26 -> 0 | AH26: =AH6-AH16 -> 6733315
A27: 毛利率 | B27: 4 | C27: =IF(C6=0,,C26/C6) -> 0.15153385 | D27: =IF(D6=0,,D26/D6) -> 0.20644218 | E27: =IF(E6=0,,E26/E6) -> 0.1493489 | F27: =IF(F6=0,,F26/F6) -> 0.20774515 | G27: =IF(G6=0,,G26/G6) -> 0.16297577 | H27: =IF(H6=0,,H26/H6) -> 0.19891774 | I27: =IF(I6=0,,I26/I6) -> 0.17410752 | J27: =IF(J6=0,,J26/J6) -> 0.19034939 | ... AB27: =IF(AB6=0,,AB26/AB6) -> 0.20417371 | AD27: =AD26/AD6 -> 0.17296755 | AE27: =AE26/AE6 -> 0.20417371 | AF27: =AA27-AD27 -> 0 | AG27: =AB27-AE27 -> 0 | AH27: =AH26/AH6 -> 0.18539693
A28: 税金及附加 | B28: 5 | C28: ='2025年中心利润表 '!C28+'2025年江苏分部利润表'!C28+'2025年浙江分部利润表'!C28+'2025年上海分部利润表'!C28+'2025年赣皖区域利润表'!C28 -> 35117.14 | D28: ='2025年中心利润表 '!D28+'2025年江苏分部利润表'!D28+'2025年浙江分部利润表'!D28+'2025年上海分部利润表'!D28+'2025年赣皖区域利润表'!D28 -> 83233.005 | E28: ='2025年中心利润表 '!E28+'2025年江苏分部利润表'!E28+'2025年浙江分部利润表'!E28+'2025年上海分部利润表'!E28+'2025年赣皖区域利润表'!E28 -> 47073.6 | F28: ='2025年中心利润表 '!F28+'2025年江苏分部利润表'!F28+'2025年浙江分部利润表'!F28+'2025年上海分部利润表'!F28+'2025年赣皖区域利润表'!F28 -> 51642.694 | G28: ='2025年中心利润表 '!G28+'2025年江苏分部利润表'!G28+'2025年浙江分部利润表'!G28+'2025年上海分部利润表'!G28+'2025年赣皖区域利润表'!G28 -> 82351.24 | H28: ='2025年中心利润表 '!H28+'2025年江苏分部利润表'!H28+'2025年浙江分部利润表'!H28+'2025年上海分部利润表'!H28+'2025年赣皖区域利润表'!H28 -> 71769.332 | I28: ='2025年中心利润表 '!I28+'2025年江苏分部利润表'!I28+'2025年浙江分部利润表'!I28+'2025年上海分部利润表'!I28+'2025年赣皖区域利润表'!I28 -> 97760.84 | J28: ='2025年中心利润表 '!J28+'2025年江苏分部利润表'!J28+'2025年浙江分部利润表'!J28+'2025年上海分部利润表'!J28+'2025年赣皖区域利润表'!J28 -> 100362.8 | ... Z28: ='2025年中心利润表 '!Z28+'2025年江苏分部利润表'!Z28+'2025年浙江分部利润表'!Z28+'2025年上海分部利润表'!Z28+'2025年赣皖区域利润表'!Z28 -> 125156.11 | AA28: =C28+E28+G28+I28+K28+M28+O28+Q28+S28+U28+W28+Y28 -> 1161420.4 | AB28: =D28+F28+H28+J28+L28+N28+P28+R28+T28+V28+X28+Z28 -> 1015349.5 | AD28: =SUMIF($C$5:$Z$5,$AD$5,C28:Z28) -> 1161420.4 | AE28: =SUMIF($C$5:$Z$5,$AD$5,D28:AA28) -> 1015349.5 | AF28: =AA28-AD28 -> 0 | AG28: =AB28-AE28 -> 0 | AH28: =SUM('[1]2024年全面预算利润表 (销售1中心)2.8亿'!$E$33:$H$33) -> 319601.69
A29: 销售费用 | B29: 6 | C29: =SUM(C30:C101)-C30-C33-C42-C53-C65 -> 736578.18 | D29: =SUM(D30:D101)-D30-D33-D42-D53-D65 -> 661019.17 | E29: =SUM(E30:E101)-E30-E33-E42-E53-E65 -> 574743.98 | F29: =SUM(F30:F101)-F30-F33-F42-F53-F65 -> 471368.5 | G29: =SUM(G30:G101)-G30-G33-G42-G53-G65 -> 748602.01 | H29: =SUM(H30:H101)-H30-H33-H42-H53-H65 -> 484266.56 | I29: =SUM(I30:I101)-I30-I33-I42-I53-I65 -> 709616.68 | J29: =SUM(J30:J101)-J30-J33-J42-J53-J65 -> 714586.55 | ... Z29: =SUM(Z30:Z101)-Z30-Z33-Z42-Z53-Z65 -> 508612.48 | AA29: =C29+E29+G29+I29+K29+M29+O29+Q29+S29+U29+W29+Y29 -> 9055651.2 | AB29: =D29+F29+H29+J29+L29+N29+P29+R29+T29+V29+X29+Z29 -> 6438464.7 | AD29: =SUMIF($C$5:$Z$5,$AD$5,C29:Z29) -> 9055651.2 | AE29: =SUMIF($C$5:$Z$5,$AD$5,D29:AA29) -> 6438464.7 | AF29: =AD29-(SUM(AA30:AA101)-SUM(AA30,AA33,AA42,AA53,AA65)) -> 0 | AG29: =AE29-(SUM(AB30:AB101)-SUM(AB30,AB33,AB42,AB53,AB65)) -> 0 | AH29: =SUM('[1]2024年全面预算利润表 (销售1中心)2.8亿'!E34:H34) -> 2909788.3
A30: 职工薪酬 | C30: =SUM(C31:C32) -> 453892.92 | D30: =SUM(D31:D32) -> 370435.67 | E30: =SUM(E31:E32) -> 343278.72 | F30: =SUM(F31:F32) -> 269606.58 | G30: =SUM(G31:G32) -> 430336.75 | H30: =SUM(H31:H32) -> 235131.7 | I30: =SUM(I31:I32) -> 480067.42 | J30: =SUM(J31:J32) -> 402799.83 | ... Z30: =SUM(Z31:Z32) -> 263429.06 | AA30: =C30+E30+G30+I30+K30+M30+O30+Q30+S30+U30+W30+Y30 -> 6060592 | AB30: =D30+F30+H30+J30+L30+N30+P30+R30+T30+V30+X30+Z30 -> 3548826.3 | AD30: =SUMIF($C$5:$Z$5,$AD$5,C30:Z30) -> 6060592 | AE30: =SUMIF($C$5:$Z$5,$AD$5,D30:AA30) -> 3548826.3 | AF30: =AA30-AD30 -> 0 | AG30: =AB30-AE30 -> 0 | AH30: =SUM('[1]2024年全面预算利润表 (销售1中心)2.8亿'!E35:H35) -> 1979870
A31: 工资 | C31: ='2025年中心利润表 '!C31+'2025年江苏分部利润表'!C31+'2025年浙江分部利润表'!C31+'2025年上海分部利润表'!C31+'2025年赣皖区域利润表'!C31 -> 181191 | D31: ='2025年中心利润表 '!D31+'2025年江苏分部利润表'!D31+'2025年浙江分部利润表'!D31+'2025年上海分部利润表'!D31+'2025年赣皖区域利润表'!D31 -> 210924.98 | E31: ='2025年中心利润表 '!E31+'2025年江苏分部利润表'!E31+'2025年浙江分部利润表'!E31+'2025年上海分部利润表'!E31+'2025年赣皖区域利润表'!E31 -> 181241 | F31: ='2025年中心利润表 '!F31+'2025年江苏分部利润表'!F31+'2025年浙江分部利润表'!F31+'2025年上海分部利润表'!F31+'2025年赣皖区域利润表'!F31 -> 203875.58 | G31: ='2025年中心利润表 '!G31+'2025年江苏分部利润表'!G31+'2025年浙江分部利润表'!G31+'2025年上海分部利润表'!G31+'2025年赣皖区域利润表'!G31 -> 181241 | H31: ='2025年中心利润表 '!H31+'2025年江苏分部利润表'!H31+'2025年浙江分部利润表'!H31+'2025年上海分部利润表'!H31+'2025年赣皖区域利润表'!H31 -> 101305.7 | I31: ='2025年中心利润表 '!I31+'2025年江苏分部利润表'!I31+'2025年浙江分部利润表'!I31+'2025年上海分部利润表'!I31+'2025年赣皖区域利润表'!I31 -> 191671 | J31: ='2025年中心利润表 '!J31+'2025年江苏分部利润表'!J31+'2025年浙江分部利润表'!J31+'2025年上海分部利润表'!J31+'2025年赣皖区域利润表'!J31 -> 171658.83 | ... Z31: ='2025年中心利润表 '!Z31+'2025年江苏分部利润表'!Z31+'2025年浙江分部利润表'!Z31+'2025年上海分部利润表'!Z31+'2025年赣皖区域利润表'!Z31 -> 157536.06 | AA31: =C31+E31+G31+I31+K31+M31+O31+Q31+S31+U31+W31+Y31 -> 2272612 | AB31: =D31+F31+H31+J31+L31+N31+P31+R31+T31+V31+X31+Z31 -> 1986631.6 | AD31: =SUMIF($C$5:$Z$5,$AD$5,C31:Z31) -> 2272612 | AE31: =SUMIF($C$5:$Z$5,$AD$5,D31:AA31) -> 1986631.6 | AF31: =AA31-AD31 -> 0 | AG31: =AB31-AE31 -> 0 | AH31: =SUM('[1]2024年全面预算利润表 (销售1中心)2.8亿'!E36:H36) -> 893600
A32: 奖金及提成 | C32: ='2025年中心利润表 '!C32+'2025年江苏分部利润表'!C32+'2025年浙江分部利润表'!C32+'2025年上海分部利润表'!C32+'2025年赣皖区域利润表'!C32 -> 272701.92 | D32: ='2025年中心利润表 '!D32+'2025年江苏分部利润表'!D32+'2025年浙江分部利润表'!D32+'2025年上海分部利润表'!D32+'2025年赣皖区域利润表'!D32 -> 159510.69 | E32: ='2025年中心利润表 '!E32+'2025年江苏分部利润表'!E32+'2025年浙江分部利润表'!E32+'2025年上海分部利润表'!E32+'2025年赣皖区域利润表'!E32 -> 162037.72 | F32: ='2025年中心利润表 '!F32+'2025年江苏分部利润表'!F32+'2025年浙江分部利润表'!F32+'2025年上海分部利润表'!F32+'2025年赣皖区域利润表'!F32 -> 65731 | G32: ='2025年中心利润表 '!G32+'2025年江苏分部利润表'!G32+'2025年浙江分部利润表'!G32+'2025年上海分部利润表'!G32+'2025年赣皖区域利润表'!G32 -> 249095.75 | H32: ='2025年中心利润表 '!H32+'2025年江苏分部利润表'!H32+'2025年浙江分部利润表'!H32+'2025年上海分部利润表'!H32+'2025年赣皖区域利润表'!H32 -> 133826 | I32: ='2025年中心利润表 '!I32+'2025年江苏分部利润表'!I32+'2025年浙江分部利润表'!I32+'2025年上海分部利润表'!I32+'2025年赣皖区域利润表'!I32 -> 288396.42 | J32: ='2025年中心利润表 '!J32+'2025年江苏分部利润表'!J32+'2025年浙江分部利润表'!J32+'2025年上海分部利润表'!J32+'2025年赣皖区域利润表'!J32 -> 231141 | ... Z32: ='2025年中心利润表 '!Z32+'2025年江苏分部利润表'!Z32+'2025年浙江分部利润表'!Z32+'2025年上海分部利润表'!Z32+'2025年赣皖区域利润表'!Z32 -> 105893 | AA32: =C32+E32+G32+I32+K32+M32+O32+Q32+S32+U32+W32+Y32 -> 3787980 | AB32: =D32+F32+H32+J32+L32+N32+P32+R32+T32+V32+X32+Z32 -> 1562194.7 | AD32: =SUMIF($C$5:$Z$5,$AD$5,C32:Z32) -> 3787980 | AE32: =SUMIF($C$5:$Z$5,$AD$5,D32:AA32) -> 1562194.7 | AF32: =AA32-AD32 -> 0 | AG32: =AB32-AE32 -> 0 | AH32: =SUM('[1]2024年全面预算利润表 (销售1中心)2.8亿'!E37:H37) -> 1086270
A33: 社保 | C33: =SUM(C34:C38) -> 30201.6 | D33: =SUM(D34:D38) -> 28007.26 | E33: =SUM(E34:E38) -> 30201.6 | F33: =SUM(F34:F38) -> 24135.4 | G33: =SUM(G34:G38) -> 30201.6 | H33: =SUM(H34:H38) -> 25465.02 | I33: =SUM(I34:I38) -> 30201.6 | J33: =SUM(J34:J38) -> 25465.02 | ... Z33: =SUM(Z34:Z38) -> 26385.87 | AA33: =C33+E33+G33+I33+K33+M33+O33+Q33+S33+U33+W33+Y33 -> 362419.2 | AB33: =D33+F33+H33+J33+L33+N33+P33+R33+T33+V33+X33+Z33 -> 310549.07 | AD33: =SUMIF($C$5:$Z$5,$AD$5,C33:Z33) -> 362419.2 | AE33: =SUMIF($C$5:$Z$5,$AD$5,D33:AA33) -> 310549.07 | AF33: =AA33-AD33 -> 0 | AG33: =AB33-AE33 -> 0 | AH33: =SUM('[1]2024年全面预算利润表 (销售1中心)2.8亿'!E38:H38) -> 121836.62
A34: 养老 | C34: ='2025年中心利润表 '!C34+'2025年江苏分部利润表'!C34+'2025年浙江分部利润表'!C34+'2025年上海分部利润表'!C34+'2025年赣皖区域利润表'!C34 -> 18720 | D34: ='2025年中心利润表 '!D34+'2025年江苏分部利润表'!D34+'2025年浙江分部利润表'!D34+'2025年上海分部利润表'!D34+'2025年赣皖区域利润表'!D34 -> 17743.68 | E34: ='2025年中心利润表 '!E34+'2025年江苏分部利润表'!E34+'2025年浙江分部利润表'!E34+'2025年上海分部利润表'!E34+'2025年赣皖区域利润表'!E34 -> 18720 | F34: ='2025年中心利润表 '!F34+'2025年江苏分部利润表'!F34+'2025年浙江分部利润表'!F34+'2025年上海分部利润表'!F34+'2025年赣皖区域利润表'!F34 -> 15362.88 | G34: ='2025年中心利润表 '!G34+'2025年江苏分部利润表'!G34+'2025年浙江分部利润表'!G34+'2025年上海分部利润表'!G34+'2025年赣皖区域利润表'!G34 -> 18720 | H34: ='2025年中心利润表 '!H34+'2025年江苏分部利润表'!H34+'2025年浙江分部利润表'!H34+'2025年上海分部利润表'!H34+'2025年赣皖区域利润表'!H34 -> 16168.32 | I34: ='2025年中心利润表 '!I34+'2025年江苏分部利润表'!I34+'2025年浙江分部利润表'!I34+'2025年上海分部利润表'!I34+'2025年赣皖区域利润表'!I34 -> 18720 | J34: ='2025年中心利润表 '!J34+'2025年江苏分部利润表'!J34+'2025年浙江分部利润表'!J34+'2025年上海分部利润表'!J34+'2025年赣皖区域利润表'!J34 -> 16168.32 | ... Z34: ='2025年中心利润表 '!Z34+'2025年江苏分部利润表'!Z34+'2025年浙江分部利润表'!Z34+'2025年上海分部利润表'!Z34+'2025年赣皖区域利润表'!Z34 -> 16752.96 | AA34: =C34+E34+G34+I34+K34+M34+O34+Q34+S34+U34+W34+Y34 -> 224640 | AB34: =D34+F34+H34+J34+L34+N34+P34+R34+T34+V34+X34+Z34 -> 198411.84 | AD34: =SUMIF($C$5:$Z$5,$AD$5,C34:Z34) -> 224640 | AE34: =SUMIF($C$5:$Z$5,$AD$5,D34:AA34) -> 198411.84 | AF34: =AA34-AD34 -> 0 | AG34: =AB34-AE34 -> 0 | AH34: =SUM('[1]2024年全面预算利润表 (销售1中心)2.8亿'!E39:H39) -> 73521.84
A35: 医疗 | C35: ='2025年中心利润表 '!C35+'2025年江苏分部利润表'!C35+'2025年浙江分部利润表'!C35+'2025年上海分部利润表'!C35+'2025年赣皖区域利润表'!C35 -> 9984 | D35: ='2025年中心利润表 '!D35+'2025年江苏分部利润表'!D35+'2025年浙江分部利润表'!D35+'2025年上海分部利润表'!D35+'2025年赣皖区域利润表'!D35 -> 9475.56 | E35: ='2025年中心利润表 '!E35+'2025年江苏分部利润表'!E35+'2025年浙江分部利润表'!E35+'2025年上海分部利润表'!E35+'2025年赣皖区域利润表'!E35 -> 9984 | F35: ='2025年中心利润表 '!F35+'2025年江苏分部利润表'!F35+'2025年浙江分部利润表'!F35+'2025年上海分部利润表'!F35+'2025年赣皖区域利润表'!F35 -> 8112.3 | G35: ='2025年中心利润表 '!G35+'2025年江苏分部利润表'!G35+'2025年浙江分部利润表'!G35+'2025年上海分部利润表'!G35+'2025年赣皖区域利润表'!G35 -> 9984 | H35: ='2025年中心利润表 '!H35+'2025年江苏分部利润表'!H35+'2025年浙江分部利润表'!H35+'2025年上海分部利润表'!H35+'2025年赣皖区域利润表'!H35 -> 8589.42 | I35: ='2025年中心利润表 '!I35+'2025年江苏分部利润表'!I35+'2025年浙江分部利润表'!I35+'2025年上海分部利润表'!I35+'2025年赣皖区域利润表'!I35 -> 9984 | J35: ='2025年中心利润表 '!J35+'2025年江苏分部利润表'!J35+'2025年浙江分部利润表'!J35+'2025年上海分部利润表'!J35+'2025年赣皖区域利润表'!J35 -> 8589.42 | ... Z35: ='2025年中心利润表 '!Z35+'2025年江苏分部利润表'!Z35+'2025年浙江分部利润表'!Z35+'2025年上海分部利润表'!Z35+'2025年赣皖区域利润表'!Z35 -> 8900.01 | AA35: =C35+E35+G35+I35+K35+M35+O35+Q35+S35+U35+W35+Y35 -> 119808 | AB35: =D35+F35+H35+J35+L35+N35+P35+R35+T35+V35+X35+Z35 -> 103456.68 | AD35: =SUMIF($C$5:$Z$5,$AD$5,C35:Z35) -> 119808 | AE35: =SUMIF($C$5:$Z$5,$AD$5,D35:AA35) -> 103456.68 | AF35: =AA35-AD35 -> 0 | AG35: =AB35-AE35 -> 0 | AH35: =SUM('[1]2024年全面预算利润表 (销售1中心)2.8亿'!E40:H40) -> 44638.26
A36: 工伤 | C36: ='2025年中心利润表 '!C36+'2025年江苏分部利润表'!C36+'2025年浙江分部利润表'!C36+'2025年上海分部利润表'!C36+'2025年赣皖区域利润表'!C36 -> 249.6 | D36: ='2025年中心利润表 '!D36+'2025年江苏分部利润表'!D36+'2025年浙江分部利润表'!D36+'2025年上海分部利润表'!D36+'2025年赣皖区域利润表'!D36 -> 233.53 | E36: ='2025年中心利润表 '!E36+'2025年江苏分部利润表'!E36+'2025年浙江分部利润表'!E36+'2025年上海分部利润表'!E36+'2025年赣皖区域利润表'!E36 -> 249.6 | F36: ='2025年中心利润表 '!F36+'2025年江苏分部利润表'!F36+'2025年浙江分部利润表'!F36+'2025年上海分部利润表'!F36+'2025年赣皖区域利润表'!F36 -> 173.57 | G36: ='2025年中心利润表 '!G36+'2025年江苏分部利润表'!G36+'2025年浙江分部利润表'!G36+'2025年上海分部利润表'!G36+'2025年赣皖区域利润表'!G36 -> 249.6 | H36: ='2025年中心利润表 '!H36+'2025年江苏分部利润表'!H36+'2025年浙江分部利润表'!H36+'2025年上海分部利润表'!H36+'2025年赣皖区域利润表'!H36 -> 198.74 | I36: ='2025年中心利润表 '!I36+'2025年江苏分部利润表'!I36+'2025年浙江分部利润表'!I36+'2025年上海分部利润表'!I36+'2025年赣皖区域利润表'!I36 -> 249.6 | J36: ='2025年中心利润表 '!J36+'2025年江苏分部利润表'!J36+'2025年浙江分部利润表'!J36+'2025年上海分部利润表'!J36+'2025年赣皖区域利润表'!J36 -> 198.74 | ... Z36: ='2025年中心利润表 '!Z36+'2025年江苏分部利润表'!Z36+'2025年浙江分部利润表'!Z36+'2025年上海分部利润表'!Z36+'2025年赣皖区域利润表'!Z36 -> 209.37 | AA36: =C36+E36+G36+I36+K36+M36+O36+Q36+S36+U36+W36+Y36 -> 2995.2 | AB36: =D36+F36+H36+J36+L36+N36+P36+R36+T36+V36+X36+Z36 -> 2482.26 | AD36: =SUMIF($C$5:$Z$5,$AD$5,C36:Z36) -> 2995.2 | AE36: =SUMIF($C$5:$Z$5,$AD$5,D36:AA36) -> 2482.26 | AF36: =AA36-AD36 -> 0 | AG36: =AB36-AE36 -> 0 | AH36: =SUM('[1]2024年全面预算利润表 (销售1中心)2.8亿'!E41:H41) -> 1050.74
A37: 失业 | C37: ='2025年中心利润表 '!C37+'2025年江苏分部利润表'!C37+'2025年浙江分部利润表'!C37+'2025年上海分部利润表'!C37+'2025年赣皖区域利润表'!C37 -> 624 | D37: ='2025年中心利润表 '!D37+'2025年江苏分部利润表'!D37+'2025年浙江分部利润表'!D37+'2025年上海分部利润表'!D37+'2025年赣皖区域利润表'!D37 -> 554.49 | E37: ='2025年中心利润表 '!E37+'2025年江苏分部利润表'!E37+'2025年浙江分部利润表'!E37+'2025年上海分部利润表'!E37+'2025年赣皖区域利润表'!E37 -> 624 | F37: ='2025年中心利润表 '!F37+'2025年江苏分部利润表'!F37+'2025年浙江分部利润表'!F37+'2025年上海分部利润表'!F37+'2025年赣皖区域利润表'!F37 -> 486.65 | G37: ='2025年中心利润表 '!G37+'2025年江苏分部利润表'!G37+'2025年浙江分部利润表'!G37+'2025年上海分部利润表'!G37+'2025年赣皖区域利润表'!G37 -> 624 | H37: ='2025年中心利润表 '!H37+'2025年江苏分部利润表'!H37+'2025年浙江分部利润表'!H37+'2025年上海分部利润表'!H37+'2025年赣皖区域利润表'!H37 -> 508.54 | I37: ='2025年中心利润表 '!I37+'2025年江苏分部利润表'!I37+'2025年浙江分部利润表'!I37+'2025年上海分部利润表'!I37+'2025年赣皖区域利润表'!I37 -> 624 | J37: ='2025年中心利润表 '!J37+'2025年江苏分部利润表'!J37+'2025年浙江分部利润表'!J37+'2025年上海分部利润表'!J37+'2025年赣皖区域利润表'!J37 -> 508.54 | ... Z37: ='2025年中心利润表 '!Z37+'2025年江苏分部利润表'!Z37+'2025年浙江分部利润表'!Z37+'2025年上海分部利润表'!Z37+'2025年赣皖区域利润表'!Z37 -> 523.53 | AA37: =C37+E37+G37+I37+K37+M37+O37+Q37+S37+U37+W37+Y37 -> 7488 | AB37: =D37+F37+H37+J37+L37+N37+P37+R37+T37+V37+X37+Z37 -> 6198.29 | AD37: =SUMIF($C$5:$Z$5,$AD$5,C37:Z37) -> 7488 | AE37: =SUMIF($C$5:$Z$5,$AD$5,D37:AA37) -> 6198.29 | AF37: =AA37-AD37 -> 0 | AG37: =AB37-AE37 -> 0 | AH37: =SUM('[1]2024年全面预算利润表 (销售1中心)2.8亿'!E42:H42) -> 2625.78
A38: 生育 | C38: ='2025年中心利润表 '!C38+'2025年江苏分部利润表'!C38+'2025年浙江分部利润表'!C38+'2025年上海分部利润表'!C38+'2025年赣皖区域利润表'!C38 -> 624 | D38: ='2025年中心利润表 '!D38+'2025年江苏分部利润表'!D38+'2025年浙江分部利润表'!D38+'2025年上海分部利润表'!D38+'2025年赣皖区域利润表'!D38 -> 0 | E38: ='2025年中心利润表 '!E38+'2025年江苏分部利润表'!E38+'2025年浙江分部利润表'!E38+'2025年上海分部利润表'!E38+'2025年赣皖区域利润表'!E38 -> 624 | F38: ='2025年中心利润表 '!F38+'2025年江苏分部利润表'!F38+'2025年浙江分部利润表'!F38+'2025年上海分部利润表'!F38+'2025年赣皖区域利润表'!F38 -> 0 | G38: ='2025年中心利润表 '!G38+'2025年江苏分部利润表'!G38+'2025年浙江分部利润表'!G38+'2025年上海分部利润表'!G38+'2025年赣皖区域利润表'!G38 -> 624 | H38: ='2025年中心利润表 '!H38+'2025年江苏分部利润表'!H38+'2025年浙江分部利润表'!H38+'2025年上海分部利润表'!H38+'2025年赣皖区域利润表'!H38 -> 0 | I38: ='2025年中心利润表 '!I38+'2025年江苏分部利润表'!I38+'2025年浙江分部利润表'!I38+'2025年上海分部利润表'!I38+'2025年赣皖区域利润表'!I38 -> 624 | J38: ='2025年中心利润表 '!J38+'2025年江苏分部利润表'!J38+'2025年浙江分部利润表'!J38+'2025年上海分部利润表'!J38+'2025年赣皖区域利润表'!J38 -> 0 | ... Z38: ='2025年中心利润表 '!Z38+'2025年江苏分部利润表'!Z38+'2025年浙江分部利润表'!Z38+'2025年上海分部利润表'!Z38+'2025年赣皖区域利润表'!Z38 -> 0 | AA38: =C38+E38+G38+I38+K38+M38+O38+Q38+S38+U38+W38+Y38 -> 7488 | AB38: =D38+F38+H38+J38+L38+N38+P38+R38+T38+V38+X38+Z38 -> 0 | AD38: =SUMIF($C$5:$Z$5,$AD$5,C38:Z38) -> 7488 | AE38: =SUMIF($C$5:$Z$5,$AD$5,D38:AA38) -> 0 | AF38: =AA38-AD38 -> 0 | AG38: =AB38-AE38 -> 0 | AH38: =SUM('[1]2024年全面预算利润表 (销售1中心)2.8亿'!E43:H43) -> 0
A39: 公积金 | C39: ='2025年中心利润表 '!C39+'2025年江苏分部利润表'!C39+'2025年浙江分部利润表'!C39+'2025年上海分部利润表'!C39+'2025年赣皖区域利润表'!C39 -> 6456 | D39: ='2025年中心利润表 '!D39+'2025年江苏分部利润表'!D39+'2025年浙江分部利润表'!D39+'2025年上海分部利润表'!D39+'2025年赣皖区域利润表'!D39 -> 6067 | E39: ='2025年中心利润表 '!E39+'2025年江苏分部利润表'!E39+'2025年浙江分部利润表'!E39+'2025年上海分部利润表'!E39+'2025年赣皖区域利润表'!E39 -> 6456 | F39: ='2025年中心利润表 '!F39+'2025年江苏分部利润表'!F39+'2025年浙江分部利润表'!F39+'2025年上海分部利润表'!F39+'2025年赣皖区域利润表'!F39 -> 5500 | G39: ='2025年中心利润表 '!G39+'2025年江苏分部利润表'!G39+'2025年浙江分部利润表'!G39+'2025年上海分部利润表'!G39+'2025年赣皖区域利润表'!G39 -> 6456 | H39: ='2025年中心利润表 '!H39+'2025年江苏分部利润表'!H39+'2025年浙江分部利润表'!H39+'2025年上海分部利润表'!H39+'2025年赣皖区域利润表'!H39 -> 5649 | I39: ='2025年中心利润表 '!I39+'2025年江苏分部利润表'!I39+'2025年浙江分部利润表'!I39+'2025年上海分部利润表'!I39+'2025年赣皖区域利润表'!I39 -> 6456 | J39: ='2025年中心利润表 '!J39+'2025年江苏分部利润表'!J39+'2025年浙江分部利润表'!J39+'2025年上海分部利润表'!J39+'2025年赣皖区域利润表'!J39 -> 5649 | ... Z39: ='2025年中心利润表 '!Z39+'2025年江苏分部利润表'!Z39+'2025年浙江分部利润表'!Z39+'2025年上海分部利润表'!Z39+'2025年赣皖区域利润表'!Z39 -> 5111 | AA39: =C39+E39+G39+I39+K39+M39+O39+Q39+S39+U39+W39+Y39 -> 77472 | AB39: =D39+F39+H39+J39+L39+N39+P39+R39+T39+V39+X39+Z39 -> 63753 | AD39: =SUMIF($C$5:$Z$5,$AD$5,C39:Z39) -> 77472 | AE39: =SUMIF($C$5:$Z$5,$AD$5,D39:AA39) -> 63753 | AF39: =AA39-AD39 -> 0 | AG39: =AB39-AE39 -> 0 | AH39: =SUM('[1]2024年全面预算利润表 (销售1中心)2.8亿'!E44:H44) -> 27707
A40: 工会经费 | C40: ='2025年中心利润表 '!C40+'2025年江苏分部利润表'!C40+'2025年浙江分部利润表'!C40+'2025年上海分部利润表'!C40+'2025年赣皖区域利润表'!C40 -> 0 | D40: ='2025年中心利润表 '!D40+'2025年江苏分部利润表'!D40+'2025年浙江分部利润表'!D40+'2025年上海分部利润表'!D40+'2025年赣皖区域利润表'!D40 -> 0 | E40: ='2025年中心利润表 '!E40+'2025年江苏分部利润表'!E40+'2025年浙江分部利润表'!E40+'2025年上海分部利润表'!E40+'2025年赣皖区域利润表'!E40 -> 0 | F40: ='2025年中心利润表 '!F40+'2025年江苏分部利润表'!F40+'2025年浙江分部利润表'!F40+'2025年上海分部利润表'!F40+'2025年赣皖区域利润表'!F40 -> 0 | G40: ='2025年中心利润表 '!G40+'2025年江苏分部利润表'!G40+'2025年浙江分部利润表'!G40+'2025年上海分部利润表'!G40+'2025年赣皖区域利润表'!G40 -> 0 | H40: ='2025年中心利润表 '!H40+'2025年江苏分部利润表'!H40+'2025年浙江分部利润表'!H40+'2025年上海分部利润表'!H40+'2025年赣皖区域利润表'!H40 -> 0 | I40: ='2025年中心利润表 '!I40+'2025年江苏分部利润表'!I40+'2025年浙江分部利润表'!I40+'2025年上海分部利润表'!I40+'2025年赣皖区域利润表'!I40 -> 0 | J40: ='2025年中心利润表 '!J40+'2025年江苏分部利润表'!J40+'2025年浙江分部利润表'!J40+'2025年上海分部利润表'!J40+'2025年赣皖区域利润表'!J40 -> 0 | ... Z40: ='2025年中心利润表 '!Z40+'2025年江苏分部利润表'!Z40+'2025年浙江分部利润表'!Z40+'2025年上海分部利润表'!Z40+'2025年赣皖区域利润表'!Z40 -> 0 | AA40: =C40+E40+G40+I40+K40+M40+O40+Q40+S40+U40+W40+Y40 -> 0 | AB40: =D40+F40+H40+J40+L40+N40+P40+R40+T40+V40+X40+Z40 -> 0 | AD40: =SUMIF($C$5:$Z$5,$AD$5,C40:Z40) -> 0 | AE40: =SUMIF($C$5:$Z$5,$AD$5,D40:AA40) -> 0 | AF40: =AA40-AD40 -> 0 | AG40: =AB40-AE40 -> 0 | AH40: =SUM('[1]2024年全面预算利润表 (销售1中心)2.8亿'!E45:H45) -> 0
A41: 职工教育经费 | C41: ='2025年中心利润表 '!C41+'2025年江苏分部利润表'!C41+'2025年浙江分部利润表'!C41+'2025年上海分部利润表'!C41+'2025年赣皖区域利润表'!C41 -> 0 | D41: ='2025年中心利润表 '!D41+'2025年江苏分部利润表'!D41+'2025年浙江分部利润表'!D41+'2025年上海分部利润表'!D41+'2025年赣皖区域利润表'!D41 -> 0 | E41: ='2025年中心利润表 '!E41+'2025年江苏分部利润表'!E41+'2025年浙江分部利润表'!E41+'2025年上海分部利润表'!E41+'2025年赣皖区域利润表'!E41 -> 0 | F41: ='2025年中心利润表 '!F41+'2025年江苏分部利润表'!F41+'2025年浙江分部利润表'!F41+'2025年上海分部利润表'!F41+'2025年赣皖区域利润表'!F41 -> 0 | G41: ='2025年中心利润表 '!G41+'2025年江苏分部利润表'!G41+'2025年浙江分部利润表'!G41+'2025年上海分部利润表'!G41+'2025年赣皖区域利润表'!G41 -> 0 | H41: ='2025年中心利润表 '!H41+'2025年江苏分部利润表'!H41+'2025年浙江分部利润表'!H41+'2025年上海分部利润表'!H41+'2025年赣皖区域利润表'!H41 -> 0 | I41: ='2025年中心利润表 '!I41+'2025年江苏分部利润表'!I41+'2025年浙江分部利润表'!I41+'2025年上海分部利润表'!I41+'2025年赣皖区域利润表'!I41 -> 0 | J41: ='2025年中心利润表 '!J41+'2025年江苏分部利润表'!J41+'2025年浙江分部利润表'!J41+'2025年上海分部利润表'!J41+'2025年赣皖区域利润表'!J41 -> 0 | ... Z41: ='2025年中心利润表 '!Z41+'2025年江苏分部利润表'!Z41+'2025年浙江分部利润表'!Z41+'2025年上海分部利润表'!Z41+'2025年赣皖区域利润表'!Z41 -> 0 | AA41: =C41+E41+G41+I41+K41+M41+O41+Q41+S41+U41+W41+Y41 -> 0 | AB41: =D41+F41+H41+J41+L41+N41+P41+R41+T41+V41+X41+Z41 -> 0 | AD41: =SUMIF($C$5:$Z$5,$AD$5,C41:Z41) -> 0 | AE41: =SUMIF($C$5:$Z$5,$AD$5,D41:AA41) -> 0 | AF41: =AA41-AD41 -> 0 | AG41: =AB41-AE41 -> 0 | AH41: =SUM('[1]2024年全面预算利润表 (销售1中心)2.8亿'!E46:H46) -> 0
A42: 福利费 | C42: =SUM(C43:C49) -> 6020 | D42: =SUM(D43:D49) -> 6055.05 | E42: =SUM(E43:E49) -> 800 | F42: =SUM(F43:F49) -> 11612.52 | G42: =SUM(G43:G49) -> 2000 | H42: =SUM(H43:H49) -> 1222.51 | I42: =SUM(I43:I49) -> 1220 | J42: =SUM(J43:J49) -> 1494.95 | ... Z42: =SUM(Z43:Z49) -> 824.8 | AA42: =C42+E42+G42+I42+K42+M42+O42+Q42+S42+U42+W42+Y42 -> 22300 | AB42: =D42+F42+H42+J42+L42+N42+P42+R42+T42+V42+X42+Z42 -> 32825.8 | AD42: =SUMIF($C$5:$Z$5,$AD$5,C42:Z42) -> 22300 | AE42: =SUMIF($C$5:$Z$5,$AD$5,D42:AA42) -> 32825.8 | AF42: =AA42-AD42 -> 0 | AG42: =AB42-AE42 -> 0 | AH42: =SUM('[1]2024年全面预算利润表 (销售1中心)2.8亿'!E47:H47) -> 10900
A43: 职工房租 | C43: ='2025年中心利润表 '!C43+'2025年江苏分部利润表'!C43+'2025年浙江分部利润表'!C43+'2025年上海分部利润表'!C43+'2025年赣皖区域利润表'!C43 -> 0 | D43: ='2025年中心利润表 '!D43+'2025年江苏分部利润表'!D43+'2025年浙江分部利润表'!D43+'2025年上海分部利润表'!D43+'2025年赣皖区域利润表'!D43 -> 0 | E43: ='2025年中心利润表 '!E43+'2025年江苏分部利润表'!E43+'2025年浙江分部利润表'!E43+'2025年上海分部利润表'!E43+'2025年赣皖区域利润表'!E43 -> 0 | F43: ='2025年中心利润表 '!F43+'2025年江苏分部利润表'!F43+'2025年浙江分部利润表'!F43+'2025年上海分部利润表'!F43+'2025年赣皖区域利润表'!F43 -> 0 | G43: ='2025年中心利润表 '!G43+'2025年江苏分部利润表'!G43+'2025年浙江分部利润表'!G43+'2025年上海分部利润表'!G43+'2025年赣皖区域利润表'!G43 -> 0 | H43: ='2025年中心利润表 '!H43+'2025年江苏分部利润表'!H43+'2025年浙江分部利润表'!H43+'2025年上海分部利润表'!H43+'2025年赣皖区域利润表'!H43 -> 0 | I43: ='2025年中心利润表 '!I43+'2025年江苏分部利润表'!I43+'2025年浙江分部利润表'!I43+'2025年上海分部利润表'!I43+'2025年赣皖区域利润表'!I43 -> 0 | J43: ='2025年中心利润表 '!J43+'2025年江苏分部利润表'!J43+'2025年浙江分部利润表'!J43+'2025年上海分部利润表'!J43+'2025年赣皖区域利润表'!J43 -> 0 | ... Z43: ='2025年中心利润表 '!Z43+'2025年江苏分部利润表'!Z43+'2025年浙江分部利润表'!Z43+'2025年上海分部利润表'!Z43+'2025年赣皖区域利润表'!Z43 -> 0 | AA43: =C43+E43+G43+I43+K43+M43+O43+Q43+S43+U43+W43+Y43 -> 0 | AB43: =D43+F43+H43+J43+L43+N43+P43+R43+T43+V43+X43+Z43 -> 97 | AD43: =SUMIF($C$5:$Z$5,$AD$5,C43:Z43) -> 0 | AE43: =SUMIF($C$5:$Z$5,$AD$5,D43:AA43) -> 97 | AF43: =AA43-AD43 -> 0 | AG43: =AB43-AE43 -> 0 | AH43: =SUM('[1]2024年全面预算利润表 (销售1中心)2.8亿'!E48:H48) -> 0
A44: 水电物业费 | C44: ='2025年中心利润表 '!C44+'2025年江苏分部利润表'!C44+'2025年浙江分部利润表'!C44+'2025年上海分部利润表'!C44+'2025年赣皖区域利润表'!C44 -> 800 | D44: ='2025年中心利润表 '!D44+'2025年江苏分部利润表'!D44+'2025年浙江分部利润表'!D44+'2025年上海分部利润表'!D44+'2025年赣皖区域利润表'!D44 -> 1255.05 | E44: ='2025年中心利润表 '!E44+'2025年江苏分部利润表'!E44+'2025年浙江分部利润表'!E44+'2025年上海分部利润表'!E44+'2025年赣皖区域利润表'!E44 -> 800 | F44: ='2025年中心利润表 '!F44+'2025年江苏分部利润表'!F44+'2025年浙江分部利润表'!F44+'2025年上海分部利润表'!F44+'2025年赣皖区域利润表'!F44 -> 917.67 | G44: ='2025年中心利润表 '!G44+'2025年江苏分部利润表'!G44+'2025年浙江分部利润表'!G44+'2025年上海分部利润表'!G44+'2025年赣皖区域利润表'!G44 -> 800 | H44: ='2025年中心利润表 '!H44+'2025年江苏分部利润表'!H44+'2025年浙江分部利润表'!H44+'2025年上海分部利润表'!H44+'2025年赣皖区域利润表'!H44 -> 222.51 | I44: ='2025年中心利润表 '!I44+'2025年江苏分部利润表'!I44+'2025年浙江分部利润表'!I44+'2025年上海分部利润表'!I44+'2025年赣皖区域利润表'!I44 -> 800 | J44: ='2025年中心利润表 '!J44+'2025年江苏分部利润表'!J44+'2025年浙江分部利润表'!J44+'2025年上海分部利润表'!J44+'2025年赣皖区域利润表'!J44 -> 1494.95 | ... Z44: ='2025年中心利润表 '!Z44+'2025年江苏分部利润表'!Z44+'2025年浙江分部利润表'!Z44+'2025年上海分部利润表'!Z44+'2025年赣皖区域利润表'!Z44 -> 824.8 | AA44: =C44+E44+G44+I44+K44+M44+O44+Q44+S44+U44+W44+Y44 -> 9600 | AB44: =D44+F44+H44+J44+L44+N44+P44+R44+T44+V44+X44+Z44 -> 10481.95 | AD44: =SUMIF($C$5:$Z$5,$AD$5,C44:Z44) -> 9600 | AE44: =SUMIF($C$5:$Z$5,$AD$5,D44:AA44) -> 10481.95 | AF44: =AA44-AD44 -> 0 | AG44: =AB44-AE44 -> 0 | AH44: =SUM('[1]2024年全面预算利润表 (销售1中心)2.8亿'!E49:H49) -> 2000
A45: 员工餐 | C45: ='2025年中心利润表 '!C45+'2025年江苏分部利润表'!C45+'2025年浙江分部利润表'!C45+'2025年上海分部利润表'!C45+'2025年赣皖区域利润表'!C45 -> 0 | D45: ='2025年中心利润表 '!D45+'2025年江苏分部利润表'!D45+'2025年浙江分部利润表'!D45+'2025年上海分部利润表'!D45+'2025年赣皖区域利润表'!D45 -> 0 | E45: ='2025年中心利润表 '!E45+'2025年江苏分部利润表'!E45+'2025年浙江分部利润表'!E45+'2025年上海分部利润表'!E45+'2025年赣皖区域利润表'!E45 -> 0 | F45: ='2025年中心利润表 '!F45+'2025年江苏分部利润表'!F45+'2025年浙江分部利润表'!F45+'2025年上海分部利润表'!F45+'2025年赣皖区域利润表'!F45 -> 0 | G45: ='2025年中心利润表 '!G45+'2025年江苏分部利润表'!G45+'2025年浙江分部利润表'!G45+'2025年上海分部利润表'!G45+'2025年赣皖区域利润表'!G45 -> 0 | H45: ='2025年中心利润表 '!H45+'2025年江苏分部利润表'!H45+'2025年浙江分部利润表'!H45+'2025年上海分部利润表'!H45+'2025年赣皖区域利润表'!H45 -> 0 | I45: ='2025年中心利润表 '!I45+'2025年江苏分部利润表'!I45+'2025年浙江分部利润表'!I45+'2025年上海分部利润表'!I45+'2025年赣皖区域利润表'!I45 -> 0 | J45: ='2025年中心利润表 '!J45+'2025年江苏分部利润表'!J45+'2025年浙江分部利润表'!J45+'2025年上海分部利润表'!J45+'2025年赣皖区域利润表'!J45 -> 0 | ... Z45: ='2025年中心利润表 '!Z45+'2025年江苏分部利润表'!Z45+'2025年浙江分部利润表'!Z45+'2025年上海分部利润表'!Z45+'2025年赣皖区域利润表'!Z45 -> 0 | AA45: =C45+E45+G45+I45+K45+M45+O45+Q45+S45+U45+W45+Y45 -> 0 | AB45: =D45+F45+H45+J45+L45+N45+P45+R45+T45+V45+X45+Z45 -> 0 | AD45: =SUMIF($C$5:$Z$5,$AD$5,C45:Z45) -> 0 | AE45: =SUMIF($C$5:$Z$5,$AD$5,D45:AA45) -> 0 | AF45: =AA45-AD45 -> 0 | AG45: =AB45-AE45 -> 0 | AH45: =SUM('[1]2024年全面预算利润表 (销售1中心)2.8亿'!E50:H50) -> 0
A46: 节日礼品 | C46: ='2025年中心利润表 '!C46+'2025年江苏分部利润表'!C46+'2025年浙江分部利润表'!C46+'2025年上海分部利润表'!C46+'2025年赣皖区域利润表'!C46 -> 4800 | D46: ='2025年中心利润表 '!D46+'2025年江苏分部利润表'!D46+'2025年浙江分部利润表'!D46+'2025年上海分部利润表'!D46+'2025年赣皖区域利润表'!D46 -> 4800 | E46: ='2025年中心利润表 '!E46+'2025年江苏分部利润表'!E46+'2025年浙江分部利润表'!E46+'2025年上海分部利润表'!E46+'2025年赣皖区域利润表'!E46 -> 0 | F46: ='2025年中心利润表 '!F46+'2025年江苏分部利润表'!F46+'2025年浙江分部利润表'!F46+'2025年上海分部利润表'!F46+'2025年赣皖区域利润表'!F46 -> 0 | G46: ='2025年中心利润表 '!G46+'2025年江苏分部利润表'!G46+'2025年浙江分部利润表'!G46+'2025年上海分部利润表'!G46+'2025年赣皖区域利润表'!G46 -> 100 | H46: ='2025年中心利润表 '!H46+'2025年江苏分部利润表'!H46+'2025年浙江分部利润表'!H46+'2025年上海分部利润表'!H46+'2025年赣皖区域利润表'!H46 -> 0 | I46: ='2025年中心利润表 '!I46+'2025年江苏分部利润表'!I46+'2025年浙江分部利润表'!I46+'2025年上海分部利润表'!I46+'2025年赣皖区域利润表'!I46 -> 0 | J46: ='2025年中心利润表 '!J46+'2025年江苏分部利润表'!J46+'2025年浙江分部利润表'!J46+'2025年上海分部利润表'!J46+'2025年赣皖区域利润表'!J46 -> 0 | ... Z46: ='2025年中心利润表 '!Z46+'2025年江苏分部利润表'!Z46+'2025年浙江分部利润表'!Z46+'2025年上海分部利润表'!Z46+'2025年赣皖区域利润表'!Z46 -> 0 | AA46: =C46+E46+G46+I46+K46+M46+O46+Q46+S46+U46+W46+Y46 -> 9700 | AB46: =D46+F46+H46+J46+L46+N46+P46+R46+T46+V46+X46+Z46 -> 9000 | AD46: =SUMIF($C$5:$Z$5,$AD$5,C46:Z46) -> 9700 | AE46: =SUMIF($C$5:$Z$5,$AD$5,D46:AA46) -> 9000 | AF46: =AA46-AD46 -> 0 | AG46: =AB46-AE46 -> 0 | AH46: =SUM('[1]2024年全面预算利润表 (销售1中心)2.8亿'!E51:H51) -> 5600
A47: 生日礼品 | C47: ='2025年中心利润表 '!C47+'2025年江苏分部利润表'!C47+'2025年浙江分部利润表'!C47+'2025年上海分部利润表'!C47+'2025年赣皖区域利润表'!C47 -> 0 | D47: ='2025年中心利润表 '!D47+'2025年江苏分部利润表'!D47+'2025年浙江分部利润表'!D47+'2025年上海分部利润表'!D47+'2025年赣皖区域利润表'!D47 -> 0 | E47: ='2025年中心利润表 '!E47+'2025年江苏分部利润表'!E47+'2025年浙江分部利润表'!E47+'2025年上海分部利润表'!E47+'2025年赣皖区域利润表'!E47 -> 0 | F47: ='2025年中心利润表 '!F47+'2025年江苏分部利润表'!F47+'2025年浙江分部利润表'!F47+'2025年上海分部利润表'!F47+'2025年赣皖区域利润表'!F47 -> 0 | G47: ='2025年中心利润表 '!G47+'2025年江苏分部利润表'!G47+'2025年浙江分部利润表'!G47+'2025年上海分部利润表'!G47+'2025年赣皖区域利润表'!G47 -> 1100 | H47: ='2025年中心利润表 '!H47+'2025年江苏分部利润表'!H47+'2025年浙江分部利润表'!H47+'2025年上海分部利润表'!H47+'2025年赣皖区域利润表'!H47 -> 0 | I47: ='2025年中心利润表 '!I47+'2025年江苏分部利润表'!I47+'2025年浙江分部利润表'!I47+'2025年上海分部利润表'!I47+'2025年赣皖区域利润表'!I47 -> 0 | J47: ='2025年中心利润表 '!J47+'2025年江苏分部利润表'!J47+'2025年浙江分部利润表'!J47+'2025年上海分部利润表'!J47+'2025年赣皖区域利润表'!J47 -> 0 | ... Z47: ='2025年中心利润表 '!Z47+'2025年江苏分部利润表'!Z47+'2025年浙江分部利润表'!Z47+'2025年上海分部利润表'!Z47+'2025年赣皖区域利润表'!Z47 -> 0 | AA47: =C47+E47+G47+I47+K47+M47+O47+Q47+S47+U47+W47+Y47 -> 1320 | AB47: =D47+F47+H47+J47+L47+N47+P47+R47+T47+V47+X47+Z47 -> 0 | AD47: =SUMIF($C$5:$Z$5,$AD$5,C47:Z47) -> 1320 | AE47: =SUMIF($C$5:$Z$5,$AD$5,D47:AA47) -> 0 | AF47: =AA47-AD47 -> 0 | AG47: =AB47-AE47 -> 0 | AH47: =SUM('[1]2024年全面预算利润表 (销售1中心)2.8亿'!E52:H52) -> 300
A48: 体检 | C48: ='2025年中心利润表 '!C48+'2025年江苏分部利润表'!C48+'2025年浙江分部利润表'!C48+'2025年上海分部利润表'!C48+'2025年赣皖区域利润表'!C48 -> 0 | D48: ='2025年中心利润表 '!D48+'2025年江苏分部利润表'!D48+'2025年浙江分部利润表'!D48+'2025年上海分部利润表'!D48+'2025年赣皖区域利润表'!D48 -> 0 | E48: ='2025年中心利润表 '!E48+'2025年江苏分部利润表'!E48+'2025年浙江分部利润表'!E48+'2025年上海分部利润表'!E48+'2025年赣皖区域利润表'!E48 -> 0 | F48: ='2025年中心利润表 '!F48+'2025年江苏分部利润表'!F48+'2025年浙江分部利润表'!F48+'2025年上海分部利润表'!F48+'2025年赣皖区域利润表'!F48 -> 8000 | G48: ='2025年中心利润表 '!G48+'2025年江苏分部利润表'!G48+'2025年浙江分部利润表'!G48+'2025年上海分部利润表'!G48+'2025年赣皖区域利润表'!G48 -> 0 | H48: ='2025年中心利润表 '!H48+'2025年江苏分部利润表'!H48+'2025年浙江分部利润表'!H48+'2025年上海分部利润表'!H48+'2025年赣皖区域利润表'!H48 -> 0 | I48: ='2025年中心利润表 '!I48+'2025年江苏分部利润表'!I48+'2025年浙江分部利润表'!I48+'2025年上海分部利润表'!I48+'2025年赣皖区域利润表'!I48 -> 0 | J48: ='2025年中心利润表 '!J48+'2025年江苏分部利润表'!J48+'2025年浙江分部利润表'!J48+'2025年上海分部利润表'!J48+'2025年赣皖区域利润表'!J48 -> 0 | ... Z48: ='2025年中心利润表 '!Z48+'2025年江苏分部利润表'!Z48+'2025年浙江分部利润表'!Z48+'2025年上海分部利润表'!Z48+'2025年赣皖区域利润表'!Z48 -> 0 | AA48: =C48+E48+G48+I48+K48+M48+O48+Q48+S48+U48+W48+Y48 -> 0 | AB48: =D48+F48+H48+J48+L48+N48+P48+R48+T48+V48+X48+Z48 -> 8000 | AD48: =SUMIF($C$5:$Z$5,$AD$5,C48:Z48) -> 0 | AE48: =SUMIF($C$5:$Z$5,$AD$5,D48:AA48) -> 8000 | AF48: =AA48-AD48 -> 0 | AG48: =AB48-AE48 -> 0 | AH48: =SUM('[1]2024年全面预算利润表 (销售1中心)2.8亿'!E53:H53) -> 0
A49: 其他福利支出 | C49: ='2025年中心利润表 '!C49+'2025年江苏分部利润表'!C49+'2025年浙江分部利润表'!C49+'2025年上海分部利润表'!C49+'2025年赣皖区域利润表'!C49 -> 420 | D49: ='2025年中心利润表 '!D49+'2025年江苏分部利润表'!D49+'2025年浙江分部利润表'!D49+'2025年上海分部利润表'!D49+'2025年赣皖区域利润表'!D49 -> 0 | E49: ='2025年中心利润表 '!E49+'2025年江苏分部利润表'!E49+'2025年浙江分部利润表'!E49+'2025年上海分部利润表'!E49+'2025年赣皖区域利润表'!E49 -> 0 | F49: ='2025年中心利润表 '!F49+'2025年江苏分部利润表'!F49+'2025年浙江分部利润表'!F49+'2025年上海分部利润表'!F49+'2025年赣皖区域利润表'!F49 -> 2694.85 | G49: ='2025年中心利润表 '!G49+'2025年江苏分部利润表'!G49+'2025年浙江分部利润表'!G49+'2025年上海分部利润表'!G49+'2025年赣皖区域利润表'!G49 -> 0 | H49: ='2025年中心利润表 '!H49+'2025年江苏分部利润表'!H49+'2025年浙江分部利润表'!H49+'2025年上海分部利润表'!H49+'2025年赣皖区域利润表'!H49 -> 1000 | I49: ='2025年中心利润表 '!I49+'2025年江苏分部利润表'!I49+'2025年浙江分部利润表'!I49+'2025年上海分部利润表'!I49+'2025年赣皖区域利润表'!I49 -> 420 | J49: ='2025年中心利润表 '!J49+'2025年江苏分部利润表'!J49+'2025年浙江分部利润表'!J49+'2025年上海分部利润表'!J49+'2025年赣皖区域利润表'!J49 -> 0 | ... Z49: ='2025年中心利润表 '!Z49+'2025年江苏分部利润表'!Z49+'2025年浙江分部利润表'!Z49+'2025年上海分部利润表'!Z49+'2025年赣皖区域利润表'!Z49 -> 0 | AA49: =C49+E49+G49+I49+K49+M49+O49+Q49+S49+U49+W49+Y49 -> 1680 | AB49: =D49+F49+H49+J49+L49+N49+P49+R49+T49+V49+X49+Z49 -> 5246.85 | AD49: =SUMIF($C$5:$Z$5,$AD$5,C49:Z49) -> 1680 | AE49: =SUMIF($C$5:$Z$5,$AD$5,D49:AA49) -> 5246.85 | AF49: =AA49-AD49 -> 0 | AG49: =AB49-AE49 -> 0 | AH49: =SUM('[1]2024年全面预算利润表 (销售1中心)2.8亿'!E54:H54) -> 3000
A50: 招聘费 | C50: ='2025年中心利润表 '!C50+'2025年江苏分部利润表'!C50+'2025年浙江分部利润表'!C50+'2025年上海分部利润表'!C50+'2025年赣皖区域利润表'!C50 -> 0 | D50: ='2025年中心利润表 '!D50+'2025年江苏分部利润表'!D50+'2025年浙江分部利润表'!D50+'2025年上海分部利润表'!D50+'2025年赣皖区域利润表'!D50 -> 0 | E50: ='2025年中心利润表 '!E50+'2025年江苏分部利润表'!E50+'2025年浙江分部利润表'!E50+'2025年上海分部利润表'!E50+'2025年赣皖区域利润表'!E50 -> 0 | F50: ='2025年中心利润表 '!F50+'2025年江苏分部利润表'!F50+'2025年浙江分部利润表'!F50+'2025年上海分部利润表'!F50+'2025年赣皖区域利润表'!F50 -> 0 | G50: ='2025年中心利润表 '!G50+'2025年江苏分部利润表'!G50+'2025年浙江分部利润表'!G50+'2025年上海分部利润表'!G50+'2025年赣皖区域利润表'!G50 -> 0 | H50: ='2025年中心利润表 '!H50+'2025年江苏分部利润表'!H50+'2025年浙江分部利润表'!H50+'2025年上海分部利润表'!H50+'2025年赣皖区域利润表'!H50 -> 0 | I50: ='2025年中心利润表 '!I50+'2025年江苏分部利润表'!I50+'2025年浙江分部利润表'!I50+'2025年上海分部利润表'!I50+'2025年赣皖区域利润表'!I50 -> 0 | J50: ='2025年中心利润表 '!J50+'2025年江苏分部利润表'!J50+'2025年浙江分部利润表'!J50+'2025年上海分部利润表'!J50+'2025年赣皖区域利润表'!J50 -> 0 | ... Z50: ='2025年中心利润表 '!Z50+'2025年江苏分部利润表'!Z50+'2025年浙江分部利润表'!Z50+'2025年上海分部利润表'!Z50+'2025年赣皖区域利润表'!Z50 -> 0 | AA50: =C50+E50+G50+I50+K50+M50+O50+Q50+S50+U50+W50+Y50 -> 0 | AB50: =D50+F50+H50+J50+L50+N50+P50+R50+T50+V50+X50+Z50 -> 1000 | AD50: =SUMIF($C$5:$Z$5,$AD$5,C50:Z50) -> 0 | AE50: =SUMIF($C$5:$Z$5,$AD$5,D50:AA50) -> 1000 | AF50: =AA50-AD50 -> 0 | AG50: =AB50-AE50 -> 0 | AH50: =SUM('[1]2024年全面预算利润表 (销售1中心)2.8亿'!E55:H55) -> 0
A51: 办公费 | C51: ='2025年中心利润表 '!C51+'2025年江苏分部利润表'!C51+'2025年浙江分部利润表'!C51+'2025年上海分部利润表'!C51+'2025年赣皖区域利润表'!C51 -> 0 | D51: ='2025年中心利润表 '!D51+'2025年江苏分部利润表'!D51+'2025年浙江分部利润表'!D51+'2025年上海分部利润表'!D51+'2025年赣皖区域利润表'!D51 -> 0 | E51: ='2025年中心利润表 '!E51+'2025年江苏分部利润表'!E51+'2025年浙江分部利润表'!E51+'2025年上海分部利润表'!E51+'2025年赣皖区域利润表'!E51 -> 0 | F51: ='2025年中心利润表 '!F51+'2025年江苏分部利润表'!F51+'2025年浙江分部利润表'!F51+'2025年上海分部利润表'!F51+'2025年赣皖区域利润表'!F51 -> 190 | G51: ='2025年中心利润表 '!G51+'2025年江苏分部利润表'!G51+'2025年浙江分部利润表'!G51+'2025年上海分部利润表'!G51+'2025年赣皖区域利润表'!G51 -> 0 | H51: ='2025年中心利润表 '!H51+'2025年江苏分部利润表'!H51+'2025年浙江分部利润表'!H51+'2025年上海分部利润表'!H51+'2025年赣皖区域利润表'!H51 -> 210 | I51: ='2025年中心利润表 '!I51+'2025年江苏分部利润表'!I51+'2025年浙江分部利润表'!I51+'2025年上海分部利润表'!I51+'2025年赣皖区域利润表'!I51 -> 0 | J51: ='2025年中心利润表 '!J51+'2025年江苏分部利润表'!J51+'2025年浙江分部利润表'!J51+'2025年上海分部利润表'!J51+'2025年赣皖区域利润表'!J51 -> 0 | ... Z51: ='2025年中心利润表 '!Z51+'2025年江苏分部利润表'!Z51+'2025年浙江分部利润表'!Z51+'2025年上海分部利润表'!Z51+'2025年赣皖区域利润表'!Z51 -> 225 | AA51: =C51+E51+G51+I51+K51+M51+O51+Q51+S51+U51+W51+Y51 -> 0 | AB51: =D51+F51+H51+J51+L51+N51+P51+R51+T51+V51+X51+Z51 -> 1483 | AD51: =SUMIF($C$5:$Z$5,$AD$5,C51:Z51) -> 0 | AE51: =SUMIF($C$5:$Z$5,$AD$5,D51:AA51) -> 1483 | AF51: =AA51-AD51 -> 0 | AG51: =AB51-AE51 -> 0 | AH51: =SUM('[1]2024年全面预算利润表 (销售1中心)2.8亿'!E56:H56) -> 0
A52: 市内交通费 | C52: ='2025年中心利润表 '!C52+'2025年江苏分部利润表'!C52+'2025年浙江分部利润表'!C52+'2025年上海分部利润表'!C52+'2025年赣皖区域利润表'!C52 -> 0 | D52: ='2025年中心利润表 '!D52+'2025年江苏分部利润表'!D52+'2025年浙江分部利润表'!D52+'2025年上海分部利润表'!D52+'2025年赣皖区域利润表'!D52 -> 0 | E52: ='2025年中心利润表 '!E52+'2025年江苏分部利润表'!E52+'2025年浙江分部利润表'!E52+'2025年上海分部利润表'!E52+'2025年赣皖区域利润表'!E52 -> 0 | F52: ='2025年中心利润表 '!F52+'2025年江苏分部利润表'!F52+'2025年浙江分部利润表'!F52+'2025年上海分部利润表'!F52+'2025年赣皖区域利润表'!F52 -> 0 | G52: ='2025年中心利润表 '!G52+'2025年江苏分部利润表'!G52+'2025年浙江分部利润表'!G52+'2025年上海分部利润表'!G52+'2025年赣皖区域利润表'!G52 -> 0 | H52: ='2025年中心利润表 '!H52+'2025年江苏分部利润表'!H52+'2025年浙江分部利润表'!H52+'2025年上海分部利润表'!H52+'2025年赣皖区域利润表'!H52 -> 0 | I52: ='2025年中心利润表 '!I52+'2025年江苏分部利润表'!I52+'2025年浙江分部利润表'!I52+'2025年上海分部利润表'!I52+'2025年赣皖区域利润表'!I52 -> 0 | J52: ='2025年中心利润表 '!J52+'2025年江苏分部利润表'!J52+'2025年浙江分部利润表'!J52+'2025年上海分部利润表'!J52+'2025年赣皖区域利润表'!J52 -> 0 | ... Z52: ='2025年中心利润表 '!Z52+'2025年江苏分部利润表'!Z52+'2025年浙江分部利润表'!Z52+'2025年上海分部利润表'!Z52+'2025年赣皖区域利润表'!Z52 -> 0 | AA52: =C52+E52+G52+I52+K52+M52+O52+Q52+S52+U52+W52+Y52 -> 0 | AB52: =D52+F52+H52+J52+L52+N52+P52+R52+T52+V52+X52+Z52 -> 0 | AD52: =SUMIF($C$5:$Z$5,$AD$5,C52:Z52) -> 0 | AE52: =SUMIF($C$5:$Z$5,$AD$5,D52:AA52) -> 0 | AF52: =AA52-AD52 -> 0 | AG52: =AB52-AE52 -> 0 | AH52: =SUM('[1]2024年全面预算利润表 (销售1中心)2.8亿'!E57:H57) -> 0
A53: 差旅费 | C53: =SUM(C54:C58) -> 94918.33 | D53: =SUM(D54:D58) -> 107463.04 | E53: =SUM(E54:E58) -> 94918.33 | F53: =SUM(F54:F58) -> 71610.01 | G53: =SUM(G54:G58) -> 102918.33 | H53: =SUM(H54:H58) -> 101321.71 | I53: =SUM(I54:I58) -> 102918.33 | J53: =SUM(J54:J58) -> 105291.55 | ... Z53: =SUM(Z54:Z58) -> 102211.9 | AA53: =C53+E53+G53+I53+K53+M53+O53+Q53+S53+U53+W53+Y53 -> 1219020 | AB53: =D53+F53+H53+J53+L53+N53+P53+R53+T53+V53+X53+Z53 -> 1142075.9 | AD53: =SUMIF($C$5:$Z$5,$AD$5,C53:Z53) -> 1219020 | AE53: =SUMIF($C$5:$Z$5,$AD$5,D53:AA53) -> 1142075.9 | AF53: =AA53-AD53 -> 0 | AG53: =AB53-AE53 -> 0 | AH53: =SUM('[1]2024年全面预算利润表 (销售1中心)2.8亿'!E58:H58) -> 439629.48
A54: 交通费 | C54: ='2025年中心利润表 '!C54+'2025年江苏分部利润表'!C54+'2025年浙江分部利润表'!C54+'2025年上海分部利润表'!C54+'2025年赣皖区域利润表'!C54 -> 24150 | D54: ='2025年中心利润表 '!D54+'2025年江苏分部利润表'!D54+'2025年浙江分部利润表'!D54+'2025年上海分部利润表'!D54+'2025年赣皖区域利润表'!D54 -> 20483.28 | E54: ='2025年中心利润表 '!E54+'2025年江苏分部利润表'!E54+'2025年浙江分部利润表'!E54+'2025年上海分部利润表'!E54+'2025年赣皖区域利润表'!E54 -> 24150 | F54: ='2025年中心利润表 '!F54+'2025年江苏分部利润表'!F54+'2025年浙江分部利润表'!F54+'2025年上海分部利润表'!F54+'2025年赣皖区域利润表'!F54 -> 26961.02 | G54: ='2025年中心利润表 '!G54+'2025年江苏分部利润表'!G54+'2025年浙江分部利润表'!G54+'2025年上海分部利润表'!G54+'2025年赣皖区域利润表'!G54 -> 27150 | H54: ='2025年中心利润表 '!H54+'2025年江苏分部利润表'!H54+'2025年浙江分部利润表'!H54+'2025年上海分部利润表'!H54+'2025年赣皖区域利润表'!H54 -> 32311.71 | I54: ='2025年中心利润表 '!I54+'2025年江苏分部利润表'!I54+'2025年浙江分部利润表'!I54+'2025年上海分部利润表'!I54+'2025年赣皖区域利润表'!I54 -> 27150 | J54: ='2025年中心利润表 '!J54+'2025年江苏分部利润表'!J54+'2025年浙江分部利润表'!J54+'2025年上海分部利润表'!J54+'2025年赣皖区域利润表'!J54 -> 39471.56 | ... Z54: ='2025年中心利润表 '!Z54+'2025年江苏分部利润表'!Z54+'2025年浙江分部利润表'!Z54+'2025年上海分部利润表'!Z54+'2025年赣皖区域利润表'!Z54 -> 33468.42 | AA54: =C54+E54+G54+I54+K54+M54+O54+Q54+S54+U54+W54+Y54 -> 319800 | AB54: =D54+F54+H54+J54+L54+N54+P54+R54+T54+V54+X54+Z54 -> 393941.85 | AD54: =SUMIF($C$5:$Z$5,$AD$5,C54:Z54) -> 319800 | AE54: =SUMIF($C$5:$Z$5,$AD$5,D54:AA54) -> 393941.85 | AF54: =AA54-AD54 -> 0 | AG54: =AB54-AE54 -> 0 | AH54: =SUM('[1]2024年全面预算利润表 (销售1中心)2.8亿'!E59:H59) -> 109937.93
A55: 住宿费 | C55: ='2025年中心利润表 '!C55+'2025年江苏分部利润表'!C55+'2025年浙江分部利润表'!C55+'2025年上海分部利润表'!C55+'2025年赣皖区域利润表'!C55 -> 30743.33 | D55: ='2025年中心利润表 '!D55+'2025年江苏分部利润表'!D55+'2025年浙江分部利润表'!D55+'2025年上海分部利润表'!D55+'2025年赣皖区域利润表'!D55 -> 38717.76 | E55: ='2025年中心利润表 '!E55+'2025年江苏分部利润表'!E55+'2025年浙江分部利润表'!E55+'2025年上海分部利润表'!E55+'2025年赣皖区域利润表'!E55 -> 30743.33 | F55: ='2025年中心利润表 '!F55+'2025年江苏分部利润表'!F55+'2025年浙江分部利润表'!F55+'2025年上海分部利润表'!F55+'2025年赣皖区域利润表'!F55 -> 19647.61 | G55: ='2025年中心利润表 '!G55+'2025年江苏分部利润表'!G55+'2025年浙江分部利润表'!G55+'2025年上海分部利润表'!G55+'2025年赣皖区域利润表'!G55 -> 35743.33 | H55: ='2025年中心利润表 '!H55+'2025年江苏分部利润表'!H55+'2025年浙江分部利润表'!H55+'2025年上海分部利润表'!H55+'2025年赣皖区域利润表'!H55 -> 30397.87 | I55: ='2025年中心利润表 '!I55+'2025年江苏分部利润表'!I55+'2025年浙江分部利润表'!I55+'2025年上海分部利润表'!I55+'2025年赣皖区域利润表'!I55 -> 35743.33 | J55: ='2025年中心利润表 '!J55+'2025年江苏分部利润表'!J55+'2025年浙江分部利润表'!J55+'2025年上海分部利润表'!J55+'2025年赣皖区域利润表'!J55 -> 26166.39 | ... Z55: ='2025年中心利润表 '!Z55+'2025年江苏分部利润表'!Z55+'2025年浙江分部利润表'!Z55+'2025年上海分部利润表'!Z55+'2025年赣皖区域利润表'!Z55 -> 32682.98 | AA55: =C55+E55+G55+I55+K55+M55+O55+Q55+S55+U55+W55+Y55 -> 418920 | AB55: =D55+F55+H55+J55+L55+N55+P55+R55+T55+V55+X55+Z55 -> 320823.01 | AD55: =SUMIF($C$5:$Z$5,$AD$5,C55:Z55) -> 418920 | AE55: =SUMIF($C$5:$Z$5,$AD$5,D55:AA55) -> 320823.01 | AF55: =AA55-AD55 -> 0 | AG55: =AB55-AE55 -> 0 | AH55: =SUM('[1]2024年全面预算利润表 (销售1中心)2.8亿'!E60:H60) -> 173840
A56: 餐费 | C56: ='2025年中心利润表 '!C56+'2025年江苏分部利润表'!C56+'2025年浙江分部利润表'!C56+'2025年上海分部利润表'!C56+'2025年赣皖区域利润表'!C56 -> 29025 | D56: ='2025年中心利润表 '!D56+'2025年江苏分部利润表'!D56+'2025年浙江分部利润表'!D56+'2025年上海分部利润表'!D56+'2025年赣皖区域利润表'!D56 -> 42676 | E56: ='2025年中心利润表 '!E56+'2025年江苏分部利润表'!E56+'2025年浙江分部利润表'!E56+'2025年上海分部利润表'!E56+'2025年赣皖区域利润表'!E56 -> 29025 | F56: ='2025年中心利润表 '!F56+'2025年江苏分部利润表'!F56+'2025年浙江分部利润表'!F56+'2025年上海分部利润表'!F56+'2025年赣皖区域利润表'!F56 -> 15084.8 | G56: ='2025年中心利润表 '!G56+'2025年江苏分部利润表'!G56+'2025年浙江分部利润表'!G56+'2025年上海分部利润表'!G56+'2025年赣皖区域利润表'!G56 -> 29025 | H56: ='2025年中心利润表 '!H56+'2025年江苏分部利润表'!H56+'2025年浙江分部利润表'!H56+'2025年上海分部利润表'!H56+'2025年赣皖区域利润表'!H56 -> 27947.03 | I56: ='2025年中心利润表 '!I56+'2025年江苏分部利润表'!I56+'2025年浙江分部利润表'!I56+'2025年上海分部利润表'!I56+'2025年赣皖区域利润表'!I56 -> 29025 | J56: ='2025年中心利润表 '!J56+'2025年江苏分部利润表'!J56+'2025年浙江分部利润表'!J56+'2025年上海分部利润表'!J56+'2025年赣皖区域利润表'!J56 -> 28453.8 | ... Z56: ='2025年中心利润表 '!Z56+'2025年江苏分部利润表'!Z56+'2025年浙江分部利润表'!Z56+'2025年上海分部利润表'!Z56+'2025年赣皖区域利润表'!Z56 -> 26350 | AA56: =C56+E56+G56+I56+K56+M56+O56+Q56+S56+U56+W56+Y56 -> 348300 | AB56: =D56+F56+H56+J56+L56+N56+P56+R56+T56+V56+X56+Z56 -> 311421.55 | AD56: =SUMIF($C$5:$Z$5,$AD$5,C56:Z56) -> 348300 | AE56: =SUMIF($C$5:$Z$5,$AD$5,D56:AA56) -> 311421.55 | AF56: =AA56-AD56 -> 0 | AG56: =AB56-AE56 -> 0 | AH56: =SUM('[1]2024年全面预算利润表 (销售1中心)2.8亿'!E61:H61) -> 113355
A57: 交通补助 | C57: ='2025年中心利润表 '!C57+'2025年江苏分部利润表'!C57+'2025年浙江分部利润表'!C57+'2025年上海分部利润表'!C57+'2025年赣皖区域利润表'!C57 -> 8600 | D57: ='2025年中心利润表 '!D57+'2025年江苏分部利润表'!D57+'2025年浙江分部利润表'!D57+'2025年上海分部利润表'!D57+'2025年赣皖区域利润表'!D57 -> 4240 | E57: ='2025年中心利润表 '!E57+'2025年江苏分部利润表'!E57+'2025年浙江分部利润表'!E57+'2025年上海分部利润表'!E57+'2025年赣皖区域利润表'!E57 -> 8600 | F57: ='2025年中心利润表 '!F57+'2025年江苏分部利润表'!F57+'2025年浙江分部利润表'!F57+'2025年上海分部利润表'!F57+'2025年赣皖区域利润表'!F57 -> 7700.78 | G57: ='2025年中心利润表 '!G57+'2025年江苏分部利润表'!G57+'2025年浙江分部利润表'!G57+'2025年上海分部利润表'!G57+'2025年赣皖区域利润表'!G57 -> 8600 | H57: ='2025年中心利润表 '!H57+'2025年江苏分部利润表'!H57+'2025年浙江分部利润表'!H57+'2025年上海分部利润表'!H57+'2025年赣皖区域利润表'!H57 -> 8028 | I57: ='2025年中心利润表 '!I57+'2025年江苏分部利润表'!I57+'2025年浙江分部利润表'!I57+'2025年上海分部利润表'!I57+'2025年赣皖区域利润表'!I57 -> 8600 | J57: ='2025年中心利润表 '!J57+'2025年江苏分部利润表'!J57+'2025年浙江分部利润表'!J57+'2025年上海分部利润表'!J57+'2025年赣皖区域利润表'!J57 -> 8500 | ... Z57: ='2025年中心利润表 '!Z57+'2025年江苏分部利润表'!Z57+'2025年浙江分部利润表'!Z57+'2025年上海分部利润表'!Z57+'2025年赣皖区域利润表'!Z57 -> 7700 | AA57: =C57+E57+G57+I57+K57+M57+O57+Q57+S57+U57+W57+Y57 -> 103200 | AB57: =D57+F57+H57+J57+L57+N57+P57+R57+T57+V57+X57+Z57 -> 88741.14 | AD57: =SUMIF($C$5:$Z$5,$AD$5,C57:Z57) -> 103200 | AE57: =SUMIF($C$5:$Z$5,$AD$5,D57:AA57) -> 88741.14 | AF57: =AA57-AD57 -> 0 | AG57: =AB57-AE57 -> 0 | AH57: =SUM('[1]2024年全面预算利润表 (销售1中心)2.8亿'!E62:H62) -> 33137.931
A58: 通讯补助 | C58: ='2025年中心利润表 '!C58+'2025年江苏分部利润表'!C58+'2025年浙江分部利润表'!C58+'2025年上海分部利润表'!C58+'2025年赣皖区域利润表'!C58 -> 2400 | D58: ='2025年中心利润表 '!D58+'2025年江苏分部利润表'!D58+'2025年浙江分部利润表'!D58+'2025年上海分部利润表'!D58+'2025年赣皖区域利润表'!D58 -> 1346 | E58: ='2025年中心利润表 '!E58+'2025年江苏分部利润表'!E58+'2025年浙江分部利润表'!E58+'2025年上海分部利润表'!E58+'2025年赣皖区域利润表'!E58 -> 2400 | F58: ='2025年中心利润表 '!F58+'2025年江苏分部利润表'!F58+'2025年浙江分部利润表'!F58+'2025年上海分部利润表'!F58+'2025年赣皖区域利润表'!F58 -> 2215.8 | G58: ='2025年中心利润表 '!G58+'2025年江苏分部利润表'!G58+'2025年浙江分部利润表'!G58+'2025年上海分部利润表'!G58+'2025年赣皖区域利润表'!G58 -> 2400 | H58: ='2025年中心利润表 '!H58+'2025年江苏分部利润表'!H58+'2025年浙江分部利润表'!H58+'2025年上海分部利润表'!H58+'2025年赣皖区域利润表'!H58 -> 2637.1 | I58: ='2025年中心利润表 '!I58+'2025年江苏分部利润表'!I58+'2025年浙江分部利润表'!I58+'2025年上海分部利润表'!I58+'2025年赣皖区域利润表'!I58 -> 2400 | J58: ='2025年中心利润表 '!J58+'2025年江苏分部利润表'!J58+'2025年浙江分部利润表'!J58+'2025年上海分部利润表'!J58+'2025年赣皖区域利润表'!J58 -> 2699.8 | ... Z58: ='2025年中心利润表 '!Z58+'2025年江苏分部利润表'!Z58+'2025年浙江分部利润表'!Z58+'2025年上海分部利润表'!Z58+'2025年赣皖区域利润表'!Z58 -> 2010.5 | AA58: =C58+E58+G58+I58+K58+M58+O58+Q58+S58+U58+W58+Y58 -> 28800 | AB58: =D58+F58+H58+J58+L58+N58+P58+R58+T58+V58+X58+Z58 -> 27148.4 | AD58: =SUMIF($C$5:$Z$5,$AD$5,C58:Z58) -> 28800 | AE58: =SUMIF($C$5:$Z$5,$AD$5,D58:AA58) -> 27148.4 | AF58: =AA58-AD58 -> 0 | AG58: =AB58-AE58 -> 0 | AH58: =SUM('[1]2024年全面预算利润表 (销售1中心)2.8亿'!E63:H63) -> 9358.6207
A59: 招待费 | C59: ='2025年中心利润表 '!C59+'2025年江苏分部利润表'!C59+'2025年浙江分部利润表'!C59+'2025年上海分部利润表'!C59+'2025年赣皖区域利润表'!C59 -> 63983.33 | D59: ='2025年中心利润表 '!D59+'2025年江苏分部利润表'!D59+'2025年浙江分部利润表'!D59+'2025年上海分部利润表'!D59+'2025年赣皖区域利润表'!D59 -> 56005.21 | E59: ='2025年中心利润表 '!E59+'2025年江苏分部利润表'!E59+'2025年浙江分部利润表'!E59+'2025年上海分部利润表'!E59+'2025年赣皖区域利润表'!E59 -> 17983.33 | F59: ='2025年中心利润表 '!F59+'2025年江苏分部利润表'!F59+'2025年浙江分部利润表'!F59+'2025年上海分部利润表'!F59+'2025年赣皖区域利润表'!F59 -> 18499 | G59: ='2025年中心利润表 '!G59+'2025年江苏分部利润表'!G59+'2025年浙江分部利润表'!G59+'2025年上海分部利润表'!G59+'2025年赣皖区域利润表'!G59 -> 58983.33 | H59: ='2025年中心利润表 '!H59+'2025年江苏分部利润表'!H59+'2025年浙江分部利润表'!H59+'2025年上海分部利润表'!H59+'2025年赣皖区域利润表'!H59 -> 22628.13 | I59: ='2025年中心利润表 '!I59+'2025年江苏分部利润表'!I59+'2025年浙江分部利润表'!I59+'2025年上海分部利润表'!I59+'2025年赣皖区域利润表'!I59 -> 17983.33 | J59: ='2025年中心利润表 '!J59+'2025年江苏分部利润表'!J59+'2025年浙江分部利润表'!J59+'2025年上海分部利润表'!J59+'2025年赣皖区域利润表'!J59 -> 41372.75 | ... Z59: ='2025年中心利润表 '!Z59+'2025年江苏分部利润表'!Z59+'2025年浙江分部利润表'!Z59+'2025年上海分部利润表'!Z59+'2025年赣皖区域利润表'!Z59 -> 15313.38 | AA59: =C59+E59+G59+I59+K59+M59+O59+Q59+S59+U59+W59+Y59 -> 317800 | AB59: =D59+F59+H59+J59+L59+N59+P59+R59+T59+V59+X59+Z59 -> 317453.7 | AD59: =SUMIF($C$5:$Z$5,$AD$5,C59:Z59) -> 317800 | AE59: =SUMIF($C$5:$Z$5,$AD$5,D59:AA59) -> 317453.7 | AF59: =AA59-AD59 -> 0 | AG59: =AB59-AE59 -> 0 | AH59: =SUM('[1]2024年全面预算利润表 (销售1中心)2.8亿'!E64:H64) -> 94800
A60: 通讯费 | C60: ='2025年中心利润表 '!C60+'2025年江苏分部利润表'!C60+'2025年浙江分部利润表'!C60+'2025年上海分部利润表'!C60+'2025年赣皖区域利润表'!C60 -> 0 | D60: ='2025年中心利润表 '!D60+'2025年江苏分部利润表'!D60+'2025年浙江分部利润表'!D60+'2025年上海分部利润表'!D60+'2025年赣皖区域利润表'!D60 -> 0 | E60: ='2025年中心利润表 '!E60+'2025年江苏分部利润表'!E60+'2025年浙江分部利润表'!E60+'2025年上海分部利润表'!E60+'2025年赣皖区域利润表'!E60 -> 0 | F60: ='2025年中心利润表 '!F60+'2025年江苏分部利润表'!F60+'2025年浙江分部利润表'!F60+'2025年上海分部利润表'!F60+'2025年赣皖区域利润表'!F60 -> 0 | G60: ='2025年中心利润表 '!G60+'2025年江苏分部利润表'!G60+'2025年浙江分部利润表'!G60+'2025年上海分部利润表'!G60+'2025年赣皖区域利润表'!G60 -> 0 | H60: ='2025年中心利润表 '!H60+'2025年江苏分部利润表'!H60+'2025年浙江分部利润表'!H60+'2025年上海分部利润表'!H60+'2025年赣皖区域利润表'!H60 -> 0 | I60: ='2025年中心利润表 '!I60+'2025年江苏分部利润表'!I60+'2025年浙江分部利润表'!I60+'2025年上海分部利润表'!I60+'2025年赣皖区域利润表'!I60 -> 0 | J60: ='2025年中心利润表 '!J60+'2025年江苏分部利润表'!J60+'2025年浙江分部利润表'!J60+'2025年上海分部利润表'!J60+'2025年赣皖区域利润表'!J60 -> 0 | ... Z60: ='2025年中心利润表 '!Z60+'2025年江苏分部利润表'!Z60+'2025年浙江分部利润表'!Z60+'2025年上海分部利润表'!Z60+'2025年赣皖区域利润表'!Z60 -> 0 | AA60: =C60+E60+G60+I60+K60+M60+O60+Q60+S60+U60+W60+Y60 -> 0 | AB60: =D60+F60+H60+J60+L60+N60+P60+R60+T60+V60+X60+Z60 -> 0 | AD60: =SUMIF($C$5:$Z$5,$AD$5,C60:Z60) -> 0 | AE60: =SUMIF($C$5:$Z$5,$AD$5,D60:AA60) -> 0 | AF60: =AA60-AD60 -> 0 | AG60: =AB60-AE60 -> 0 | AH60: =SUM('[1]2024年全面预算利润表 (销售1中心)2.8亿'!E65:H65) -> 0
A61: 网络费 | C61: ='2025年中心利润表 '!C61+'2025年江苏分部利润表'!C61+'2025年浙江分部利润表'!C61+'2025年上海分部利润表'!C61+'2025年赣皖区域利润表'!C61 -> 50 | D61: ='2025年中心利润表 '!D61+'2025年江苏分部利润表'!D61+'2025年浙江分部利润表'!D61+'2025年上海分部利润表'!D61+'2025年赣皖区域利润表'!D61 -> 0 | E61: ='2025年中心利润表 '!E61+'2025年江苏分部利润表'!E61+'2025年浙江分部利润表'!E61+'2025年上海分部利润表'!E61+'2025年赣皖区域利润表'!E61 -> 50 | F61: ='2025年中心利润表 '!F61+'2025年江苏分部利润表'!F61+'2025年浙江分部利润表'!F61+'2025年上海分部利润表'!F61+'2025年赣皖区域利润表'!F61 -> 0 | G61: ='2025年中心利润表 '!G61+'2025年江苏分部利润表'!G61+'2025年浙江分部利润表'!G61+'2025年上海分部利润表'!G61+'2025年赣皖区域利润表'!G61 -> 50 | H61: ='2025年中心利润表 '!H61+'2025年江苏分部利润表'!H61+'2025年浙江分部利润表'!H61+'2025年上海分部利润表'!H61+'2025年赣皖区域利润表'!H61 -> 0 | I61: ='2025年中心利润表 '!I61+'2025年江苏分部利润表'!I61+'2025年浙江分部利润表'!I61+'2025年上海分部利润表'!I61+'2025年赣皖区域利润表'!I61 -> 50 | J61: ='2025年中心利润表 '!J61+'2025年江苏分部利润表'!J61+'2025年浙江分部利润表'!J61+'2025年上海分部利润表'!J61+'2025年赣皖区域利润表'!J61 -> 0 | ... Z61: ='2025年中心利润表 '!Z61+'2025年江苏分部利润表'!Z61+'2025年浙江分部利润表'!Z61+'2025年上海分部利润表'!Z61+'2025年赣皖区域利润表'!Z61 -> 0 | AA61: =C61+E61+G61+I61+K61+M61+O61+Q61+S61+U61+W61+Y61 -> 600 | AB61: =D61+F61+H61+J61+L61+N61+P61+R61+T61+V61+X61+Z61 -> 0 | AD61: =SUMIF($C$5:$Z$5,$AD$5,C61:Z61) -> 600 | AE61: =SUMIF($C$5:$Z$5,$AD$5,D61:AA61) -> 0 | AF61: =AA61-AD61 -> 0 | AG61: =AB61-AE61 -> 0 | AH61: =SUM('[1]2024年全面预算利润表 (销售1中心)2.8亿'!E66:H66) -> 200
A62: 修理费 | C62: ='2025年中心利润表 '!C62+'2025年江苏分部利润表'!C62+'2025年浙江分部利润表'!C62+'2025年上海分部利润表'!C62+'2025年赣皖区域利润表'!C62 -> 0 | D62: ='2025年中心利润表 '!D62+'2025年江苏分部利润表'!D62+'2025年浙江分部利润表'!D62+'2025年上海分部利润表'!D62+'2025年赣皖区域利润表'!D62 -> 0 | E62: ='2025年中心利润表 '!E62+'2025年江苏分部利润表'!E62+'2025年浙江分部利润表'!E62+'2025年上海分部利润表'!E62+'2025年赣皖区域利润表'!E62 -> 0 | F62: ='2025年中心利润表 '!F62+'2025年江苏分部利润表'!F62+'2025年浙江分部利润表'!F62+'2025年上海分部利润表'!F62+'2025年赣皖区域利润表'!F62 -> 0 | G62: ='2025年中心利润表 '!G62+'2025年江苏分部利润表'!G62+'2025年浙江分部利润表'!G62+'2025年上海分部利润表'!G62+'2025年赣皖区域利润表'!G62 -> 0 | H62: ='2025年中心利润表 '!H62+'2025年江苏分部利润表'!H62+'2025年浙江分部利润表'!H62+'2025年上海分部利润表'!H62+'2025年赣皖区域利润表'!H62 -> 0 | I62: ='2025年中心利润表 '!I62+'2025年江苏分部利润表'!I62+'2025年浙江分部利润表'!I62+'2025年上海分部利润表'!I62+'2025年赣皖区域利润表'!I62 -> 0 | J62: ='2025年中心利润表 '!J62+'2025年江苏分部利润表'!J62+'2025年浙江分部利润表'!J62+'2025年上海分部利润表'!J62+'2025年赣皖区域利润表'!J62 -> 0 | ... Z62: ='2025年中心利润表 '!Z62+'2025年江苏分部利润表'!Z62+'2025年浙江分部利润表'!Z62+'2025年上海分部利润表'!Z62+'2025年赣皖区域利润表'!Z62 -> 0 | AA62: =C62+E62+G62+I62+K62+M62+O62+Q62+S62+U62+W62+Y62 -> 0 | AB62: =D62+F62+H62+J62+L62+N62+P62+R62+T62+V62+X62+Z62 -> 0 | AD62: =SUMIF($C$5:$Z$5,$AD$5,C62:Z62) -> 0 | AE62: =SUMIF($C$5:$Z$5,$AD$5,D62:AA62) -> 0 | AF62: =AA62-AD62 -> 0 | AG62: =AB62-AE62 -> 0 | AH62: =SUM('[1]2024年全面预算利润表 (销售1中心)2.8亿'!E67:H67) -> 0
A63: 车辆费 | C63: ='2025年中心利润表 '!C63+'2025年江苏分部利润表'!C63+'2025年浙江分部利润表'!C63+'2025年上海分部利润表'!C63+'2025年赣皖区域利润表'!C63 -> 0 | D63: ='2025年中心利润表 '!D63+'2025年江苏分部利润表'!D63+'2025年浙江分部利润表'!D63+'2025年上海分部利润表'!D63+'2025年赣皖区域利润表'!D63 -> 0 | E63: ='2025年中心利润表 '!E63+'2025年江苏分部利润表'!E63+'2025年浙江分部利润表'!E63+'2025年上海分部利润表'!E63+'2025年赣皖区域利润表'!E63 -> 0 | F63: ='2025年中心利润表 '!F63+'2025年江苏分部利润表'!F63+'2025年浙江分部利润表'!F63+'2025年上海分部利润表'!F63+'2025年赣皖区域利润表'!F63 -> 0 | G63: ='2025年中心利润表 '!G63+'2025年江苏分部利润表'!G63+'2025年浙江分部利润表'!G63+'2025年上海分部利润表'!G63+'2025年赣皖区域利润表'!G63 -> 0 | H63: ='2025年中心利润表 '!H63+'2025年江苏分部利润表'!H63+'2025年浙江分部利润表'!H63+'2025年上海分部利润表'!H63+'2025年赣皖区域利润表'!H63 -> 0 | I63: ='2025年中心利润表 '!I63+'2025年江苏分部利润表'!I63+'2025年浙江分部利润表'!I63+'2025年上海分部利润表'!I63+'2025年赣皖区域利润表'!I63 -> 0 | J63: ='2025年中心利润表 '!J63+'2025年江苏分部利润表'!J63+'2025年浙江分部利润表'!J63+'2025年上海分部利润表'!J63+'2025年赣皖区域利润表'!J63 -> 0 | ... Z63: ='2025年中心利润表 '!Z63+'2025年江苏分部利润表'!Z63+'2025年浙江分部利润表'!Z63+'2025年上海分部利润表'!Z63+'2025年赣皖区域利润表'!Z63 -> 0 | AA63: =C63+E63+G63+I63+K63+M63+O63+Q63+S63+U63+W63+Y63 -> 0 | AB63: =D63+F63+H63+J63+L63+N63+P63+R63+T63+V63+X63+Z63 -> 0 | AD63: =SUMIF($C$5:$Z$5,$AD$5,C63:Z63) -> 0 | AE63: =SUMIF($C$5:$Z$5,$AD$5,D63:AA63) -> 0 | AF63: =AA63-AD63 -> 0 | AG63: =AB63-AE63 -> 0 | AH63: =SUM('[1]2024年全面预算利润表 (销售1中心)2.8亿'!E68:H68) -> 0
A64: 租赁费 | C64: ='2025年中心利润表 '!C64+'2025年江苏分部利润表'!C64+'2025年浙江分部利润表'!C64+'2025年上海分部利润表'!C64+'2025年赣皖区域利润表'!C64 -> 19510 | D64: ='2025年中心利润表 '!D64+'2025年江苏分部利润表'!D64+'2025年浙江分部利润表'!D64+'2025年上海分部利润表'!D64+'2025年赣皖区域利润表'!D64 -> 17166.5 | E64: ='2025年中心利润表 '!E64+'2025年江苏分部利润表'!E64+'2025年浙江分部利润表'!E64+'2025年上海分部利润表'!E64+'2025年赣皖区域利润表'!E64 -> 19510 | F64: ='2025年中心利润表 '!F64+'2025年江苏分部利润表'!F64+'2025年浙江分部利润表'!F64+'2025年上海分部利润表'!F64+'2025年赣皖区域利润表'!F64 -> 16979 | G64: ='2025年中心利润表 '!G64+'2025年江苏分部利润表'!G64+'2025年浙江分部利润表'!G64+'2025年上海分部利润表'!G64+'2025年赣皖区域利润表'!G64 -> 19510 | H64: ='2025年中心利润表 '!H64+'2025年江苏分部利润表'!H64+'2025年浙江分部利润表'!H64+'2025年上海分部利润表'!H64+'2025年赣皖区域利润表'!H64 -> 16979 | I64: ='2025年中心利润表 '!I64+'2025年江苏分部利润表'!I64+'2025年浙江分部利润表'!I64+'2025年上海分部利润表'!I64+'2025年赣皖区域利润表'!I64 -> 19510 | J64: ='2025年中心利润表 '!J64+'2025年江苏分部利润表'!J64+'2025年浙江分部利润表'!J64+'2025年上海分部利润表'!J64+'2025年赣皖区域利润表'!J64 -> 17736 | ... Z64: ='2025年中心利润表 '!Z64+'2025年江苏分部利润表'!Z64+'2025年浙江分部利润表'!Z64+'2025年上海分部利润表'!Z64+'2025年赣皖区域利润表'!Z64 -> 17642.03 | AA64: =C64+E64+G64+I64+K64+M64+O64+Q64+S64+U64+W64+Y64 -> 234120 | AB64: =D64+F64+H64+J64+L64+N64+P64+R64+T64+V64+X64+Z64 -> 203657.99 | AD64: =SUMIF($C$5:$Z$5,$AD$5,C64:Z64) -> 234120 | AE64: =SUMIF($C$5:$Z$5,$AD$5,D64:AA64) -> 203657.99 | AF64: =AA64-AD64 -> 0 | AG64: =AB64-AE64 -> 0 | AH64: =SUM('[1]2024年全面预算利润表 (销售1中心)2.8亿'!E69:H69) -> 52000
A65: 能源费 | C65: =SUM(C66:C69) -> 150 | D65: =SUM(D66:D69) -> 0 | E65: =SUM(E66:E69) -> 150 | F65: =SUM(F66:F69) -> 0 | G65: =SUM(G66:G69) -> 150 | H65: =SUM(H66:H69) -> 0 | I65: =SUM(I66:I69) -> 150 | J65: =SUM(J66:J69) -> 0 | ... Z65: =SUM(Z66:Z69) -> 0 | AA65: =C65+E65+G65+I65+K65+M65+O65+Q65+S65+U65+W65+Y65 -> 1800 | AB65: =D65+F65+H65+J65+L65+N65+P65+R65+T65+V65+X65+Z65 -> 0 | AD65: =SUMIF($C$5:$Z$5,$AD$5,C65:Z65) -> 1800 | AE65: =SUMIF($C$5:$Z$5,$AD$5,D65:AA65) -> 0 | AF65: =AA65-AD65 -> 0 | AG65: =AB65-AE65 -> 0 | AH65: =SUM('[1]2024年全面预算利润表 (销售1中心)2.8亿'!E70:H70) -> 0
A66: 水费 | C66: ='2025年中心利润表 '!C66+'2025年江苏分部利润表'!C66+'2025年浙江分部利润表'!C66+'2025年上海分部利润表'!C66+'2025年赣皖区域利润表'!C66 -> 40 | D66: ='2025年中心利润表 '!D66+'2025年江苏分部利润表'!D66+'2025年浙江分部利润表'!D66+'2025年上海分部利润表'!D66+'2025年赣皖区域利润表'!D66 -> 0 | E66: ='2025年中心利润表 '!E66+'2025年江苏分部利润表'!E66+'2025年浙江分部利润表'!E66+'2025年上海分部利润表'!E66+'2025年赣皖区域利润表'!E66 -> 40 | F66: ='2025年中心利润表 '!F66+'2025年江苏分部利润表'!F66+'2025年浙江分部利润表'!F66+'2025年上海分部利润表'!F66+'2025年赣皖区域利润表'!F66 -> 0 | G66: ='2025年中心利润表 '!G66+'2025年江苏分部利润表'!G66+'2025年浙江分部利润表'!G66+'2025年上海分部利润表'!G66+'2025年赣皖区域利润表'!G66 -> 40 | H66: ='2025年中心利润表 '!H66+'2025年江苏分部利润表'!H66+'2025年浙江分部利润表'!H66+'2025年上海分部利润表'!H66+'2025年赣皖区域利润表'!H66 -> 0 | I66: ='2025年中心利润表 '!I66+'2025年江苏分部利润表'!I66+'2025年浙江分部利润表'!I66+'2025年上海分部利润表'!I66+'2025年赣皖区域利润表'!I66 -> 40 | J66: ='2025年中心利润表 '!J66+'2025年江苏分部利润表'!J66+'2025年浙江分部利润表'!J66+'2025年上海分部利润表'!J66+'2025年赣皖区域利润表'!J66 -> 0 | ... Z66: ='2025年中心利润表 '!Z66+'2025年江苏分部利润表'!Z66+'2025年浙江分部利润表'!Z66+'2025年上海分部利润表'!Z66+'2025年赣皖区域利润表'!Z66 -> 0 | AA66: =C66+E66+G66+I66+K66+M66+O66+Q66+S66+U66+W66+Y66 -> 480 | AB66: =D66+F66+H66+J66+L66+N66+P66+R66+T66+V66+X66+Z66 -> 0 | AD66: =SUMIF($C$5:$Z$5,$AD$5,C66:Z66) -> 480 | AE66: =SUMIF($C$5:$Z$5,$AD$5,D66:AA66) -> 0 | AF66: =AA66-AD66 -> 0 | AG66: =AB66-AE66 -> 0 | AH66: =SUM('[1]2024年全面预算利润表 (销售1中心)2.8亿'!E71:H71) -> 0
A67: 电费 | C67: ='2025年中心利润表 '!C67+'2025年江苏分部利润表'!C67+'2025年浙江分部利润表'!C67+'2025年上海分部利润表'!C67+'2025年赣皖区域利润表'!C67 -> 110 | D67: ='2025年中心利润表 '!D67+'2025年江苏分部利润表'!D67+'2025年浙江分部利润表'!D67+'2025年上海分部利润表'!D67+'2025年赣皖区域利润表'!D67 -> 0 | E67: ='2025年中心利润表 '!E67+'2025年江苏分部利润表'!E67+'2025年浙江分部利润表'!E67+'2025年上海分部利润表'!E67+'2025年赣皖区域利润表'!E67 -> 110 | F67: ='2025年中心利润表 '!F67+'2025年江苏分部利润表'!F67+'2025年浙江分部利润表'!F67+'2025年上海分部利润表'!F67+'2025年赣皖区域利润表'!F67 -> 0 | G67: ='2025年中心利润表 '!G67+'2025年江苏分部利润表'!G67+'2025年浙江分部利润表'!G67+'2025年上海分部利润表'!G67+'2025年赣皖区域利润表'!G67 -> 110 | H67: ='2025年中心利润表 '!H67+'2025年江苏分部利润表'!H67+'2025年浙江分部利润表'!H67+'2025年上海分部利润表'!H67+'2025年赣皖区域利润表'!H67 -> 0 | I67: ='2025年中心利润表 '!I67+'2025年江苏分部利润表'!I67+'2025年浙江分部利润表'!I67+'2025年上海分部利润表'!I67+'2025年赣皖区域利润表'!I67 -> 110 | J67: ='2025年中心利润表 '!J67+'2025年江苏分部利润表'!J67+'2025年浙江分部利润表'!J67+'2025年上海分部利润表'!J67+'2025年赣皖区域利润表'!J67 -> 0 | ... Z67: ='2025年中心利润表 '!Z67+'2025年江苏分部利润表'!Z67+'2025年浙江分部利润表'!Z67+'2025年上海分部利润表'!Z67+'2025年赣皖区域利润表'!Z67 -> 0 | AA67: =C67+E67+G67+I67+K67+M67+O67+Q67+S67+U67+W67+Y67 -> 1320 | AB67: =D67+F67+H67+J67+L67+N67+P67+R67+T67+V67+X67+Z67 -> 0 | AD67: =SUMIF($C$5:$Z$5,$AD$5,C67:Z67) -> 1320 | AE67: =SUMIF($C$5:$Z$5,$AD$5,D67:AA67) -> 0 | AF67: =AA67-AD67 -> 0 | AG67: =AB67-AE67 -> 0 | AH67: =SUM('[1]2024年全面预算利润表 (销售1中心)2.8亿'!E72:H72) -> 0
A68: 燃气费 | C68: ='2025年中心利润表 '!C68+'2025年江苏分部利润表'!C68+'2025年浙江分部利润表'!C68+'2025年上海分部利润表'!C68+'2025年赣皖区域利润表'!C68 -> 0 | D68: ='2025年中心利润表 '!D68+'2025年江苏分部利润表'!D68+'2025年浙江分部利润表'!D68+'2025年上海分部利润表'!D68+'2025年赣皖区域利润表'!D68 -> 0 | E68: ='2025年中心利润表 '!E68+'2025年江苏分部利润表'!E68+'2025年浙江分部利润表'!E68+'2025年上海分部利润表'!E68+'2025年赣皖区域利润表'!E68 -> 0 | F68: ='2025年中心利润表 '!F68+'2025年江苏分部利润表'!F68+'2025年浙江分部利润表'!F68+'2025年上海分部利润表'!F68+'2025年赣皖区域利润表'!F68 -> 0 | G68: ='2025年中心利润表 '!G68+'2025年江苏分部利润表'!G68+'2025年浙江分部利润表'!G68+'2025年上海分部利润表'!G68+'2025年赣皖区域利润表'!G68 -> 0 | H68: ='2025年中心利润表 '!H68+'2025年江苏分部利润表'!H68+'2025年浙江分部利润表'!H68+'2025年上海分部利润表'!H68+'2025年赣皖区域利润表'!H68 -> 0 | I68: ='2025年中心利润表 '!I68+'2025年江苏分部利润表'!I68+'2025年浙江分部利润表'!I68+'2025年上海分部利润表'!I68+'2025年赣皖区域利润表'!I68 -> 0 | J68: ='2025年中心利润表 '!J68+'2025年江苏分部利润表'!J68+'2025年浙江分部利润表'!J68+'2025年上海分部利润表'!J68+'2025年赣皖区域利润表'!J68 -> 0 | ... Z68: ='2025年中心利润表 '!Z68+'2025年江苏分部利润表'!Z68+'2025年浙江分部利润表'!Z68+'2025年上海分部利润表'!Z68+'2025年赣皖区域利润表'!Z68 -> 0 | AA68: =C68+E68+G68+I68+K68+M68+O68+Q68+S68+U68+W68+Y68 -> 0 | AB68: =D68+F68+H68+J68+L68+N68+P68+R68+T68+V68+X68+Z68 -> 0 | AD68: =SUMIF($C$5:$Z$5,$AD$5,C68:Z68) -> 0 | AE68: =SUMIF($C$5:$Z$5,$AD$5,D68:AA68) -> 0 | AF68: =AA68-AD68 -> 0 | AG68: =AB68-AE68 -> 0 | AH68: =SUM('[1]2024年全面预算利润表 (销售1中心)2.8亿'!E73:H73) -> 0
A69: 蒸汽费 | C69: ='2025年中心利润表 '!C69+'2025年江苏分部利润表'!C69+'2025年浙江分部利润表'!C69+'2025年上海分部利润表'!C69+'2025年赣皖区域利润表'!C69 -> 0 | D69: ='2025年中心利润表 '!D69+'2025年江苏分部利润表'!D69+'2025年浙江分部利润表'!D69+'2025年上海分部利润表'!D69+'2025年赣皖区域利润表'!D69 -> 0 | E69: ='2025年中心利润表 '!E69+'2025年江苏分部利润表'!E69+'2025年浙江分部利润表'!E69+'2025年上海分部利润表'!E69+'2025年赣皖区域利润表'!E69 -> 0 | F69: ='2025年中心利润表 '!F69+'2025年江苏分部利润表'!F69+'2025年浙江分部利润表'!F69+'2025年上海分部利润表'!F69+'2025年赣皖区域利润表'!F69 -> 0 | G69: ='2025年中心利润表 '!G69+'2025年江苏分部利润表'!G69+'2025年浙江分部利润表'!G69+'2025年上海分部利润表'!G69+'2025年赣皖区域利润表'!G69 -> 0 | H69: ='2025年中心利润表 '!H69+'2025年江苏分部利润表'!H69+'2025年浙江分部利润表'!H69+'2025年上海分部利润表'!H69+'2025年赣皖区域利润表'!H69 -> 0 | I69: ='2025年中心利润表 '!I69+'2025年江苏分部利润表'!I69+'2025年浙江分部利润表'!I69+'2025年上海分部利润表'!I69+'2025年赣皖区域利润表'!I69 -> 0 | J69: ='2025年中心利润表 '!J69+'2025年江苏分部利润表'!J69+'2025年浙江分部利润表'!J69+'2025年上海分部利润表'!J69+'2025年赣皖区域利润表'!J69 -> 0 | ... Z69: ='2025年中心利润表 '!Z69+'2025年江苏分部利润表'!Z69+'2025年浙江分部利润表'!Z69+'2025年上海分部利润表'!Z69+'2025年赣皖区域利润表'!Z69 -> 0 | AA69: =C69+E69+G69+I69+K69+M69+O69+Q69+S69+U69+W69+Y69 -> 0 | AB69: =D69+F69+H69+J69+L69+N69+P69+R69+T69+V69+X69+Z69 -> 0 | AD69: =SUMIF($C$5:$Z$5,$AD$5,C69:Z69) -> 0 | AE69: =SUMIF($C$5:$Z$5,$AD$5,D69:AA69) -> 0 | AF69: =AA69-AD69 -> 0 | AG69: =AB69-AE69 -> 0 | AH69: =SUM('[1]2024年全面预算利润表 (销售1中心)2.8亿'!E74:H74) -> 0
A70: 物业费 | C70: ='2025年中心利润表 '!C70+'2025年江苏分部利润表'!C70+'2025年浙江分部利润表'!C70+'2025年上海分部利润表'!C70+'2025年赣皖区域利润表'!C70 -> 0 | D70: ='2025年中心利润表 '!D70+'2025年江苏分部利润表'!D70+'2025年浙江分部利润表'!D70+'2025年上海分部利润表'!D70+'2025年赣皖区域利润表'!D70 -> 0 | E70: ='2025年中心利润表 '!E70+'2025年江苏分部利润表'!E70+'2025年浙江分部利润表'!E70+'2025年上海分部利润表'!E70+'2025年赣皖区域利润表'!E70 -> 0 | F70: ='2025年中心利润表 '!F70+'2025年江苏分部利润表'!F70+'2025年浙江分部利润表'!F70+'2025年上海分部利润表'!F70+'2025年赣皖区域利润表'!F70 -> 0 | G70: ='2025年中心利润表 '!G70+'2025年江苏分部利润表'!G70+'2025年浙江分部利润表'!G70+'2025年上海分部利润表'!G70+'2025年赣皖区域利润表'!G70 -> 0 | H70: ='2025年中心利润表 '!H70+'2025年江苏分部利润表'!H70+'2025年浙江分部利润表'!H70+'2025年上海分部利润表'!H70+'2025年赣皖区域利润表'!H70 -> 0 | I70: ='2025年中心利润表 '!I70+'2025年江苏分部利润表'!I70+'2025年浙江分部利润表'!I70+'2025年上海分部利润表'!I70+'2025年赣皖区域利润表'!I70 -> 0 | J70: ='2025年中心利润表 '!J70+'2025年江苏分部利润表'!J70+'2025年浙江分部利润表'!J70+'2025年上海分部利润表'!J70+'2025年赣皖区域利润表'!J70 -> 0 | ... Z70: ='2025年中心利润表 '!Z70+'2025年江苏分部利润表'!Z70+'2025年浙江分部利润表'!Z70+'2025年上海分部利润表'!Z70+'2025年赣皖区域利润表'!Z70 -> 0 | AA70: =C70+E70+G70+I70+K70+M70+O70+Q70+S70+U70+W70+Y70 -> 0 | AB70: =D70+F70+H70+J70+L70+N70+P70+R70+T70+V70+X70+Z70 -> 0 | AD70: =SUMIF($C$5:$Z$5,$AD$5,C70:Z70) -> 0 | AE70: =SUMIF($C$5:$Z$5,$AD$5,D70:AA70) -> 0 | AF70: =AA70-AD70 -> 0 | AG70: =AB70-AE70 -> 0 | AH70: =SUM('[1]2024年全面预算利润表 (销售1中心)2.8亿'!E75:H75) -> 0
A71: 劳动保护费 | C71: ='2025年中心利润表 '!C71+'2025年江苏分部利润表'!C71+'2025年浙江分部利润表'!C71+'2025年上海分部利润表'!C71+'2025年赣皖区域利润表'!C71 -> 0 | D71: ='2025年中心利润表 '!D71+'2025年江苏分部利润表'!D71+'2025年浙江分部利润表'!D71+'2025年上海分部利润表'!D71+'2025年赣皖区域利润表'!D71 -> 0 | E71: ='2025年中心利润表 '!E71+'2025年江苏分部利润表'!E71+'2025年浙江分部利润表'!E71+'2025年上海分部利润表'!E71+'2025年赣皖区域利润表'!E71 -> 0 | F71: ='2025年中心利润表 '!F71+'2025年江苏分部利润表'!F71+'2025年浙江分部利润表'!F71+'2025年上海分部利润表'!F71+'2025年赣皖区域利润表'!F71 -> 0 | G71: ='2025年中心利润表 '!G71+'2025年江苏分部利润表'!G71+'2025年浙江分部利润表'!G71+'2025年上海分部利润表'!G71+'2025年赣皖区域利润表'!G71 -> 7500 | H71: ='2025年中心利润表 '!H71+'2025年江苏分部利润表'!H71+'2025年浙江分部利润表'!H71+'2025年上海分部利润表'!H71+'2025年赣皖区域利润表'!H71 -> 0 | I71: ='2025年中心利润表 '!I71+'2025年江苏分部利润表'!I71+'2025年浙江分部利润表'!I71+'2025年上海分部利润表'!I71+'2025年赣皖区域利润表'!I71 -> 0 | J71: ='2025年中心利润表 '!J71+'2025年江苏分部利润表'!J71+'2025年浙江分部利润表'!J71+'2025年上海分部利润表'!J71+'2025年赣皖区域利润表'!J71 -> 0 | ... Z71: ='2025年中心利润表 '!Z71+'2025年江苏分部利润表'!Z71+'2025年浙江分部利润表'!Z71+'2025年上海分部利润表'!Z71+'2025年赣皖区域利润表'!Z71 -> 0 | AA71: =C71+E71+G71+I71+K71+M71+O71+Q71+S71+U71+W71+Y71 -> 7500 | AB71: =D71+F71+H71+J71+L71+N71+P71+R71+T71+V71+X71+Z71 -> 0 | AD71: =SUMIF($C$5:$Z$5,$AD$5,C71:Z71) -> 7500 | AE71: =SUMIF($C$5:$Z$5,$AD$5,D71:AA71) -> 0 | AF71: =AA71-AD71 -> 0 | AG71: =AB71-AE71 -> 0 | AH71: =SUM('[1]2024年全面预算利润表 (销售1中心)2.8亿'!E76:H76) -> 1600
A72: 顾问费 | C72: ='2025年中心利润表 '!C72+'2025年江苏分部利润表'!C72+'2025年浙江分部利润表'!C72+'2025年上海分部利润表'!C72+'2025年赣皖区域利润表'!C72 -> 0 | D72: ='2025年中心利润表 '!D72+'2025年江苏分部利润表'!D72+'2025年浙江分部利润表'!D72+'2025年上海分部利润表'!D72+'2025年赣皖区域利润表'!D72 -> 0 | E72: ='2025年中心利润表 '!E72+'2025年江苏分部利润表'!E72+'2025年浙江分部利润表'!E72+'2025年上海分部利润表'!E72+'2025年赣皖区域利润表'!E72 -> 0 | F72: ='2025年中心利润表 '!F72+'2025年江苏分部利润表'!F72+'2025年浙江分部利润表'!F72+'2025年上海分部利润表'!F72+'2025年赣皖区域利润表'!F72 -> 0 | G72: ='2025年中心利润表 '!G72+'2025年江苏分部利润表'!G72+'2025年浙江分部利润表'!G72+'2025年上海分部利润表'!G72+'2025年赣皖区域利润表'!G72 -> 0 | H72: ='2025年中心利润表 '!H72+'2025年江苏分部利润表'!H72+'2025年浙江分部利润表'!H72+'2025年上海分部利润表'!H72+'2025年赣皖区域利润表'!H72 -> 0 | I72: ='2025年中心利润表 '!I72+'2025年江苏分部利润表'!I72+'2025年浙江分部利润表'!I72+'2025年上海分部利润表'!I72+'2025年赣皖区域利润表'!I72 -> 0 | J72: ='2025年中心利润表 '!J72+'2025年江苏分部利润表'!J72+'2025年浙江分部利润表'!J72+'2025年上海分部利润表'!J72+'2025年赣皖区域利润表'!J72 -> 0 | ... Z72: ='2025年中心利润表 '!Z72+'2025年江苏分部利润表'!Z72+'2025年浙江分部利润表'!Z72+'2025年上海分部利润表'!Z72+'2025年赣皖区域利润表'!Z72 -> 0 | AA72: =C72+E72+G72+I72+K72+M72+O72+Q72+S72+U72+W72+Y72 -> 0 | AB72: =D72+F72+H72+J72+L72+N72+P72+R72+T72+V72+X72+Z72 -> 20727.72 | AD72: =SUMIF($C$5:$Z$5,$AD$5,C72:Z72) -> 0 | AE72: =SUMIF($C$5:$Z$5,$AD$5,D72:AA72) -> 20727.72 | AF72: =AA72-AD72 -> 0 | AG72: =AB72-AE72 -> 0 | AH72: =SUM('[1]2024年全面预算利润表 (销售1中心)2.8亿'!E77:H77) -> 0
A73: 快递费 | C73: ='2025年中心利润表 '!C73+'2025年江苏分部利润表'!C73+'2025年浙江分部利润表'!C73+'2025年上海分部利润表'!C73+'2025年赣皖区域利润表'!C73 -> 5700 | D73: ='2025年中心利润表 '!D73+'2025年江苏分部利润表'!D73+'2025年浙江分部利润表'!D73+'2025年上海分部利润表'!D73+'2025年赣皖区域利润表'!D73 -> 3073.29 | E73: ='2025年中心利润表 '!E73+'2025年江苏分部利润表'!E73+'2025年浙江分部利润表'!E73+'2025年上海分部利润表'!E73+'2025年赣皖区域利润表'!E73 -> 5700 | F73: ='2025年中心利润表 '!F73+'2025年江苏分部利润表'!F73+'2025年浙江分部利润表'!F73+'2025年上海分部利润表'!F73+'2025年赣皖区域利润表'!F73 -> 4056.94 | G73: ='2025年中心利润表 '!G73+'2025年江苏分部利润表'!G73+'2025年浙江分部利润表'!G73+'2025年上海分部利润表'!G73+'2025年赣皖区域利润表'!G73 -> 5700 | H73: ='2025年中心利润表 '!H73+'2025年江苏分部利润表'!H73+'2025年浙江分部利润表'!H73+'2025年上海分部利润表'!H73+'2025年赣皖区域利润表'!H73 -> 7830.97 | I73: ='2025年中心利润表 '!I73+'2025年江苏分部利润表'!I73+'2025年浙江分部利润表'!I73+'2025年上海分部利润表'!I73+'2025年赣皖区域利润表'!I73 -> 5700 | J73: ='2025年中心利润表 '!J73+'2025年江苏分部利润表'!J73+'2025年浙江分部利润表'!J73+'2025年上海分部利润表'!J73+'2025年赣皖区域利润表'!J73 -> 8884.32 | ... Z73: ='2025年中心利润表 '!Z73+'2025年江苏分部利润表'!Z73+'2025年浙江分部利润表'!Z73+'2025年上海分部利润表'!Z73+'2025年赣皖区域利润表'!Z73 -> 4300.83 | AA73: =C73+E73+G73+I73+K73+M73+O73+Q73+S73+U73+W73+Y73 -> 68400 | AB73: =D73+F73+H73+J73+L73+N73+P73+R73+T73+V73+X73+Z73 -> 57661.76 | AD73: =SUMIF($C$5:$Z$5,$AD$5,C73:Z73) -> 68400 | AE73: =SUMIF($C$5:$Z$5,$AD$5,D73:AA73) -> 57661.76 | AF73: =AA73-AD73 -> 0 | AG73: =AB73-AE73 -> 0 | AH73: =SUM('[1]2024年全面预算利润表 (销售1中心)2.8亿'!E78:H78) -> 27232.785
A74: 诉讼费 | C74: ='2025年中心利润表 '!C74+'2025年江苏分部利润表'!C74+'2025年浙江分部利润表'!C74+'2025年上海分部利润表'!C74+'2025年赣皖区域利润表'!C74 -> 0 | D74: ='2025年中心利润表 '!D74+'2025年江苏分部利润表'!D74+'2025年浙江分部利润表'!D74+'2025年上海分部利润表'!D74+'2025年赣皖区域利润表'!D74 -> 0 | E74: ='2025年中心利润表 '!E74+'2025年江苏分部利润表'!E74+'2025年浙江分部利润表'!E74+'2025年上海分部利润表'!E74+'2025年赣皖区域利润表'!E74 -> 0 | F74: ='2025年中心利润表 '!F74+'2025年江苏分部利润表'!F74+'2025年浙江分部利润表'!F74+'2025年上海分部利润表'!F74+'2025年赣皖区域利润表'!F74 -> 0 | G74: ='2025年中心利润表 '!G74+'2025年江苏分部利润表'!G74+'2025年浙江分部利润表'!G74+'2025年上海分部利润表'!G74+'2025年赣皖区域利润表'!G74 -> 0 | H74: ='2025年中心利润表 '!H74+'2025年江苏分部利润表'!H74+'2025年浙江分部利润表'!H74+'2025年上海分部利润表'!H74+'2025年赣皖区域利润表'!H74 -> 0 | I74: ='2025年中心利润表 '!I74+'2025年江苏分部利润表'!I74+'2025年浙江分部利润表'!I74+'2025年上海分部利润表'!I74+'2025年赣皖区域利润表'!I74 -> 0 | J74: ='2025年中心利润表 '!J74+'2025年江苏分部利润表'!J74+'2025年浙江分部利润表'!J74+'2025年上海分部利润表'!J74+'2025年赣皖区域利润表'!J74 -> 42452.83 | ... Z74: ='2025年中心利润表 '!Z74+'2025年江苏分部利润表'!Z74+'2025年浙江分部利润表'!Z74+'2025年上海分部利润表'!Z74+'2025年赣皖区域利润表'!Z74 -> 0 | AA74: =C74+E74+G74+I74+K74+M74+O74+Q74+S74+U74+W74+Y74 -> 0 | AB74: =D74+F74+H74+J74+L74+N74+P74+R74+T74+V74+X74+Z74 -> 38159.19 | AD74: =SUMIF($C$5:$Z$5,$AD$5,C74:Z74) -> 0 | AE74: =SUMIF($C$5:$Z$5,$AD$5,D74:AA74) -> 38159.19 | AF74: =AA74-AD74 -> 0 | AG74: =AB74-AE74 -> 0 | AH74: =SUM('[1]2024年全面预算利润表 (销售1中心)2.8亿'!E79:H79) -> 0
A75: 会员费 | C75: ='2025年中心利润表 '!C75+'2025年江苏分部利润表'!C75+'2025年浙江分部利润表'!C75+'2025年上海分部利润表'!C75+'2025年赣皖区域利润表'!C75 -> 0 | D75: ='2025年中心利润表 '!D75+'2025年江苏分部利润表'!D75+'2025年浙江分部利润表'!D75+'2025年上海分部利润表'!D75+'2025年赣皖区域利润表'!D75 -> 0 | E75: ='2025年中心利润表 '!E75+'2025年江苏分部利润表'!E75+'2025年浙江分部利润表'!E75+'2025年上海分部利润表'!E75+'2025年赣皖区域利润表'!E75 -> 0 | F75: ='2025年中心利润表 '!F75+'2025年江苏分部利润表'!F75+'2025年浙江分部利润表'!F75+'2025年上海分部利润表'!F75+'2025年赣皖区域利润表'!F75 -> 0 | G75: ='2025年中心利润表 '!G75+'2025年江苏分部利润表'!G75+'2025年浙江分部利润表'!G75+'2025年上海分部利润表'!G75+'2025年赣皖区域利润表'!G75 -> 15000 | H75: ='2025年中心利润表 '!H75+'2025年江苏分部利润表'!H75+'2025年浙江分部利润表'!H75+'2025年上海分部利润表'!H75+'2025年赣皖区域利润表'!H75 -> 0 | I75: ='2025年中心利润表 '!I75+'2025年江苏分部利润表'!I75+'2025年浙江分部利润表'!I75+'2025年上海分部利润表'!I75+'2025年赣皖区域利润表'!I75 -> 0 | J75: ='2025年中心利润表 '!J75+'2025年江苏分部利润表'!J75+'2025年浙江分部利润表'!J75+'2025年上海分部利润表'!J75+'2025年赣皖区域利润表'!J75 -> 0 | ... Z75: ='2025年中心利润表 '!Z75+'2025年江苏分部利润表'!Z75+'2025年浙江分部利润表'!Z75+'2025年上海分部利润表'!Z75+'2025年赣皖区域利润表'!Z75 -> 0 | AA75: =C75+E75+G75+I75+K75+M75+O75+Q75+S75+U75+W75+Y75 -> 15000 | AB75: =D75+F75+H75+J75+L75+N75+P75+R75+T75+V75+X75+Z75 -> 0 | AD75: =SUMIF($C$5:$Z$5,$AD$5,C75:Z75) -> 15000 | AE75: =SUMIF($C$5:$Z$5,$AD$5,D75:AA75) -> 0 | AF75: =AA75-AD75 -> 0 | AG75: =AB75-AE75 -> 0 | AH75: =SUM('[1]2024年全面预算利润表 (销售1中心)2.8亿'!E80:H80) -> 15600
A76: 广告宣传费 | C76: ='2025年中心利润表 '!C76+'2025年江苏分部利润表'!C76+'2025年浙江分部利润表'!C76+'2025年上海分部利润表'!C76+'2025年赣皖区域利润表'!C76 -> 0 | D76: ='2025年中心利润表 '!D76+'2025年江苏分部利润表'!D76+'2025年浙江分部利润表'!D76+'2025年上海分部利润表'!D76+'2025年赣皖区域利润表'!D76 -> 833.33 | E76: ='2025年中心利润表 '!E76+'2025年江苏分部利润表'!E76+'2025年浙江分部利润表'!E76+'2025年上海分部利润表'!E76+'2025年赣皖区域利润表'!E76 -> 0 | F76: ='2025年中心利润表 '!F76+'2025年江苏分部利润表'!F76+'2025年浙江分部利润表'!F76+'2025年上海分部利润表'!F76+'2025年赣皖区域利润表'!F76 -> 2283.33 | G76: ='2025年中心利润表 '!G76+'2025年江苏分部利润表'!G76+'2025年浙江分部利润表'!G76+'2025年上海分部利润表'!G76+'2025年赣皖区域利润表'!G76 -> 0 | H76: ='2025年中心利润表 '!H76+'2025年江苏分部利润表'!H76+'2025年浙江分部利润表'!H76+'2025年上海分部利润表'!H76+'2025年赣皖区域利润表'!H76 -> 833.33 | I76: ='2025年中心利润表 '!I76+'2025年江苏分部利润表'!I76+'2025年浙江分部利润表'!I76+'2025年上海分部利润表'!I76+'2025年赣皖区域利润表'!I76 -> 0 | J76: ='2025年中心利润表 '!J76+'2025年江苏分部利润表'!J76+'2025年浙江分部利润表'!J76+'2025年上海分部利润表'!J76+'2025年赣皖区域利润表'!J76 -> 1081.33 | ... Z76: ='2025年中心利润表 '!Z76+'2025年江苏分部利润表'!Z76+'2025年浙江分部利润表'!Z76+'2025年上海分部利润表'!Z76+'2025年赣皖区域利润表'!Z76 -> 12100 | AA76: =C76+E76+G76+I76+K76+M76+O76+Q76+S76+U76+W76+Y76 -> 0 | AB76: =D76+F76+H76+J76+L76+N76+P76+R76+T76+V76+X76+Z76 -> 22628.02 | AD76: =SUMIF($C$5:$Z$5,$AD$5,C76:Z76) -> 0 | AE76: =SUMIF($C$5:$Z$5,$AD$5,D76:AA76) -> 22628.02 | AF76: =AA76-AD76 -> 0 | AG76: =AB76-AE76 -> 0 | AH76: =SUM('[1]2024年全面预算利润表 (销售1中心)2.8亿'!E81:H81) -> 14000
A77: 会务费 | C77: ='2025年中心利润表 '!C77+'2025年江苏分部利润表'!C77+'2025年浙江分部利润表'!C77+'2025年上海分部利润表'!C77+'2025年赣皖区域利润表'!C77 -> 4500 | D77: ='2025年中心利润表 '!D77+'2025年江苏分部利润表'!D77+'2025年浙江分部利润表'!D77+'2025年上海分部利润表'!D77+'2025年赣皖区域利润表'!D77 -> 30000 | E77: ='2025年中心利润表 '!E77+'2025年江苏分部利润表'!E77+'2025年浙江分部利润表'!E77+'2025年上海分部利润表'!E77+'2025年赣皖区域利润表'!E77 -> 4500 | F77: ='2025年中心利润表 '!F77+'2025年江苏分部利润表'!F77+'2025年浙江分部利润表'!F77+'2025年上海分部利润表'!F77+'2025年赣皖区域利润表'!F77 -> 0 | G77: ='2025年中心利润表 '!G77+'2025年江苏分部利润表'!G77+'2025年浙江分部利润表'!G77+'2025年上海分部利润表'!G77+'2025年赣皖区域利润表'!G77 -> 4500 | H77: ='2025年中心利润表 '!H77+'2025年江苏分部利润表'!H77+'2025年浙江分部利润表'!H77+'2025年上海分部利润表'!H77+'2025年赣皖区域利润表'!H77 -> 0 | I77: ='2025年中心利润表 '!I77+'2025年江苏分部利润表'!I77+'2025年浙江分部利润表'!I77+'2025年上海分部利润表'!I77+'2025年赣皖区域利润表'!I77 -> 4500 | J77: ='2025年中心利润表 '!J77+'2025年江苏分部利润表'!J77+'2025年浙江分部利润表'!J77+'2025年上海分部利润表'!J77+'2025年赣皖区域利润表'!J77 -> 0 | ... Z77: ='2025年中心利润表 '!Z77+'2025年江苏分部利润表'!Z77+'2025年浙江分部利润表'!Z77+'2025年上海分部利润表'!Z77+'2025年赣皖区域利润表'!Z77 -> 0 | AA77: =C77+E77+G77+I77+K77+M77+O77+Q77+S77+U77+W77+Y77 -> 134000 | AB77: =D77+F77+H77+J77+L77+N77+P77+R77+T77+V77+X77+Z77 -> 59691.44 | AD77: =SUMIF($C$5:$Z$5,$AD$5,C77:Z77) -> 134000 | AE77: =SUMIF($C$5:$Z$5,$AD$5,D77:AA77) -> 59691.44 | AF77: =AA77-AD77 -> 0 | AG77: =AB77-AE77 -> 0 | AH77: =SUM('[1]2024年全面预算利润表 (销售1中心)2.8亿'!E82:H82) -> 0
... A101: 报废损失 | C101: ='2025年中心利润表 '!C101+'2025年江苏分部利润表'!C101+'2025年浙江分部利润表'!C101+'2025年上海分部利润表'!C101+'2025年赣皖区域利润表'!C101 -> 2000 | D101: ='2025年中心利润表 '!D101+'2025年江苏分部利润表'!D101+'2025年浙江分部利润表'!D101+'2025年上海分部利润表'!D101+'2025年赣皖区域利润表'!D101 -> 0 | E101: ='2025年中心利润表 '!E101+'2025年江苏分部利润表'!E101+'2025年浙江分部利润表'!E101+'2025年上海分部利润表'!E101+'2025年赣皖区域利润表'!E101 -> 2000 | F101: ='2025年中心利润表 '!F101+'2025年江苏分部利润表'!F101+'2025年浙江分部利润表'!F101+'2025年上海分部利润表'!F101+'2025年赣皖区域利润表'!F101 -> 0 | G101: ='2025年中心利润表 '!G101+'2025年江苏分部利润表'!G101+'2025年浙江分部利润表'!G101+'2025年上海分部利润表'!G101+'2025年赣皖区域利润表'!G101 -> 2000 | H101: ='2025年中心利润表 '!H101+'2025年江苏分部利润表'!H101+'2025年浙江分部利润表'!H101+'2025年上海分部利润表'!H101+'2025年赣皖区域利润表'!H101 -> 0 | I101: ='2025年中心利润表 '!I101+'2025年江苏分部利润表'!I101+'2025年浙江分部利润表'!I101+'2025年上海分部利润表'!I101+'2025年赣皖区域利润表'!I101 -> 2000 | J101: ='2025年中心利润表 '!J101+'2025年江苏分部利润表'!J101+'2025年浙江分部利润表'!J101+'2025年上海分部利润表'!J101+'2025年赣皖区域利润表'!J101 -> 0 | ... Z101: ='2025年中心利润表 '!Z101+'2025年江苏分部利润表'!Z101+'2025年浙江分部利润表'!Z101+'2025年上海分部利润表'!Z101+'2025年赣皖区域利润表'!Z101 -> 6608.11 | AA101: =C101+E101+G101+I101+K101+M101+O101+Q101+S101+U101+W101+Y101 -> 24000 | AB101: =D101+F101+H101+J101+L101+N101+P101+R101+T101+V101+X101+Z101 -> 6608.11 | AD101: =SUMIF($C$5:$Z$5,$AD$5,C101:Z101) -> 24000 | AE101: =SUMIF($C$5:$Z$5,$AD$5,D101:AA101) -> 6608.11 | AF101: =AA101-AD101 -> 0 | AG101: =AB101-AE101 -> 0 | AH101: =SUM('[1]2024年全面预算利润表 (销售1中心)2.8亿'!E106:H106) -> 0
A102: 管理费用 | B102: 7 | C102: =SUM(C103:C175)-C103-C106-C115-C126-C138-C172 -> 0 | D102: =SUM(D103:D175)-D103-D106-D115-D126-D138-D172 -> 0 | E102: =SUM(E103:E175)-E103-E106-E115-E126-E138-E172 -> 0 | F102: =SUM(F103:F175)-F103-F106-F115-F126-F138-F172 -> 0 | G102: =SUM(G103:G175)-G103-G106-G115-G126-G138-G172 -> 0 | H102: =SUM(H103:H175)-H103-H106-H115-H126-H138-H172 -> 0 | I102: =SUM(I103:I175)-I103-I106-I115-I126-I138-I172 -> 0 | J102: =SUM(J103:J175)-J103-J106-J115-J126-J138-J172 -> 0 | ... Z102: =SUM(Z103:Z175)-Z103-Z106-Z115-Z126-Z138-Z172 -> 0 | AA102: =C102+E102+G102+I102+K102+M102+O102+Q102+S102+U102+W102+Y102 -> 0 | AB102: =SUM(D102:Z102) -> 0 | AD102: =SUMIF($C$5:$Z$5,$AD$5,C102:Z102) -> 0 | AE102: =SUMIF($C$5:$Z$5,$AD$5,D102:AA102) -> 0 | AF102: =AA102-AD102 -> 0 | AG102: =AB102-AE102 -> 0
A103: 职工薪酬 | C103: =SUM(C104:C105) -> 0 | D103: =SUM(D104:D105) -> 0 | E103: =SUM(E104:E105) -> 0 | F103: =SUM(F104:F105) -> 0 | G103: =SUM(G104:G105) -> 0 | H103: =SUM(H104:H105) -> 0 | I103: =SUM(I104:I105) -> 0 | J103: =SUM(J104:J105) -> 0 | ... Z103: =SUM(Z104:Z105) -> 0 | AA103: =C103+E103+G103+I103+K103+M103+O103+Q103+S103+U103+W103+Y103 -> 0 | AB103: =D103+F103+H103+J103+L103+N103+P103+R103+T103+V103+X103+Z103 -> 0 | AD103: =SUMIF($C$5:$Z$5,$AD$5,C103:Z103) -> 0 | AE103: =SUMIF($C$5:$Z$5,$AD$5,D103:AA103) -> 0 | AF103: =AA103-AD103 -> 0 | AG103: =AB103-AE103 -> 0 | AH103: =SUM('[1]2024年全面预算利润表 (销售1中心)2.8亿'!E108:H108) -> 0
A104: 工资 | C104: ='2025年中心利润表 '!C104+'2025年江苏分部利润表'!C104+'2025年浙江分部利润表'!C104+'2025年上海分部利润表'!C104+'2025年赣皖区域利润表'!C104 -> 0 | D104: ='2025年中心利润表 '!D104+'2025年江苏分部利润表'!D104+'2025年浙江分部利润表'!D104+'2025年上海分部利润表'!D104+'2025年赣皖区域利润表'!D104 -> 0 | E104: ='2025年中心利润表 '!E104+'2025年江苏分部利润表'!E104+'2025年浙江分部利润表'!E104+'2025年上海分部利润表'!E104+'2025年赣皖区域利润表'!E104 -> 0 | F104: ='2025年中心利润表 '!F104+'2025年江苏分部利润表'!F104+'2025年浙江分部利润表'!F104+'2025年上海分部利润表'!F104+'2025年赣皖区域利润表'!F104 -> 0 | G104: ='2025年中心利润表 '!G104+'2025年江苏分部利润表'!G104+'2025年浙江分部利润表'!G104+'2025年上海分部利润表'!G104+'2025年赣皖区域利润表'!G104 -> 0 | H104: ='2025年中心利润表 '!H104+'2025年江苏分部利润表'!H104+'2025年浙江分部利润表'!H104+'2025年上海分部利润表'!H104+'2025年赣皖区域利润表'!H104 -> 0 | I104: ='2025年中心利润表 '!I104+'2025年江苏分部利润表'!I104+'2025年浙江分部利润表'!I104+'2025年上海分部利润表'!I104+'2025年赣皖区域利润表'!I104 -> 0 | J104: ='2025年中心利润表 '!J104+'2025年江苏分部利润表'!J104+'2025年浙江分部利润表'!J104+'2025年上海分部利润表'!J104+'2025年赣皖区域利润表'!J104 -> 0 | ... Z104: ='2025年中心利润表 '!Z104+'2025年江苏分部利润表'!Z104+'2025年浙江分部利润表'!Z104+'2025年上海分部利润表'!Z104+'2025年赣皖区域利润表'!Z104 -> 0 | AA104: =C104+E104+G104+I104+K104+M104+O104+Q104+S104+U104+W104+Y104 -> 0 | AB104: =D104+F104+H104+J104+L104+N104+P104+R104+T104+V104+X104+Z104 -> 0 | AD104: =SUMIF($C$5:$Z$5,$AD$5,C104:Z104) -> 0 | AE104: =SUMIF($C$5:$Z$5,$AD$5,D104:AA104) -> 0 | AF104: =AA104-AD104 -> 0 | AG104: =AB104-AE104 -> 0 | AH104: =SUM('[1]2024年全面预算利润表 (销售1中心)2.8亿'!E109:H109) -> 0
A105: 奖金及提成 | C105: ='2025年中心利润表 '!C105+'2025年江苏分部利润表'!C105+'2025年浙江分部利润表'!C105+'2025年上海分部利润表'!C105+'2025年赣皖区域利润表'!C105 -> 0 | D105: ='2025年中心利润表 '!D105+'2025年江苏分部利润表'!D105+'2025年浙江分部利润表'!D105+'2025年上海分部利润表'!D105+'2025年赣皖区域利润表'!D105 -> 0 | E105: ='2025年中心利润表 '!E105+'2025年江苏分部利润表'!E105+'2025年浙江分部利润表'!E105+'2025年上海分部利润表'!E105+'2025年赣皖区域利润表'!E105 -> 0 | F105: ='2025年中心利润表 '!F105+'2025年江苏分部利润表'!F105+'2025年浙江分部利润表'!F105+'2025年上海分部利润表'!F105+'2025年赣皖区域利润表'!F105 -> 0 | G105: ='2025年中心利润表 '!G105+'2025年江苏分部利润表'!G105+'2025年浙江分部利润表'!G105+'2025年上海分部利润表'!G105+'2025年赣皖区域利润表'!G105 -> 0 | H105: ='2025年中心利润表 '!H105+'2025年江苏分部利润表'!H105+'2025年浙江分部利润表'!H105+'2025年上海分部利润表'!H105+'2025年赣皖区域利润表'!H105 -> 0 | I105: ='2025年中心利润表 '!I105+'2025年江苏分部利润表'!I105+'2025年浙江分部利润表'!I105+'2025年上海分部利润表'!I105+'2025年赣皖区域利润表'!I105 -> 0 | J105: ='2025年中心利润表 '!J105+'2025年江苏分部利润表'!J105+'2025年浙江分部利润表'!J105+'2025年上海分部利润表'!J105+'2025年赣皖区域利润表'!J105 -> 0 | ... Z105: ='2025年中心利润表 '!Z105+'2025年江苏分部利润表'!Z105+'2025年浙江分部利润表'!Z105+'2025年上海分部利润表'!Z105+'2025年赣皖区域利润表'!Z105 -> 0 | AA105: =C105+E105+G105+I105+K105+M105+O105+Q105+S105+U105+W105+Y105 -> 0 | AB105: =D105+F105+H105+J105+L105+N105+P105+R105+T105+V105+X105+Z105 -> 0 | AD105: =SUMIF($C$5:$Z$5,$AD$5,C105:Z105) -> 0 | AE105: =SUMIF($C$5:$Z$5,$AD$5,D105:AA105) -> 0 | AF105: =AA105-AD105 -> 0 | AG105: =AB105-AE105 -> 0 | AH105: =SUM('[1]2024年全面预算利润表 (销售1中心)2.8亿'!E110:H110) -> 0
A106: 社保 | C106: =SUM(C107:C111) -> 0 | D106: =SUM(D107:D111) -> 0 | E106: =SUM(E107:E111) -> 0 | F106: =SUM(F107:F111) -> 0 | G106: =SUM(G107:G111) -> 0 | H106: =SUM(H107:H111) -> 0 | I106: =SUM(I107:I111) -> 0 | J106: =SUM(J107:J111) -> 0 | ... Z106: =SUM(Z107:Z111) -> 0 | AA106: =C106+E106+G106+I106+K106+M106+O106+Q106+S106+U106+W106+Y106 -> 0 | AB106: =D106+F106+H106+J106+L106+N106+P106+R106+T106+V106+X106+Z106 -> 0 | AD106: =SUMIF($C$5:$Z$5,$AD$5,C106:Z106) -> 0 | AE106: =SUMIF($C$5:$Z$5,$AD$5,D106:AA106) -> 0 | AF106: =AA106-AD106 -> 0 | AG106: =AB106-AE106 -> 0 | AH106: =SUM('[1]2024年全面预算利润表 (销售1中心)2.8亿'!E111:H111) -> 0
A107: 养老 | C107: ='2025年中心利润表 '!C107+'2025年江苏分部利润表'!C107+'2025年浙江分部利润表'!C107+'2025年上海分部利润表'!C107+'2025年赣皖区域利润表'!C107 -> 0 | D107: ='2025年中心利润表 '!D107+'2025年江苏分部利润表'!D107+'2025年浙江分部利润表'!D107+'2025年上海分部利润表'!D107+'2025年赣皖区域利润表'!D107 -> 0 | E107: ='2025年中心利润表 '!E107+'2025年江苏分部利润表'!E107+'2025年浙江分部利润表'!E107+'2025年上海分部利润表'!E107+'2025年赣皖区域利润表'!E107 -> 0 | F107: ='2025年中心利润表 '!F107+'2025年江苏分部利润表'!F107+'2025年浙江分部利润表'!F107+'2025年上海分部利润表'!F107+'2025年赣皖区域利润表'!F107 -> 0 | G107: ='2025年中心利润表 '!G107+'2025年江苏分部利润表'!G107+'2025年浙江分部利润表'!G107+'2025年上海分部利润表'!G107+'2025年赣皖区域利润表'!G107 -> 0 | H107: ='2025年中心利润表 '!H107+'2025年江苏分部利润表'!H107+'2025年浙江分部利润表'!H107+'2025年上海分部利润表'!H107+'2025年赣皖区域利润表'!H107 -> 0 | I107: ='2025年中心利润表 '!I107+'2025年江苏分部利润表'!I107+'2025年浙江分部利润表'!I107+'2025年上海分部利润表'!I107+'2025年赣皖区域利润表'!I107 -> 0 | J107: ='2025年中心利润表 '!J107+'2025年江苏分部利润表'!J107+'2025年浙江分部利润表'!J107+'2025年上海分部利润表'!J107+'2025年赣皖区域利润表'!J107 -> 0 | ... Z107: ='2025年中心利润表 '!Z107+'2025年江苏分部利润表'!Z107+'2025年浙江分部利润表'!Z107+'2025年上海分部利润表'!Z107+'2025年赣皖区域利润表'!Z107 -> 0 | AA107: =C107+E107+G107+I107+K107+M107+O107+Q107+S107+U107+W107+Y107 -> 0 | AB107: =D107+F107+H107+J107+L107+N107+P107+R107+T107+V107+X107+Z107 -> 0 | AD107: =SUMIF($C$5:$Z$5,$AD$5,C107:Z107) -> 0 | AE107: =SUMIF($C$5:$Z$5,$AD$5,D107:AA107) -> 0 | AF107: =AA107-AD107 -> 0 | AG107: =AB107-AE107 -> 0 | AH107: =SUM('[1]2024年全面预算利润表 (销售1中心)2.8亿'!E112:H112) -> 0
A108: 医疗 | C108: ='2025年中心利润表 '!C108+'2025年江苏分部利润表'!C108+'2025年浙江分部利润表'!C108+'2025年上海分部利润表'!C108+'2025年赣皖区域利润表'!C108 -> 0 | D108: ='2025年中心利润表 '!D108+'2025年江苏分部利润表'!D108+'2025年浙江分部利润表'!D108+'2025年上海分部利润表'!D108+'2025年赣皖区域利润表'!D108 -> 0 | E108: ='2025年中心利润表 '!E108+'2025年江苏分部利润表'!E108+'2025年浙江分部利润表'!E108+'2025年上海分部利润表'!E108+'2025年赣皖区域利润表'!E108 -> 0 | F108: ='2025年中心利润表 '!F108+'2025年江苏分部利润表'!F108+'2025年浙江分部利润表'!F108+'2025年上海分部利润表'!F108+'2025年赣皖区域利润表'!F108 -> 0 | G108: ='2025年中心利润表 '!G108+'2025年江苏分部利润表'!G108+'2025年浙江分部利润表'!G108+'2025年上海分部利润表'!G108+'2025年赣皖区域利润表'!G108 -> 0 | H108: ='2025年中心利润表 '!H108+'2025年江苏分部利润表'!H108+'2025年浙江分部利润表'!H108+'2025年上海分部利润表'!H108+'2025年赣皖区域利润表'!H108 -> 0 | I108: ='2025年中心利润表 '!I108+'2025年江苏分部利润表'!I108+'2025年浙江分部利润表'!I108+'2025年上海分部利润表'!I108+'2025年赣皖区域利润表'!I108 -> 0 | J108: ='2025年中心利润表 '!J108+'2025年江苏分部利润表'!J108+'2025年浙江分部利润表'!J108+'2025年上海分部利润表'!J108+'2025年赣皖区域利润表'!J108 -> 0 | ... Z108: ='2025年中心利润表 '!Z108+'2025年江苏分部利润表'!Z108+'2025年浙江分部利润表'!Z108+'2025年上海分部利润表'!Z108+'2025年赣皖区域利润表'!Z108 -> 0 | AA108: =C108+E108+G108+I108+K108+M108+O108+Q108+S108+U108+W108+Y108 -> 0 | AB108: =D108+F108+H108+J108+L108+N108+P108+R108+T108+V108+X108+Z108 -> 0 | AD108: =SUMIF($C$5:$Z$5,$AD$5,C108:Z108) -> 0 | AE108: =SUMIF($C$5:$Z$5,$AD$5,D108:AA108) -> 0 | AF108: =AA108-AD108 -> 0 | AG108: =AB108-AE108 -> 0 | AH108: =SUM('[1]2024年全面预算利润表 (销售1中心)2.8亿'!E113:H113) -> 0
A109: 工伤 | C109: ='2025年中心利润表 '!C109+'2025年江苏分部利润表'!C109+'2025年浙江分部利润表'!C109+'2025年上海分部利润表'!C109+'2025年赣皖区域利润表'!C109 -> 0 | D109: ='2025年中心利润表 '!D109+'2025年江苏分部利润表'!D109+'2025年浙江分部利润表'!D109+'2025年上海分部利润表'!D109+'2025年赣皖区域利润表'!D109 -> 0 | E109: ='2025年中心利润表 '!E109+'2025年江苏分部利润表'!E109+'2025年浙江分部利润表'!E109+'2025年上海分部利润表'!E109+'2025年赣皖区域利润表'!E109 -> 0 | F109: ='2025年中心利润表 '!F109+'2025年江苏分部利润表'!F109+'2025年浙江分部利润表'!F109+'2025年上海分部利润表'!F109+'2025年赣皖区域利润表'!F109 -> 0 | G109: ='2025年中心利润表 '!G109+'2025年江苏分部利润表'!G109+'2025年浙江分部利润表'!G109+'2025年上海分部利润表'!G109+'2025年赣皖区域利润表'!G109 -> 0 | H109: ='2025年中心利润表 '!H109+'2025年江苏分部利润表'!H109+'2025年浙江分部利润表'!H109+'2025年上海分部利润表'!H109+'2025年赣皖区域利润表'!H109 -> 0 | I109: ='2025年中心利润表 '!I109+'2025年江苏分部利润表'!I109+'2025年浙江分部利润表'!I109+'2025年上海分部利润表'!I109+'2025年赣皖区域利润表'!I109 -> 0 | J109: ='2025年中心利润表 '!J109+'2025年江苏分部利润表'!J109+'2025年浙江分部利润表'!J109+'2025年上海分部利润表'!J109+'2025年赣皖区域利润表'!J109 -> 0 | ... Z109: ='2025年中心利润表 '!Z109+'2025年江苏分部利润表'!Z109+'2025年浙江分部利润表'!Z109+'2025年上海分部利润表'!Z109+'2025年赣皖区域利润表'!Z109 -> 0 | AA109: =C109+E109+G109+I109+K109+M109+O109+Q109+S109+U109+W109+Y109 -> 0 | AB109: =D109+F109+H109+J109+L109+N109+P109+R109+T109+V109+X109+Z109 -> 0 | AD109: =SUMIF($C$5:$Z$5,$AD$5,C109:Z109) -> 0 | AE109: =SUMIF($C$5:$Z$5,$AD$5,D109:AA109) -> 0 | AF109: =AA109-AD109 -> 0 | AG109: =AB109-AE109 -> 0 | AH109: =SUM('[1]2024年全面预算利润表 (销售1中心)2.8亿'!E114:H114) -> 0
A110: 失业 | C110: ='2025年中心利润表 '!C110+'2025年江苏分部利润表'!C110+'2025年浙江分部利润表'!C110+'2025年上海分部利润表'!C110+'2025年赣皖区域利润表'!C110 -> 0 | D110: ='2025年中心利润表 '!D110+'2025年江苏分部利润表'!D110+'2025年浙江分部利润表'!D110+'2025年上海分部利润表'!D110+'2025年赣皖区域利润表'!D110 -> 0 | E110: ='2025年中心利润表 '!E110+'2025年江苏分部利润表'!E110+'2025年浙江分部利润表'!E110+'2025年上海分部利润表'!E110+'2025年赣皖区域利润表'!E110 -> 0 | F110: ='2025年中心利润表 '!F110+'2025年江苏分部利润表'!F110+'2025年浙江分部利润表'!F110+'2025年上海分部利润表'!F110+'2025年赣皖区域利润表'!F110 -> 0 | G110: ='2025年中心利润表 '!G110+'2025年江苏分部利润表'!G110+'2025年浙江分部利润表'!G110+'2025年上海分部利润表'!G110+'2025年赣皖区域利润表'!G110 -> 0 | H110: ='2025年中心利润表 '!H110+'2025年江苏分部利润表'!H110+'2025年浙江分部利润表'!H110+'2025年上海分部利润表'!H110+'2025年赣皖区域利润表'!H110 -> 0 | I110: ='2025年中心利润表 '!I110+'2025年江苏分部利润表'!I110+'2025年浙江分部利润表'!I110+'2025年上海分部利润表'!I110+'2025年赣皖区域利润表'!I110 -> 0 | J110: ='2025年中心利润表 '!J110+'2025年江苏分部利润表'!J110+'2025年浙江分部利润表'!J110+'2025年上海分部利润表'!J110+'2025年赣皖区域利润表'!J110 -> 0 | ... Z110: ='2025年中心利润表 '!Z110+'2025年江苏分部利润表'!Z110+'2025年浙江分部利润表'!Z110+'2025年上海分部利润表'!Z110+'2025年赣皖区域利润表'!Z110 -> 0 | AA110: =C110+E110+G110+I110+K110+M110+O110+Q110+S110+U110+W110+Y110 -> 0 | AB110: =D110+F110+H110+J110+L110+N110+P110+R110+T110+V110+X110+Z110 -> 0 | AD110: =SUMIF($C$5:$Z$5,$AD$5,C110:Z110) -> 0 | AE110: =SUMIF($C$5:$Z$5,$AD$5,D110:AA110) -> 0 | AF110: =AA110-AD110 -> 0 | AG110: =AB110-AE110 -> 0 | AH110: =SUM('[1]2024年全面预算利润表 (销售1中心)2.8亿'!E115:H115) -> 0
A111: 生育 | C111: ='2025年中心利润表 '!C111+'2025年江苏分部利润表'!C111+'2025年浙江分部利润表'!C111+'2025年上海分部利润表'!C111+'2025年赣皖区域利润表'!C111 -> 0 | D111: ='2025年中心利润表 '!D111+'2025年江苏分部利润表'!D111+'2025年浙江分部利润表'!D111+'2025年上海分部利润表'!D111+'2025年赣皖区域利润表'!D111 -> 0 | E111: ='2025年中心利润表 '!E111+'2025年江苏分部利润表'!E111+'2025年浙江分部利润表'!E111+'2025年上海分部利润表'!E111+'2025年赣皖区域利润表'!E111 -> 0 | F111: ='2025年中心利润表 '!F111+'2025年江苏分部利润表'!F111+'2025年浙江分部利润表'!F111+'2025年上海分部利润表'!F111+'2025年赣皖区域利润表'!F111 -> 0 | G111: ='2025年中心利润表 '!G111+'2025年江苏分部利润表'!G111+'2025年浙江分部利润表'!G111+'2025年上海分部利润表'!G111+'2025年赣皖区域利润表'!G111 -> 0 | H111: ='2025年中心利润表 '!H111+'2025年江苏分部利润表'!H111+'2025年浙江分部利润表'!H111+'2025年上海分部利润表'!H111+'2025年赣皖区域利润表'!H111 -> 0 | I111: ='2025年中心利润表 '!I111+'2025年江苏分部利润表'!I111+'2025年浙江分部利润表'!I111+'2025年上海分部利润表'!I111+'2025年赣皖区域利润表'!I111 -> 0 | J111: ='2025年中心利润表 '!J111+'2025年江苏分部利润表'!J111+'2025年浙江分部利润表'!J111+'2025年上海分部利润表'!J111+'2025年赣皖区域利润表'!J111 -> 0 | ... Z111: ='2025年中心利润表 '!Z111+'2025年江苏分部利润表'!Z111+'2025年浙江分部利润表'!Z111+'2025年上海分部利润表'!Z111+'2025年赣皖区域利润表'!Z111 -> 0 | AA111: =C111+E111+G111+I111+K111+M111+O111+Q111+S111+U111+W111+Y111 -> 0 | AB111: =D111+F111+H111+J111+L111+N111+P111+R111+T111+V111+X111+Z111 -> 0 | AD111: =SUMIF($C$5:$Z$5,$AD$5,C111:Z111) -> 0 | AE111: =SUMIF($C$5:$Z$5,$AD$5,D111:AA111) -> 0 | AF111: =AA111-AD111 -> 0 | AG111: =AB111-AE111 -> 0 | AH111: =SUM('[1]2024年全面预算利润表 (销售1中心)2.8亿'!E116:H116) -> 0
A112: 公积金 | C112: ='2025年中心利润表 '!C112+'2025年江苏分部利润表'!C112+'2025年浙江分部利润表'!C112+'2025年上海分部利润表'!C112+'2025年赣皖区域利润表'!C112 -> 0 | D112: ='2025年中心利润表 '!D112+'2025年江苏分部利润表'!D112+'2025年浙江分部利润表'!D112+'2025年上海分部利润表'!D112+'2025年赣皖区域利润表'!D112 -> 0 | E112: ='2025年中心利润表 '!E112+'2025年江苏分部利润表'!E112+'2025年浙江分部利润表'!E112+'2025年上海分部利润表'!E112+'2025年赣皖区域利润表'!E112 -> 0 | F112: ='2025年中心利润表 '!F112+'2025年江苏分部利润表'!F112+'2025年浙江分部利润表'!F112+'2025年上海分部利润表'!F112+'2025年赣皖区域利润表'!F112 -> 0 | G112: ='2025年中心利润表 '!G112+'2025年江苏分部利润表'!G112+'2025年浙江分部利润表'!G112+'2025年上海分部利润表'!G112+'2025年赣皖区域利润表'!G112 -> 0 | H112: ='2025年中心利润表 '!H112+'2025年江苏分部利润表'!H112+'2025年浙江分部利润表'!H112+'2025年上海分部利润表'!H112+'2025年赣皖区域利润表'!H112 -> 0 | I112: ='2025年中心利润表 '!I112+'2025年江苏分部利润表'!I112+'2025年浙江分部利润表'!I112+'2025年上海分部利润表'!I112+'2025年赣皖区域利润表'!I112 -> 0 | J112: ='2025年中心利润表 '!J112+'2025年江苏分部利润表'!J112+'2025年浙江分部利润表'!J112+'2025年上海分部利润表'!J112+'2025年赣皖区域利润表'!J112 -> 0 | ... Z112: ='2025年中心利润表 '!Z112+'2025年江苏分部利润表'!Z112+'2025年浙江分部利润表'!Z112+'2025年上海分部利润表'!Z112+'2025年赣皖区域利润表'!Z112 -> 0 | AA112: =C112+E112+G112+I112+K112+M112+O112+Q112+S112+U112+W112+Y112 -> 0 | AB112: =D112+F112+H112+J112+L112+N112+P112+R112+T112+V112+X112+Z112 -> 0 | AD112: =SUMIF($C$5:$Z$5,$AD$5,C112:Z112) -> 0 | AE112: =SUMIF($C$5:$Z$5,$AD$5,D112:AA112) -> 0 | AF112: =AA112-AD112 -> 0 | AG112: =AB112-AE112 -> 0 | AH112: =SUM('[1]2024年全面预算利润表 (销售1中心)2.8亿'!E117:H117) -> 0
A113: 工会经费 | C113: ='2025年中心利润表 '!C113+'2025年江苏分部利润表'!C113+'2025年浙江分部利润表'!C113+'2025年上海分部利润表'!C113+'2025年赣皖区域利润表'!C113 -> 0 | D113: ='2025年中心利润表 '!D113+'2025年江苏分部利润表'!D113+'2025年浙江分部利润表'!D113+'2025年上海分部利润表'!D113+'2025年赣皖区域利润表'!D113 -> 0 | E113: ='2025年中心利润表 '!E113+'2025年江苏分部利润表'!E113+'2025年浙江分部利润表'!E113+'2025年上海分部利润表'!E113+'2025年赣皖区域利润表'!E113 -> 0 | F113: ='2025年中心利润表 '!F113+'2025年江苏分部利润表'!F113+'2025年浙江分部利润表'!F113+'2025年上海分部利润表'!F113+'2025年赣皖区域利润表'!F113 -> 0 | G113: ='2025年中心利润表 '!G113+'2025年江苏分部利润表'!G113+'2025年浙江分部利润表'!G113+'2025年上海分部利润表'!G113+'2025年赣皖区域利润表'!G113 -> 0 | H113: ='2025年中心利润表 '!H113+'2025年江苏分部利润表'!H113+'2025年浙江分部利润表'!H113+'2025年上海分部利润表'!H113+'2025年赣皖区域利润表'!H113 -> 0 | I113: ='2025年中心利润表 '!I113+'2025年江苏分部利润表'!I113+'2025年浙江分部利润表'!I113+'2025年上海分部利润表'!I113+'2025年赣皖区域利润表'!I113 -> 0 | J113: ='2025年中心利润表 '!J113+'2025年江苏分部利润表'!J113+'2025年浙江分部利润表'!J113+'2025年上海分部利润表'!J113+'2025年赣皖区域利润表'!J113 -> 0 | ... Z113: ='2025年中心利润表 '!Z113+'2025年江苏分部利润表'!Z113+'2025年浙江分部利润表'!Z113+'2025年上海分部利润表'!Z113+'2025年赣皖区域利润表'!Z113 -> 0 | AA113: =C113+E113+G113+I113+K113+M113+O113+Q113+S113+U113+W113+Y113 -> 0 | AB113: =D113+F113+H113+J113+L113+N113+P113+R113+T113+V113+X113+Z113 -> 0 | AD113: =SUMIF($C$5:$Z$5,$AD$5,C113:Z113) -> 0 | AE113: =SUMIF($C$5:$Z$5,$AD$5,D113:AA113) -> 0 | AF113: =AA113-AD113 -> 0 | AG113: =AB113-AE113 -> 0 | AH113: =SUM('[1]2024年全面预算利润表 (销售1中心)2.8亿'!E118:H118) -> 0
A114: 职工教育经费 | C114: ='2025年中心利润表 '!C114+'2025年江苏分部利润表'!C114+'2025年浙江分部利润表'!C114+'2025年上海分部利润表'!C114+'2025年赣皖区域利润表'!C114 -> 0 | D114: ='2025年中心利润表 '!D114+'2025年江苏分部利润表'!D114+'2025年浙江分部利润表'!D114+'2025年上海分部利润表'!D114+'2025年赣皖区域利润表'!D114 -> 0 | E114: ='2025年中心利润表 '!E114+'2025年江苏分部利润表'!E114+'2025年浙江分部利润表'!E114+'2025年上海分部利润表'!E114+'2025年赣皖区域利润表'!E114 -> 0 | F114: ='2025年中心利润表 '!F114+'2025年江苏分部利润表'!F114+'2025年浙江分部利润表'!F114+'2025年上海分部利润表'!F114+'2025年赣皖区域利润表'!F114 -> 0 | G114: ='2025年中心利润表 '!G114+'2025年江苏分部利润表'!G114+'2025年浙江分部利润表'!G114+'2025年上海分部利润表'!G114+'2025年赣皖区域利润表'!G114 -> 0 | H114: ='2025年中心利润表 '!H114+'2025年江苏分部利润表'!H114+'2025年浙江分部利润表'!H114+'2025年上海分部利润表'!H114+'2025年赣皖区域利润表'!H114 -> 0 | I114: ='2025年中心利润表 '!I114+'2025年江苏分部利润表'!I114+'2025年浙江分部利润表'!I114+'2025年上海分部利润表'!I114+'2025年赣皖区域利润表'!I114 -> 0 | J114: ='2025年中心利润表 '!J114+'2025年江苏分部利润表'!J114+'2025年浙江分部利润表'!J114+'2025年上海分部利润表'!J114+'2025年赣皖区域利润表'!J114 -> 0 | ... Z114: ='2025年中心利润表 '!Z114+'2025年江苏分部利润表'!Z114+'2025年浙江分部利润表'!Z114+'2025年上海分部利润表'!Z114+'2025年赣皖区域利润表'!Z114 -> 0 | AA114: =C114+E114+G114+I114+K114+M114+O114+Q114+S114+U114+W114+Y114 -> 0 | AB114: =D114+F114+H114+J114+L114+N114+P114+R114+T114+V114+X114+Z114 -> 0 | AD114: =SUMIF($C$5:$Z$5,$AD$5,C114:Z114) -> 0 | AE114: =SUMIF($C$5:$Z$5,$AD$5,D114:AA114) -> 0 | AF114: =AA114-AD114 -> 0 | AG114: =AB114-AE114 -> 0 | AH114: =SUM('[1]2024年全面预算利润表 (销售1中心)2.8亿'!E119:H119) -> 0
A115: 福利费 | C115: =SUM(C116:C122) -> 0 | D115: =SUM(D116:D122) -> 0 | E115: =SUM(E116:E122) -> 0 | F115: =SUM(F116:F122) -> 0 | G115: =SUM(G116:G122) -> 0 | H115: =SUM(H116:H122) -> 0 | I115: =SUM(I116:I122) -> 0 | J115: =SUM(J116:J122) -> 0 | ... Z115: =SUM(Z116:Z122) -> 0 | AA115: =C115+E115+G115+I115+K115+M115+O115+Q115+S115+U115+W115+Y115 -> 0 | AB115: =D115+F115+H115+J115+L115+N115+P115+R115+T115+V115+X115+Z115 -> 0 | AD115: =SUMIF($C$5:$Z$5,$AD$5,C115:Z115) -> 0 | AE115: =SUMIF($C$5:$Z$5,$AD$5,D115:AA115) -> 0 | AF115: =AA115-AD115 -> 0 | AG115: =AB115-AE115 -> 0 | AH115: =SUM('[1]2024年全面预算利润表 (销售1中心)2.8亿'!E120:H120) -> 0
A116: 职工房租 | C116: ='2025年中心利润表 '!C116+'2025年江苏分部利润表'!C116+'2025年浙江分部利润表'!C116+'2025年上海分部利润表'!C116+'2025年赣皖区域利润表'!C116 -> 0 | D116: ='2025年中心利润表 '!D116+'2025年江苏分部利润表'!D116+'2025年浙江分部利润表'!D116+'2025年上海分部利润表'!D116+'2025年赣皖区域利润表'!D116 -> 0 | E116: ='2025年中心利润表 '!E116+'2025年江苏分部利润表'!E116+'2025年浙江分部利润表'!E116+'2025年上海分部利润表'!E116+'2025年赣皖区域利润表'!E116 -> 0 | F116: ='2025年中心利润表 '!F116+'2025年江苏分部利润表'!F116+'2025年浙江分部利润表'!F116+'2025年上海分部利润表'!F116+'2025年赣皖区域利润表'!F116 -> 0 | G116: ='2025年中心利润表 '!G116+'2025年江苏分部利润表'!G116+'2025年浙江分部利润表'!G116+'2025年上海分部利润表'!G116+'2025年赣皖区域利润表'!G116 -> 0 | H116: ='2025年中心利润表 '!H116+'2025年江苏分部利润表'!H116+'2025年浙江分部利润表'!H116+'2025年上海分部利润表'!H116+'2025年赣皖区域利润表'!H116 -> 0 | I116: ='2025年中心利润表 '!I116+'2025年江苏分部利润表'!I116+'2025年浙江分部利润表'!I116+'2025年上海分部利润表'!I116+'2025年赣皖区域利润表'!I116 -> 0 | J116: ='2025年中心利润表 '!J116+'2025年江苏分部利润表'!J116+'2025年浙江分部利润表'!J116+'2025年上海分部利润表'!J116+'2025年赣皖区域利润表'!J116 -> 0 | ... Z116: ='2025年中心利润表 '!Z116+'2025年江苏分部利润表'!Z116+'2025年浙江分部利润表'!Z116+'2025年上海分部利润表'!Z116+'2025年赣皖区域利润表'!Z116 -> 0 | AA116: =C116+E116+G116+I116+K116+M116+O116+Q116+S116+U116+W116+Y116 -> 0 | AB116: =D116+F116+H116+J116+L116+N116+P116+R116+T116+V116+X116+Z116 -> 0 | AD116: =SUMIF($C$5:$Z$5,$AD$5,C116:Z116) -> 0 | AE116: =SUMIF($C$5:$Z$5,$AD$5,D116:AA116) -> 0 | AF116: =AA116-AD116 -> 0 | AG116: =AB116-AE116 -> 0 | AH116: =SUM('[1]2024年全面预算利润表 (销售1中心)2.8亿'!E121:H121) -> 0
A117: 水电物业费 | C117: ='2025年中心利润表 '!C117+'2025年江苏分部利润表'!C117+'2025年浙江分部利润表'!C117+'2025年上海分部利润表'!C117+'2025年赣皖区域利润表'!C117 -> 0 | D117: ='2025年中心利润表 '!D117+'2025年江苏分部利润表'!D117+'2025年浙江分部利润表'!D117+'2025年上海分部利润表'!D117+'2025年赣皖区域利润表'!D117 -> 0 | E117: ='2025年中心利润表 '!E117+'2025年江苏分部利润表'!E117+'2025年浙江分部利润表'!E117+'2025年上海分部利润表'!E117+'2025年赣皖区域利润表'!E117 -> 0 | F117: ='2025年中心利润表 '!F117+'2025年江苏分部利润表'!F117+'2025年浙江分部利润表'!F117+'2025年上海分部利润表'!F117+'2025年赣皖区域利润表'!F117 -> 0 | G117: ='2025年中心利润表 '!G117+'2025年江苏分部利润表'!G117+'2025年浙江分部利润表'!G117+'2025年上海分部利润表'!G117+'2025年赣皖区域利润表'!G117 -> 0 | H117: ='2025年中心利润表 '!H117+'2025年江苏分部利润表'!H117+'2025年浙江分部利润表'!H117+'2025年上海分部利润表'!H117+'2025年赣皖区域利润表'!H117 -> 0 | I117: ='2025年中心利润表 '!I117+'2025年江苏分部利润表'!I117+'2025年浙江分部利润表'!I117+'2025年上海分部利润表'!I117+'2025年赣皖区域利润表'!I117 -> 0 | J117: ='2025年中心利润表 '!J117+'2025年江苏分部利润表'!J117+'2025年浙江分部利润表'!J117+'2025年上海分部利润表'!J117+'2025年赣皖区域利润表'!J117 -> 0 | ... Z117: ='2025年中心利润表 '!Z117+'2025年江苏分部利润表'!Z117+'2025年浙江分部利润表'!Z117+'2025年上海分部利润表'!Z117+'2025年赣皖区域利润表'!Z117 -> 0 | AA117: =C117+E117+G117+I117+K117+M117+O117+Q117+S117+U117+W117+Y117 -> 0 | AB117: =D117+F117+H117+J117+L117+N117+P117+R117+T117+V117+X117+Z117 -> 0 | AD117: =SUMIF($C$5:$Z$5,$AD$5,C117:Z117) -> 0 | AE117: =SUMIF($C$5:$Z$5,$AD$5,D117:AA117) -> 0 | AF117: =AA117-AD117 -> 0 | AG117: =AB117-AE117 -> 0 | AH117: =SUM('[1]2024年全面预算利润表 (销售1中心)2.8亿'!E122:H122) -> 0
A118: 员工餐 | C118: ='2025年中心利润表 '!C118+'2025年江苏分部利润表'!C118+'2025年浙江分部利润表'!C118+'2025年上海分部利润表'!C118+'2025年赣皖区域利润表'!C118 -> 0 | D118: ='2025年中心利润表 '!D118+'2025年江苏分部利润表'!D118+'2025年浙江分部利润表'!D118+'2025年上海分部利润表'!D118+'2025年赣皖区域利润表'!D118 -> 0 | E118: ='2025年中心利润表 '!E118+'2025年江苏分部利润表'!E118+'2025年浙江分部利润表'!E118+'2025年上海分部利润表'!E118+'2025年赣皖区域利润表'!E118 -> 0 | F118: ='2025年中心利润表 '!F118+'2025年江苏分部利润表'!F118+'2025年浙江分部利润表'!F118+'2025年上海分部利润表'!F118+'2025年赣皖区域利润表'!F118 -> 0 | G118: ='2025年中心利润表 '!G118+'2025年江苏分部利润表'!G118+'2025年浙江分部利润表'!G118+'2025年上海分部利润表'!G118+'2025年赣皖区域利润表'!G118 -> 0 | H118: ='2025年中心利润表 '!H118+'2025年江苏分部利润表'!H118+'2025年浙江分部利润表'!H118+'2025年上海分部利润表'!H118+'2025年赣皖区域利润表'!H118 -> 0 | I118: ='2025年中心利润表 '!I118+'2025年江苏分部利润表'!I118+'2025年浙江分部利润表'!I118+'2025年上海分部利润表'!I118+'2025年赣皖区域利润表'!I118 -> 0 | J118: ='2025年中心利润表 '!J118+'2025年江苏分部利润表'!J118+'2025年浙江分部利润表'!J118+'2025年上海分部利润表'!J118+'2025年赣皖区域利润表'!J118 -> 0 | ... Z118: ='2025年中心利润表 '!Z118+'2025年江苏分部利润表'!Z118+'2025年浙江分部利润表'!Z118+'2025年上海分部利润表'!Z118+'2025年赣皖区域利润表'!Z118 -> 0 | AA118: =C118+E118+G118+I118+K118+M118+O118+Q118+S118+U118+W118+Y118 -> 0 | AB118: =D118+F118+H118+J118+L118+N118+P118+R118+T118+V118+X118+Z118 -> 0 | AD118: =SUMIF($C$5:$Z$5,$AD$5,C118:Z118) -> 0 | AE118: =SUMIF($C$5:$Z$5,$AD$5,D118:AA118) -> 0 | AF118: =AA118-AD118 -> 0 | AG118: =AB118-AE118 -> 0 | AH118: =SUM('[1]2024年全面预算利润表 (销售1中心)2.8亿'!E123:H123) -> 0
A119: 节日礼品 | C119: ='2025年中心利润表 '!C119+'2025年江苏分部利润表'!C119+'2025年浙江分部利润表'!C119+'2025年上海分部利润表'!C119+'2025年赣皖区域利润表'!C119 -> 0 | D119: ='2025年中心利润表 '!D119+'2025年江苏分部利润表'!D119+'2025年浙江分部利润表'!D119+'2025年上海分部利润表'!D119+'2025年赣皖区域利润表'!D119 -> 0 | E119: ='2025年中心利润表 '!E119+'2025年江苏分部利润表'!E119+'2025年浙江分部利润表'!E119+'2025年上海分部利润表'!E119+'2025年赣皖区域利润表'!E119 -> 0 | F119: ='2025年中心利润表 '!F119+'2025年江苏分部利润表'!F119+'2025年浙江分部利润表'!F119+'2025年上海分部利润表'!F119+'2025年赣皖区域利润表'!F119 -> 0 | G119: ='2025年中心利润表 '!G119+'2025年江苏分部利润表'!G119+'2025年浙江分部利润表'!G119+'2025年上海分部利润表'!G119+'2025年赣皖区域利润表'!G119 -> 0 | H119: ='2025年中心利润表 '!H119+'2025年江苏分部利润表'!H119+'2025年浙江分部利润表'!H119+'2025年上海分部利润表'!H119+'2025年赣皖区域利润表'!H119 -> 0 | I119: ='2025年中心利润表 '!I119+'2025年江苏分部利润表'!I119+'2025年浙江分部利润表'!I119+'2025年上海分部利润表'!I119+'2025年赣皖区域利润表'!I119 -> 0 | J119: ='2025年中心利润表 '!J119+'2025年江苏分部利润表'!J119+'2025年浙江分部利润表'!J119+'2025年上海分部利润表'!J119+'2025年赣皖区域利润表'!J119 -> 0 | ... Z119: ='2025年中心利润表 '!Z119+'2025年江苏分部利润表'!Z119+'2025年浙江分部利润表'!Z119+'2025年上海分部利润表'!Z119+'2025年赣皖区域利润表'!Z119 -> 0 | AA119: =C119+E119+G119+I119+K119+M119+O119+Q119+S119+U119+W119+Y119 -> 0 | AB119: =D119+F119+H119+J119+L119+N119+P119+R119+T119+V119+X119+Z119 -> 0 | AD119: =SUMIF($C$5:$Z$5,$AD$5,C119:Z119) -> 0 | AE119: =SUMIF($C$5:$Z$5,$AD$5,D119:AA119) -> 0 | AF119: =AA119-AD119 -> 0 | AG119: =AB119-AE119 -> 0 | AH119: =SUM('[1]2024年全面预算利润表 (销售1中心)2.8亿'!E124:H124) -> 0
A120: 生日礼品 | C120: ='2025年中心利润表 '!C120+'2025年江苏分部利润表'!C120+'2025年浙江分部利润表'!C120+'2025年上海分部利润表'!C120+'2025年赣皖区域利润表'!C120 -> 0 | D120: ='2025年中心利润表 '!D120+'2025年江苏分部利润表'!D120+'2025年浙江分部利润表'!D120+'2025年上海分部利润表'!D120+'2025年赣皖区域利润表'!D120 -> 0 | E120: ='2025年中心利润表 '!E120+'2025年江苏分部利润表'!E120+'2025年浙江分部利润表'!E120+'2025年上海分部利润表'!E120+'2025年赣皖区域利润表'!E120 -> 0 | F120: ='2025年中心利润表 '!F120+'2025年江苏分部利润表'!F120+'2025年浙江分部利润表'!F120+'2025年上海分部利润表'!F120+'2025年赣皖区域利润表'!F120 -> 0 | G120: ='2025年中心利润表 '!G120+'2025年江苏分部利润表'!G120+'2025年浙江分部利润表'!G120+'2025年上海分部利润表'!G120+'2025年赣皖区域利润表'!G120 -> 0 | H120: ='2025年中心利润表 '!H120+'2025年江苏分部利润表'!H120+'2025年浙江分部利润表'!H120+'2025年上海分部利润表'!H120+'2025年赣皖区域利润表'!H120 -> 0 | I120: ='2025年中心利润表 '!I120+'2025年江苏分部利润表'!I120+'2025年浙江分部利润表'!I120+'2025年上海分部利润表'!I120+'2025年赣皖区域利润表'!I120 -> 0 | J120: ='2025年中心利润表 '!J120+'2025年江苏分部利润表'!J120+'2025年浙江分部利润表'!J120+'2025年上海分部利润表'!J120+'2025年赣皖区域利润表'!J120 -> 0 | ... Z120: ='2025年中心利润表 '!Z120+'2025年江苏分部利润表'!Z120+'2025年浙江分部利润表'!Z120+'2025年上海分部利润表'!Z120+'2025年赣皖区域利润表'!Z120 -> 0 | AA120: =C120+E120+G120+I120+K120+M120+O120+Q120+S120+U120+W120+Y120 -> 0 | AB120: =D120+F120+H120+J120+L120+N120+P120+R120+T120+V120+X120+Z120 -> 0 | AD120: =SUMIF($C$5:$Z$5,$AD$5,C120:Z120) -> 0 | AE120: =SUMIF($C$5:$Z$5,$AD$5,D120:AA120) -> 0 | AF120: =AA120-AD120 -> 0 | AG120: =AB120-AE120 -> 0 | AH120: =SUM('[1]2024年全面预算利润表 (销售1中心)2.8亿'!E125:H125) -> 0
A121: 体检 | C121: ='2025年中心利润表 '!C121+'2025年江苏分部利润表'!C121+'2025年浙江分部利润表'!C121+'2025年上海分部利润表'!C121+'2025年赣皖区域利润表'!C121 -> 0 | D121: ='2025年中心利润表 '!D121+'2025年江苏分部利润表'!D121+'2025年浙江分部利润表'!D121+'2025年上海分部利润表'!D121+'2025年赣皖区域利润表'!D121 -> 0 | E121: ='2025年中心利润表 '!E121+'2025年江苏分部利润表'!E121+'2025年浙江分部利润表'!E121+'2025年上海分部利润表'!E121+'2025年赣皖区域利润表'!E121 -> 0 | F121: ='2025年中心利润表 '!F121+'2025年江苏分部利润表'!F121+'2025年浙江分部利润表'!F121+'2025年上海分部利润表'!F121+'2025年赣皖区域利润表'!F121 -> 0 | G121: ='2025年中心利润表 '!G121+'2025年江苏分部利润表'!G121+'2025年浙江分部利润表'!G121+'2025年上海分部利润表'!G121+'2025年赣皖区域利润表'!G121 -> 0 | H121: ='2025年中心利润表 '!H121+'2025年江苏分部利润表'!H121+'2025年浙江分部利润表'!H121+'2025年上海分部利润表'!H121+'2025年赣皖区域利润表'!H121 -> 0 | I121: ='2025年中心利润表 '!I121+'2025年江苏分部利润表'!I121+'2025年浙江分部利润表'!I121+'2025年上海分部利润表'!I121+'2025年赣皖区域利润表'!I121 -> 0 | J121: ='2025年中心利润表 '!J121+'2025年江苏分部利润表'!J121+'2025年浙江分部利润表'!J121+'2025年上海分部利润表'!J121+'2025年赣皖区域利润表'!J121 -> 0 | ... Z121: ='2025年中心利润表 '!Z121+'2025年江苏分部利润表'!Z121+'2025年浙江分部利润表'!Z121+'2025年上海分部利润表'!Z121+'2025年赣皖区域利润表'!Z121 -> 0 | AA121: =C121+E121+G121+I121+K121+M121+O121+Q121+S121+U121+W121+Y121 -> 0 | AB121: =D121+F121+H121+J121+L121+N121+P121+R121+T121+V121+X121+Z121 -> 0 | AD121: =SUMIF($C$5:$Z$5,$AD$5,C121:Z121) -> 0 | AE121: =SUMIF($C$5:$Z$5,$AD$5,D121:AA121) -> 0 | AF121: =AA121-AD121 -> 0 | AG121: =AB121-AE121 -> 0 | AH121: =SUM('[1]2024年全面预算利润表 (销售1中心)2.8亿'!E126:H126) -> 0
A122: 其他福利支出 | C122: ='2025年中心利润表 '!C122+'2025年江苏分部利润表'!C122+'2025年浙江分部利润表'!C122+'2025年上海分部利润表'!C122+'2025年赣皖区域利润表'!C122 -> 0 | D122: ='2025年中心利润表 '!D122+'2025年江苏分部利润表'!D122+'2025年浙江分部利润表'!D122+'2025年上海分部利润表'!D122+'2025年赣皖区域利润表'!D122 -> 0 | E122: ='2025年中心利润表 '!E122+'2025年江苏分部利润表'!E122+'2025年浙江分部利润表'!E122+'2025年上海分部利润表'!E122+'2025年赣皖区域利润表'!E122 -> 0 | F122: ='2025年中心利润表 '!F122+'2025年江苏分部利润表'!F122+'2025年浙江分部利润表'!F122+'2025年上海分部利润表'!F122+'2025年赣皖区域利润表'!F122 -> 0 | G122: ='2025年中心利润表 '!G122+'2025年江苏分部利润表'!G122+'2025年浙江分部利润表'!G122+'2025年上海分部利润表'!G122+'2025年赣皖区域利润表'!G122 -> 0 | H122: ='2025年中心利润表 '!H122+'2025年江苏分部利润表'!H122+'2025年浙江分部利润表'!H122+'2025年上海分部利润表'!H122+'2025年赣皖区域利润表'!H122 -> 0 | I122: ='2025年中心利润表 '!I122+'2025年江苏分部利润表'!I122+'2025年浙江分部利润表'!I122+'2025年上海分部利润表'!I122+'2025年赣皖区域利润表'!I122 -> 0 | J122: ='2025年中心利润表 '!J122+'2025年江苏分部利润表'!J122+'2025年浙江分部利润表'!J122+'2025年上海分部利润表'!J122+'2025年赣皖区域利润表'!J122 -> 0 | ... Z122: ='2025年中心利润表 '!Z122+'2025年江苏分部利润表'!Z122+'2025年浙江分部利润表'!Z122+'2025年上海分部利润表'!Z122+'2025年赣皖区域利润表'!Z122 -> 0 | AA122: =C122+E122+G122+I122+K122+M122+O122+Q122+S122+U122+W122+Y122 -> 0 | AB122: =D122+F122+H122+J122+L122+N122+P122+R122+T122+V122+X122+Z122 -> 0 | AD122: =SUMIF($C$5:$Z$5,$AD$5,C122:Z122) -> 0 | AE122: =SUMIF($C$5:$Z$5,$AD$5,D122:AA122) -> 0 | AF122: =AA122-AD122 -> 0 | AG122: =AB122-AE122 -> 0 | AH122: =SUM('[1]2024年全面预算利润表 (销售1中心)2.8亿'!E127:H127) -> 0
A123: 招聘费 | C123: ='2025年中心利润表 '!C123+'2025年江苏分部利润表'!C123+'2025年浙江分部利润表'!C123+'2025年上海分部利润表'!C123+'2025年赣皖区域利润表'!C123 -> 0 | D123: ='2025年中心利润表 '!D123+'2025年江苏分部利润表'!D123+'2025年浙江分部利润表'!D123+'2025年上海分部利润表'!D123+'2025年赣皖区域利润表'!D123 -> 0 | E123: ='2025年中心利润表 '!E123+'2025年江苏分部利润表'!E123+'2025年浙江分部利润表'!E123+'2025年上海分部利润表'!E123+'2025年赣皖区域利润表'!E123 -> 0 | F123: ='2025年中心利润表 '!F123+'2025年江苏分部利润表'!F123+'2025年浙江分部利润表'!F123+'2025年上海分部利润表'!F123+'2025年赣皖区域利润表'!F123 -> 0 | G123: ='2025年中心利润表 '!G123+'2025年江苏分部利润表'!G123+'2025年浙江分部利润表'!G123+'2025年上海分部利润表'!G123+'2025年赣皖区域利润表'!G123 -> 0 | H123: ='2025年中心利润表 '!H123+'2025年江苏分部利润表'!H123+'2025年浙江分部利润表'!H123+'2025年上海分部利润表'!H123+'2025年赣皖区域利润表'!H123 -> 0 | I123: ='2025年中心利润表 '!I123+'2025年江苏分部利润表'!I123+'2025年浙江分部利润表'!I123+'2025年上海分部利润表'!I123+'2025年赣皖区域利润表'!I123 -> 0 | J123: ='2025年中心利润表 '!J123+'2025年江苏分部利润表'!J123+'2025年浙江分部利润表'!J123+'2025年上海分部利润表'!J123+'2025年赣皖区域利润表'!J123 -> 0 | ... Z123: ='2025年中心利润表 '!Z123+'2025年江苏分部利润表'!Z123+'2025年浙江分部利润表'!Z123+'2025年上海分部利润表'!Z123+'2025年赣皖区域利润表'!Z123 -> 0 | AA123: =C123+E123+G123+I123+K123+M123+O123+Q123+S123+U123+W123+Y123 -> 0 | AB123: =D123+F123+H123+J123+L123+N123+P123+R123+T123+V123+X123+Z123 -> 0 | AD123: =SUMIF($C$5:$Z$5,$AD$5,C123:Z123) -> 0 | AE123: =SUMIF($C$5:$Z$5,$AD$5,D123:AA123) -> 0 | AF123: =AA123-AD123 -> 0 | AG123: =AB123-AE123 -> 0 | AH123: =SUM('[1]2024年全面预算利润表 (销售1中心)2.8亿'!E128:H128) -> 0
...

Sheet 2025年中心利润表 
A1: 中心利润表
A2: 46021 | AB2: 会企01表
A3: 编制单位：江苏美鑫食品科技有限公司 | AB3: 单位：元
A4: 项 目 | B4: 行次 | C4: 45658 | E4: 45689 | G4: 45717 | I4: 45748 | K4: 45778 | M4: 45809 | O4: 45839 | Q4: 45870 | S4: 45901 | U4: 45931 | W4: 45962 | Y4: 45992 | AA4: 2025年合计 | AD4: 2025年合计逆向验证 | AF4: 检验结果
C5: 预算数 | D5: 本月实际 | E5: 预算数 | F5: 本月实际 | G5: 预算数 | H5: 本月实际 | I5: 预算数 | J5: 本月实际 | K5: 预算数 | L5: 本月实际 | M5: 预算数 | N5: 本月实际 | O5: 预算数 | P5: 本月实际 | Q5: 预算数 | R5: 本月实际 | S5: 预算数 | T5: 本月实际 | U5: 预算数 | V5: 本月实际 | W5: 预算数 | X5: 本月实际 | Y5: 预算数 | Z5: 本月实际 | AA5: 预算数 | AB5: 本年实际 | AD5: 预算数 | AE5: 本月实际 | AF5: 预算数 | AG5: 本月实际
A6: 一、营业收入 | B6: 1 | C6: =SUM(C7:C13,C15,-C14) -> 0 | D6: =SUM(D7:D13,D15,-D14) -> 81119.48 | E6: =SUM(E7:E13,E15,-E14) -> 0 | F6: =SUM(F7:F13,F15,-F14) -> 10464.61 | G6: =SUM(G7:G13,G15,-G14) -> 0 | H6: =SUM(H7:H13,H15,-H14) -> 20687.61 | I6: =SUM(I7:I13,I15,-I14) -> 0 | J6: =SUM(J7:J13,J15,-J14) -> 29819.47 | ... Z6: =SUM(Z7:Z13,Z15,-Z14) -> 5973.45 | AA6: =C6+E6+G6+I6+K6+M6+O6+Q6+S6+U6+W6+Y6 -> 0 | AB6: =D6+F6+H6+J6+L6+N6+P6+R6+T6+V6+X6+Z6 -> 219132.76 | AD6: =SUMIF($C$5:$Z$5,$AD$5,C6:Z6) -> 0 | AE6: =SUMIF($C$5:$Z$5,$AD$5,D6:AA6) -> 219132.76 | AF6: =AA6-AD6 -> 0 | AG6: =AB6-AE6 -> 0
A7: 中式汤底 | D7: 22716.82 | F7: 243.36 | H7: 265.49 | AA7: =C7+E7+G7+I7+K7+M7+O7+Q7+S7+U7+W7+Y7 -> 0 | AB7: =D7+F7+H7+J7+L7+N7+P7+R7+T7+V7+X7+Z7 -> 23225.67 | AD7: =SUMIF($C$5:$Z$5,$AD$5,C7:Z7) -> 0 | AE7: =SUMIF($C$5:$Z$5,$AD$5,D7:AA7) -> 23225.67 | AF7: =AA7-AD7 -> 0 | AG7: =AB7-AE7 -> 0
A8: 酱料 | D8: 23057.52 | F8: 331.86 | H8: 300.88 | AA8: =C8+E8+G8+I8+K8+M8+O8+Q8+S8+U8+W8+Y8 -> 0 | AB8: =D8+F8+H8+J8+L8+N8+P8+R8+T8+V8+X8+Z8 -> 23690.26 | AD8: =SUMIF($C$5:$Z$5,$AD$5,C8:Z8) -> 0 | AE8: =SUMIF($C$5:$Z$5,$AD$5,D8:AA8) -> 23690.26 | AF8: =AA8-AD8 -> 0 | AG8: =AB8-AE8 -> 0
A9: 川味底料 | D9: 11442.48 | F9: 398.23 | H9: 594.69 | J9: 10828.32 | N9: 7123.89 | R9: 2849.56 | T9: 5383.63 | AA9: =C9+E9+G9+I9+K9+M9+O9+Q9+S9+U9+W9+Y9 -> 0 | AB9: =D9+F9+H9+J9+L9+N9+P9+R9+T9+V9+X9+Z9 -> 38620.8 | AD9: =SUMIF($C$5:$Z$5,$AD$5,C9:Z9) -> 0 | AE9: =SUMIF($C$5:$Z$5,$AD$5,D9:AA9) -> 38620.8 | AF9: =AA9-AD9 -> 0 | AG9: =AB9-AE9 -> 0
A10: 调味汁 | AA10: =C10+E10+G10+I10+K10+M10+O10+Q10+S10+U10+W10+Y10 -> 0 | AB10: =D10+F10+H10+J10+L10+N10+P10+R10+T10+V10+X10+Z10 -> 0 | AD10: =SUMIF($C$5:$Z$5,$AD$5,C10:Z10) -> 0 | AE10: =SUMIF($C$5:$Z$5,$AD$5,D10:AA10) -> 0 | AF10: =AA10-AD10 -> 0 | AG10: =AB10-AE10 -> 0
A11: 复合调味粉 | AA11: =C11+E11+G11+I11+K11+M11+O11+Q11+S11+U11+W11+Y11 -> 0 | AB11: =D11+F11+H11+J11+L11+N11+P11+R11+T11+V11+X11+Z11 -> 0 | AD11: =SUMIF($C$5:$Z$5,$AD$5,C11:Z11) -> 0 | AE11: =SUMIF($C$5:$Z$5,$AD$5,D11:AA11) -> 0 | AF11: =AA11-AD11 -> 0 | AG11: =AB11-AE11 -> 0
A12: 团餐 | AA12: =C12+E12+G12+I12+K12+M12+O12+Q12+S12+U12+W12+Y12 -> 0 | AB12: =D12+F12+H12+J12+L12+N12+P12+R12+T12+V12+X12+Z12 -> 0 | AD12: =SUMIF($C$5:$Z$5,$AD$5,C12:Z12) -> 0 | AE12: =SUMIF($C$5:$Z$5,$AD$5,D12:AA12) -> 0 | AF12: =AA12-AD12 -> 0 | AG12: =AB12-AE12 -> 0
A13: 预制菜 | D13: 23048.68 | F13: 8960.19 | H13: 19526.55 | J13: 18991.15 | L13: 12482.3 | N13: 11498.89 | P13: 12631.64 | T13: 6187.61 | X13: 12910.62 | Z13: 5973.45 | AA13: =C13+E13+G13+I13+K13+M13+O13+Q13+S13+U13+W13+Y13 -> 0 | AB13: =D13+F13+H13+J13+L13+N13+P13+R13+T13+V13+X13+Z13 -> 132211.08 | AD13: =SUMIF($C$5:$Z$5,$AD$5,C13:Z13) -> 0 | AE13: =SUMIF($C$5:$Z$5,$AD$5,D13:AA13) -> 132211.08 | AF13: =AA13-AD13 -> 0 | AG13: =AB13-AE13 -> 0
A14: 返利 | AA14: =C14+E14+G14+I14+K14+M14+O14+Q14+S14+U14+W14+Y14 -> 0 | AB14: =D14+F14+H14+J14+L14+N14+P14+R14+T14+V14+X14+Z14 -> 0 | AD14: =SUMIF($C$5:$Z$5,$AD$5,C14:Z14) -> 0 | AE14: =SUMIF($C$5:$Z$5,$AD$5,D14:AA14) -> 0
A15: 其他 | D15: 853.98 | F15: 530.97 | AA15: =C15+E15+G15+I15+K15+M15+O15+Q15+S15+U15+W15+Y15 -> 0 | AB15: =D15+F15+H15+J15+L15+N15+P15+R15+T15+V15+X15+Z15 -> 1384.95 | AD15: =SUMIF($C$5:$Z$5,$AD$5,C15:Z15) -> 0 | AE15: =SUMIF($C$5:$Z$5,$AD$5,D15:AA15) -> 1384.95 | AF15: =AA15-AD15 -> 0 | AG15: =AB15-AE15 -> 0
A16: 减：营业成本 | B16: 2 | C16: =SUM(C17:C25) -> 0 | D16: =SUM(D17:D25) -> 52622.57 | E16: =SUM(E17:E25) -> 0 | F16: =SUM(F17:F25) -> 9814.48 | G16: =SUM(G17:G25) -> 0 | H16: =SUM(H17:H25) -> 19889.02 | I16: =SUM(I17:I25) -> 0 | J16: =SUM(J17:J25) -> 24662.3 | ... Z16: =SUM(Z17:Z25) -> 5399.96 | AA16: =C16+E16+G16+I16+K16+M16+O16+Q16+S16+U16+W16+Y16 -> 0 | AB16: =D16+F16+H16+J16+L16+N16+P16+R16+T16+V16+X16+Z16 -> 174348.35 | AD16: =SUMIF($C$5:$Z$5,$AD$5,C16:Z16) -> 0 | AE16: =SUMIF($C$5:$Z$5,$AD$5,D16:AA16) -> 174348.35 | AF16: =AA16-AD16 -> 0 | AG16: =AB16-AE16 -> 0
A17: 中式汤底 | D17: 9979.56 | F17: 81.51 | H17: 167.05 | AA17: =C17+E17+G17+I17+K17+M17+O17+Q17+S17+U17+W17+Y17 -> 0 | AB17: =D17+F17+H17+J17+L17+N17+P17+R17+T17+V17+X17+Z17 -> 10228.12 | AD17: =SUMIF($C$5:$Z$5,$AD$5,C17:Z17) -> 0 | AE17: =SUMIF($C$5:$Z$5,$AD$5,D17:AA17) -> 10228.12 | AF17: =AA17-AD17 -> 0 | AG17: =AB17-AE17 -> 0
A18: 酱料 | D18: 8014.71 | F18: 157.61 | H18: 228.93 | AA18: =C18+E18+G18+I18+K18+M18+O18+Q18+S18+U18+W18+Y18 -> 0 | AB18: =D18+F18+H18+J18+L18+N18+P18+R18+T18+V18+X18+Z18 -> 8401.25 | AD18: =SUMIF($C$5:$Z$5,$AD$5,C18:Z18) -> 0 | AE18: =SUMIF($C$5:$Z$5,$AD$5,D18:AA18) -> 8401.25 | AF18: =AA18-AD18 -> 0 | AG18: =AB18-AE18 -> 0
A19: 川味底料 | D19: 6593.47 | F19: 220 | H19: 493.39 | J19: 6297.25 | N19: 3908.39 | R19: 1563.36 | T19: 2953.63 | AA19: =C19+E19+G19+I19+K19+M19+O19+Q19+S19+U19+W19+Y19 -> 0 | AB19: =D19+F19+H19+J19+L19+N19+P19+R19+T19+V19+X19+Z19 -> 22029.49 | AD19: =SUMIF($C$5:$Z$5,$AD$5,C19:Z19) -> 0 | AE19: =SUMIF($C$5:$Z$5,$AD$5,D19:AA19) -> 22029.49 | AF19: =AA19-AD19 -> 0 | AG19: =AB19-AE19 -> 0
A20: 调味汁 | AA20: =C20+E20+G20+I20+K20+M20+O20+Q20+S20+U20+W20+Y20 -> 0 | AB20: =D20+F20+H20+J20+L20+N20+P20+R20+T20+V20+X20+Z20 -> 0 | AD20: =SUMIF($C$5:$Z$5,$AD$5,C20:Z20) -> 0 | AE20: =SUMIF($C$5:$Z$5,$AD$5,D20:AA20) -> 0 | AF20: =AA20-AD20 -> 0 | AG20: =AB20-AE20 -> 0
A21: 复合调味粉 | AA21: =C21+E21+G21+I21+K21+M21+O21+Q21+S21+U21+W21+Y21 -> 0 | AB21: =D21+F21+H21+J21+L21+N21+P21+R21+T21+V21+X21+Z21 -> 0 | AD21: =SUMIF($C$5:$Z$5,$AD$5,C21:Z21) -> 0 | AE21: =SUMIF($C$5:$Z$5,$AD$5,D21:AA21) -> 0 | AF21: =AA21-AD21 -> 0 | AG21: =AB21-AE21 -> 0
A22: 团餐 | AA22: =C22+E22+G22+I22+K22+M22+O22+Q22+S22+U22+W22+Y22 -> 0 | AB22: =D22+F22+H22+J22+L22+N22+P22+R22+T22+V22+X22+Z22 -> 0 | AD22: =SUMIF($C$5:$Z$5,$AD$5,C22:Z22) -> 0 | AE22: =SUMIF($C$5:$Z$5,$AD$5,D22:AA22) -> 0 | AF22: =AA22-AD22 -> 0 | AG22: =AB22-AE22 -> 0
A23: 预制菜 | D23: 22642.04 | F23: 7925.4 | H23: 18120.75 | J23: 17195.18 | L23: 11154.92 | N23: 9773.09 | P23: 11533.4 | T23: 5577.98 | X23: 12408.55 | Z23: 4735.24 | AA23: =C23+E23+G23+I23+K23+M23+O23+Q23+S23+U23+W23+Y23 -> 0 | AB23: =D23+F23+H23+J23+L23+N23+P23+R23+T23+V23+X23+Z23 -> 121066.55 | AD23: =SUMIF($C$5:$Z$5,$AD$5,C23:Z23) -> 0 | AE23: =SUMIF($C$5:$Z$5,$AD$5,D23:AA23) -> 121066.55 | AF23: =AA23-AD23 -> 0 | AG23: =AB23-AE23 -> 0
A24: 其他 | D24: 4386.36 | F24: 477.67 | Z24: =6.92 -> 6.92 | AA24: =C24+E24+G24+I24+K24+M24+O24+Q24+S24+U24+W24+Y24 -> 0 | AB24: =D24+F24+H24+J24+L24+N24+P24+R24+T24+V24+X24+Z24 -> 4870.95 | AD24: =SUMIF($C$5:$Z$5,$AD$5,C24:Z24) -> 0 | AE24: =SUMIF($C$5:$Z$5,$AD$5,D24:AA24) -> 4870.95 | AF24: =AA24-AD24 -> 0 | AG24: =AB24-AE24 -> 0
A25: 运费 | D25: 1006.43 | F25: 952.29 | H25: 878.9 | J25: 1169.87 | L25: 290.83 | N25: 780.74 | P25: 847.7 | R25: -45.41 | T25: 533.94 | X25: 678.9 | Z25: 657.8 | AA25: =C25+E25+G25+I25+K25+M25+O25+Q25+S25+U25+W25+Y25 -> 0 | AB25: =D25+F25+H25+J25+L25+N25+P25+R25+T25+V25+X25+Z25 -> 7751.99 | AD25: =SUMIF($C$5:$Z$5,$AD$5,C25:Z25) -> 0 | AE25: =SUMIF($C$5:$Z$5,$AD$5,D25:AA25) -> 7751.99 | AF25: =AA25-AD25 -> 0 | AG25: =AB25-AE25 -> 0
A26: 毛利 | B26: 3 | C26: =C6-C16 -> 0 | D26: =D6-D16 -> 28496.91 | E26: =E6-E16 -> 0 | F26: =F6-F16 -> 650.13 | G26: =G6-G16 -> 0 | H26: =H6-H16 -> 798.59 | I26: =I6-I16 -> 0 | J26: =J6-J16 -> 5157.17 | ... Z26: =Z6-Z16 -> 573.49 | AA26: =C26+E26+G26+I26+K26+M26+O26+Q26+S26+U26+W26+Y26 -> 0 | AB26: =D26+F26+H26+J26+L26+N26+P26+R26+T26+V26+X26+Z26 -> 44784.41 | AD26: =SUMIF($C$5:$Z$5,$AD$5,C26:Z26) -> 0 | AE26: =SUMIF($C$5:$Z$5,$AD$5,D26:AA26) -> 44784.41 | AF26: =AD6-AD16-AA26 -> 0 | AG26: =AE6-AE16-AB26 -> 0
A27: 毛利率 | B27: 4 | C27: =C26/C6 -> #DIV/0! | D27: =D26/D6 -> 0.35129552 | E27: =E26/E6 -> #DIV/0! | F27: =F26/F6 -> 0.062126539 | G27: =G26/G6 -> #DIV/0! | H27: =H26/H6 -> 0.038602333 | I27: =I26/I6 -> #DIV/0! | J27: =J26/J6 -> 0.1729464 | ... AB27: =AB26/AB6 -> 0.20437113 | AD27: =AD26/AD6 -> #DIV/0! | AE27: =AE26/AE6 -> 0.20437113 | AF27: =AA27-AD27 -> #DIV/0! | AG27: =AB27-AE27 -> 0
A28: 税金及附加 | B28: 5 | C28: =C6*0.85%+C6*0.03% -> 0 | D28: =D6*0.88%+D6*0.07% -> 770.63506 | E28: =E6*0.88%+E6*0.07% -> 0 | F28: =F6*0.88%+F6*0.07% -> 99.413795 | G28: =G6*0.88%+G6*0.07% -> 0 | H28: =H6*0.88%+H6*0.07% -> 196.5323 | I28: =I6*0.88%+I6*0.07% -> 0 | J28: =J6*0.88%+J6*0.07% -> 283.28496 | K28: =K6*0.88%+K6*0.07% -> 0 | ... Z28: =Z6*0.88%+Z6*0.07% -> 56.747775 | AA28: =C28+E28+G28+I28+K28+M28+O28+Q28+S28+U28+W28+Y28 -> 0 | AB28: =D28+F28+H28+J28+L28+N28+P28+R28+T28+V28+X28+Z28 -> 2081.7612 | AD28: =SUMIF($C$5:$Z$5,$AD$5,C28:Z28) -> 0 | AE28: =SUMIF($C$5:$Z$5,$AD$5,D28:AA28) -> 2081.7612 | AF28: =AA28-AD28 -> 0 | AG28: =AB28-AE28 -> 0
A29: 销售费用 | B29: 6 | C29: =SUM(C30:C101)-C30-C33-C42-C53-C65 -> 44818.64 | D29: =SUM(D30:D101)-D30-D33-D42-D53-D65 -> 48183.95 | E29: =SUM(E30:E101)-E30-E33-E42-E53-E65 -> 31652.8 | F29: =SUM(F30:F101)-F30-F33-F42-F53-F65 -> 43456.56 | G29: =SUM(G30:G101)-G30-G33-G42-G53-G65 -> 42310.19 | H29: =SUM(H30:H101)-H30-H33-H42-H53-H65 -> -49771.99 | I29: =SUM(I30:I101)-I30-I33-I42-I53-I65 -> 46685.83 | J29: =SUM(J30:J101)-J30-J33-J42-J53-J65 -> 26981.99 | ... Z29: =SUM(Z30:Z101)-Z30-Z33-Z42-Z53-Z65 -> 18754.2 | AA29: =C29+E29+G29+I29+K29+M29+O29+Q29+S29+U29+W29+Y29 -> 599460 | AB29: =D29+F29+H29+J29+L29+N29+P29+R29+T29+V29+X29+Z29 -> 151656.62 | AD29: =SUMIF($C$5:$Z$5,$AD$5,C29:Z29) -> 599460 | AE29: =SUMIF($C$5:$Z$5,$AD$5,D29:AA29) -> 151656.62 | AF29: =AD29-(SUM(AA30:AA101)-SUM(AA30,AA33,AA42,AA53,AA65)) -> 0 | AG29: =AE29-(SUM(AB30:AB101)-SUM(AB30,AB33,AB42,AB53,AB65)) -> 0
A30: 职工薪酬 | C30: =SUM(C31:C32) -> 32443.64 | D30: =SUM(D31:D32) -> -38255.2 | E30: =SUM(E31:E32) -> 19277.8 | F30: =SUM(F31:F32) -> 35810 | G30: =SUM(G31:G32) -> 29635.19 | H30: =SUM(H31:H32) -> -58966.8 | I30: =SUM(I31:I32) -> 34310.83 | J30: =SUM(J31:J32) -> 26104 | ... Z30: =SUM(Z31:Z32) -> 16233 | AA30: =C30+E30+G30+I30+K30+M30+O30+Q30+S30+U30+W30+Y30 -> 450660 | AB30: =D30+F30+H30+J30+L30+N30+P30+R30+T30+V30+X30+Z30 -> 32213 | AD30: =SUMIF($C$5:$Z$5,$AD$5,C30:Z30) -> 450660 | AE30: =SUMIF($C$5:$Z$5,$AD$5,D30:AA30) -> 32213 | AF30: =AA30-AD30 -> 0 | AG30: =AB30-AE30 -> 0
A31: 工资 | D31: 37959.8 | F31: 35810 | H31: =-37959.8-35810 -> -73769.8 | I31: 0 | J31: 0 | K31: 0 | L31: 0 | O31: 0 | R31: 0 | S31: 0 | T31: 0 | W31: 0 | AA31: =C31+E31+G31+I31+K31+M31+O31+Q31+S31+U31+W31+Y31 -> 0 | AB31: =D31+F31+H31+J31+L31+N31+P31+R31+T31+V31+X31+Z31 -> 0 | AD31: =SUMIF($C$5:$Z$5,$AD$5,C31:Z31) -> 0 | AE31: =SUMIF($C$5:$Z$5,$AD$5,D31:AA31) -> 0 | AF31: =AA31-AD31 -> 0 | AG31: =AB31-AE31 -> 0
A32: 奖金及提成 | C32: 32443.64 | D32: -76215 | E32: 19277.8 | F32: =19239-19239 -> 0 | G32: 29635.19 | H32: =17480-2677 -> 14803 | I32: 34310.83 | J32: =35660-9556 -> 26104 | K32: 31880.84 | L32: 3574 | M32: 34062.06 | N32: =26709+2354-11842+1212-13937 -> 4496 | O32: 36365.24 | P32: =9072-3827 -> 5245 | Q32: 39996.55 | R32: 6225 | S32: 48955.37 | T32: =33110-15867 -> 17243 | U32: 40083.11 | V32: =9992-1439 -> 8553 | W32: 43515.62 | X32: =10675-4723 -> 5952 | Y32: 60133.75 | Z32: =-18547+350+23862+10568 -> 16233 | AA32: =C32+E32+G32+I32+K32+M32+O32+Q32+S32+U32+W32+Y32 -> 450660 | AB32: =D32+F32+H32+J32+L32+N32+P32+R32+T32+V32+X32+Z32 -> 32213 | AD32: =SUMIF($C$5:$Z$5,$AD$5,C32:Z32) -> 450660 | AE32: =SUMIF($C$5:$Z$5,$AD$5,D32:AA32) -> 32213 | AF32: =AA32-AD32 -> 0 | AG32: =AB32-AE32 -> 0
A33: 社保 | C33: =SUM(C34:C38) -> 0 | D33: =SUM(D34:D38) -> 0 | E33: =SUM(E34:E38) -> 0 | F33: =SUM(F34:F38) -> 0 | G33: =SUM(G34:G38) -> 0 | H33: =SUM(H34:H38) -> 0 | I33: =SUM(I34:I38) -> 0 | K33: =SUM(K34:K38) -> 0 | L33: =SUM(L34:L38) -> 0 | M33: =SUM(M34:M38) -> 0 | N33: =SUM(N34:N38) -> 0 | O33: =SUM(O34:O38) -> 0 | P33: =SUM(P34:P38) -> 0 | Q33: =SUM(Q34:Q38) -> 0 | R33: =SUM(R34:R38) -> 0 | ... Z33: =SUM(Z34:Z38) -> 0 | AA33: =C33+E33+G33+I33+K33+M33+O33+Q33+S33+U33+W33+Y33 -> 0 | AB33: =D33+F33+H33+J33+L33+N33+P33+R33+T33+V33+X33+Z33 -> 0 | AD33: =SUMIF($C$5:$Z$5,$AD$5,C33:Z33) -> 0 | AE33: =SUMIF($C$5:$Z$5,$AD$5,D33:AA33) -> 0 | AF33: =AA33-AD33 -> 0 | AG33: =AB33-AE33 -> 0
A34: 养老 | J34: 0 | AA34: =C34+E34+G34+I34+K34+M34+O34+Q34+S34+U34+W34+Y34 -> 0 | AB34: =D34+F34+H34+J34+L34+N34+P34+R34+T34+V34+X34+Z34 -> 0 | AD34: =SUMIF($C$5:$Z$5,$AD$5,C34:Z34) -> 0 | AE34: =SUMIF($C$5:$Z$5,$AD$5,D34:AA34) -> 0 | AF34: =AA34-AD34 -> 0 | AG34: =AB34-AE34 -> 0
A35: 医疗 | J35: 0 | AA35: =C35+E35+G35+I35+K35+M35+O35+Q35+S35+U35+W35+Y35 -> 0 | AB35: =D35+F35+H35+J35+L35+N35+P35+R35+T35+V35+X35+Z35 -> 0 | AD35: =SUMIF($C$5:$Z$5,$AD$5,C35:Z35) -> 0 | AE35: =SUMIF($C$5:$Z$5,$AD$5,D35:AA35) -> 0 | AF35: =AA35-AD35 -> 0 | AG35: =AB35-AE35 -> 0
A36: 工伤 | J36: 0 | AA36: =C36+E36+G36+I36+K36+M36+O36+Q36+S36+U36+W36+Y36 -> 0 | AB36: =D36+F36+H36+J36+L36+N36+P36+R36+T36+V36+X36+Z36 -> 0 | AD36: =SUMIF($C$5:$Z$5,$AD$5,C36:Z36) -> 0 | AE36: =SUMIF($C$5:$Z$5,$AD$5,D36:AA36) -> 0 | AF36: =AA36-AD36 -> 0 | AG36: =AB36-AE36 -> 0
A37: 失业 | J37: 0 | AA37: =C37+E37+G37+I37+K37+M37+O37+Q37+S37+U37+W37+Y37 -> 0 | AB37: =D37+F37+H37+J37+L37+N37+P37+R37+T37+V37+X37+Z37 -> 0 | AD37: =SUMIF($C$5:$Z$5,$AD$5,C37:Z37) -> 0 | AE37: =SUMIF($C$5:$Z$5,$AD$5,D37:AA37) -> 0 | AF37: =AA37-AD37 -> 0 | AG37: =AB37-AE37 -> 0
A38: 生育 | J38: 0 | AA38: =C38+E38+G38+I38+K38+M38+O38+Q38+S38+U38+W38+Y38 -> 0 | AB38: =D38+F38+H38+J38+L38+N38+P38+R38+T38+V38+X38+Z38 -> 0 | AD38: =SUMIF($C$5:$Z$5,$AD$5,C38:Z38) -> 0 | AE38: =SUMIF($C$5:$Z$5,$AD$5,D38:AA38) -> 0 | AF38: =AA38-AD38 -> 0 | AG38: =AB38-AE38 -> 0
A39: 公积金 | J39: 0 | AA39: =C39+E39+G39+I39+K39+M39+O39+Q39+S39+U39+W39+Y39 -> 0 | AB39: =D39+F39+H39+J39+L39+N39+P39+R39+T39+V39+X39+Z39 -> 0 | AD39: =SUMIF($C$5:$Z$5,$AD$5,C39:Z39) -> 0 | AE39: =SUMIF($C$5:$Z$5,$AD$5,D39:AA39) -> 0 | AF39: =AA39-AD39 -> 0 | AG39: =AB39-AE39 -> 0
A40: 工会经费 | J40: 0 | AA40: =C40+E40+G40+I40+K40+M40+O40+Q40+S40+U40+W40+Y40 -> 0 | AB40: =D40+F40+H40+J40+L40+N40+P40+R40+T40+V40+X40+Z40 -> 0 | AD40: =SUMIF($C$5:$Z$5,$AD$5,C40:Z40) -> 0 | AE40: =SUMIF($C$5:$Z$5,$AD$5,D40:AA40) -> 0 | AF40: =AA40-AD40 -> 0 | AG40: =AB40-AE40 -> 0
A41: 职工教育经费 | J41: 0 | AA41: =C41+E41+G41+I41+K41+M41+O41+Q41+S41+U41+W41+Y41 -> 0 | AB41: =D41+F41+H41+J41+L41+N41+P41+R41+T41+V41+X41+Z41 -> 0 | AD41: =SUMIF($C$5:$Z$5,$AD$5,C41:Z41) -> 0 | AE41: =SUMIF($C$5:$Z$5,$AD$5,D41:AA41) -> 0 | AF41: =AA41-AD41 -> 0 | AG41: =AB41-AE41 -> 0
A42: 福利费 | C42: =SUM(C43:C49) -> 0 | D42: =SUM(D43:D49) -> 0 | E42: =SUM(E43:E49) -> 0 | F42: =SUM(F43:F49) -> 2694.85 | G42: =SUM(G43:G49) -> 0 | H42: =SUM(H43:H49) -> 0 | I42: =SUM(I43:I49) -> 0 | J42: =SUM(J43:J49) -> 0 | ... Z42: =SUM(Z43:Z49) -> 0 | AA42: =C42+E42+G42+I42+K42+M42+O42+Q42+S42+U42+W42+Y42 -> 0 | AB42: =D42+F42+H42+J42+L42+N42+P42+R42+T42+V42+X42+Z42 -> 2694.85 | AD42: =SUMIF($C$5:$Z$5,$AD$5,C42:Z42) -> 0 | AE42: =SUMIF($C$5:$Z$5,$AD$5,D42:AA42) -> 2694.85 | AF42: =AA42-AD42 -> 0 | AG42: =AB42-AE42 -> 0
A43: 职工房租 | J43: 0 | AA43: =C43+E43+G43+I43+K43+M43+O43+Q43+S43+U43+W43+Y43 -> 0 | AB43: =D43+F43+H43+J43+L43+N43+P43+R43+T43+V43+X43+Z43 -> 0 | AD43: =SUMIF($C$5:$Z$5,$AD$5,C43:Z43) -> 0 | AE43: =SUMIF($C$5:$Z$5,$AD$5,D43:AA43) -> 0 | AF43: =AA43-AD43 -> 0 | AG43: =AB43-AE43 -> 0
A44: 水电物业费 | J44: 0 | AA44: =C44+E44+G44+I44+K44+M44+O44+Q44+S44+U44+W44+Y44 -> 0 | AB44: =D44+F44+H44+J44+L44+N44+P44+R44+T44+V44+X44+Z44 -> 0 | AD44: =SUMIF($C$5:$Z$5,$AD$5,C44:Z44) -> 0 | AE44: =SUMIF($C$5:$Z$5,$AD$5,D44:AA44) -> 0 | AF44: =AA44-AD44 -> 0 | AG44: =AB44-AE44 -> 0
A45: 员工餐 | J45: 0 | AA45: =C45+E45+G45+I45+K45+M45+O45+Q45+S45+U45+W45+Y45 -> 0 | AB45: =D45+F45+H45+J45+L45+N45+P45+R45+T45+V45+X45+Z45 -> 0 | AD45: =SUMIF($C$5:$Z$5,$AD$5,C45:Z45) -> 0 | AE45: =SUMIF($C$5:$Z$5,$AD$5,D45:AA45) -> 0 | AF45: =AA45-AD45 -> 0 | AG45: =AB45-AE45 -> 0
A46: 节日礼品 | J46: 0 | AA46: =C46+E46+G46+I46+K46+M46+O46+Q46+S46+U46+W46+Y46 -> 0 | AB46: =D46+F46+H46+J46+L46+N46+P46+R46+T46+V46+X46+Z46 -> 0 | AD46: =SUMIF($C$5:$Z$5,$AD$5,C46:Z46) -> 0 | AE46: =SUMIF($C$5:$Z$5,$AD$5,D46:AA46) -> 0 | AF46: =AA46-AD46 -> 0 | AG46: =AB46-AE46 -> 0
A47: 生日礼品 | J47: 0 | AA47: =C47+E47+G47+I47+K47+M47+O47+Q47+S47+U47+W47+Y47 -> 0 | AB47: =D47+F47+H47+J47+L47+N47+P47+R47+T47+V47+X47+Z47 -> 0 | AD47: =SUMIF($C$5:$Z$5,$AD$5,C47:Z47) -> 0 | AE47: =SUMIF($C$5:$Z$5,$AD$5,D47:AA47) -> 0 | AF47: =AA47-AD47 -> 0 | AG47: =AB47-AE47 -> 0
A48: 体检 | J48: 0 | AA48: =C48+E48+G48+I48+K48+M48+O48+Q48+S48+U48+W48+Y48 -> 0 | AB48: =D48+F48+H48+J48+L48+N48+P48+R48+T48+V48+X48+Z48 -> 0 | AD48: =SUMIF($C$5:$Z$5,$AD$5,C48:Z48) -> 0 | AE48: =SUMIF($C$5:$Z$5,$AD$5,D48:AA48) -> 0 | AF48: =AA48-AD48 -> 0 | AG48: =AB48-AE48 -> 0
A49: 其他福利支出 | F49: 2694.85 | J49: 0 | AA49: =C49+E49+G49+I49+K49+M49+O49+Q49+S49+U49+W49+Y49 -> 0 | AB49: =D49+F49+H49+J49+L49+N49+P49+R49+T49+V49+X49+Z49 -> 2694.85 | AD49: =SUMIF($C$5:$Z$5,$AD$5,C49:Z49) -> 0 | AE49: =SUMIF($C$5:$Z$5,$AD$5,D49:AA49) -> 2694.85 | AF49: =AA49-AD49 -> 0 | AG49: =AB49-AE49 -> 0
A50: 招聘费 | J50: 0 | AA50: =C50+E50+G50+I50+K50+M50+O50+Q50+S50+U50+W50+Y50 -> 0 | AB50: =D50+F50+H50+J50+L50+N50+P50+R50+T50+V50+X50+Z50 -> 0 | AD50: =SUMIF($C$5:$Z$5,$AD$5,C50:Z50) -> 0 | AE50: =SUMIF($C$5:$Z$5,$AD$5,D50:AA50) -> 0 | AF50: =AA50-AD50 -> 0 | AG50: =AB50-AE50 -> 0
A51: 办公费 | J51: 0 | AA51: =C51+E51+G51+I51+K51+M51+O51+Q51+S51+U51+W51+Y51 -> 0 | AB51: =D51+F51+H51+J51+L51+N51+P51+R51+T51+V51+X51+Z51 -> 0 | AD51: =SUMIF($C$5:$Z$5,$AD$5,C51:Z51) -> 0 | AE51: =SUMIF($C$5:$Z$5,$AD$5,D51:AA51) -> 0 | AF51: =AA51-AD51 -> 0 | AG51: =AB51-AE51 -> 0
A52: 市内交通费 | J52: 0 | AA52: =C52+E52+G52+I52+K52+M52+O52+Q52+S52+U52+W52+Y52 -> 0 | AB52: =D52+F52+H52+J52+L52+N52+P52+R52+T52+V52+X52+Z52 -> 0 | AD52: =SUMIF($C$5:$Z$5,$AD$5,C52:Z52) -> 0 | AE52: =SUMIF($C$5:$Z$5,$AD$5,D52:AA52) -> 0 | AF52: =AA52-AD52 -> 0 | AG52: =AB52-AE52 -> 0
A53: 差旅费 | C53: =SUM(C54:C58) -> 5275 | D53: =SUM(D54:D58) -> 51082.83 | E53: =SUM(E54:E58) -> 5275 | F53: =SUM(F54:F58) -> 2672.59 | G53: =SUM(G54:G58) -> 5275 | H53: =SUM(H54:H58) -> 5680.75 | I53: =SUM(I54:I58) -> 5275 | J53: =SUM(J54:J58) -> 3652.07 | ... Z53: =SUM(Z54:Z58) -> 2075.2 | AA53: =C53+E53+G53+I53+K53+M53+O53+Q53+S53+U53+W53+Y53 -> 63300 | AB53: =D53+F53+H53+J53+L53+N53+P53+R53+T53+V53+X53+Z53 -> 69679.14 | AD53: =SUMIF($C$5:$Z$5,$AD$5,C53:Z53) -> 63300 | AE53: =SUMIF($C$5:$Z$5,$AD$5,D53:AA53) -> 69679.14 | AF53: =AA53-AD53 -> 0 | AG53: =AB53-AE53 -> 0
A54: 交通费 | C54: 2100 | D54: 564.61 | E54: 2100 | F54: 2248.67 | G54: 2100 | H54: 1344.4 | I54: 2100 | J54: 1530.52 | K54: 2100 | L54: 414 | M54: 2100 | N54: -42.19 | O54: 2100 | P54: 616.84 | Q54: 2100 | R54: 616.39 | S54: 2100 | T54: 777.06 | U54: 2100 | W54: 2100 | Y54: 2100 | Z54: 1579.4 | AA54: =C54+E54+G54+I54+K54+M54+O54+Q54+S54+U54+W54+Y54 -> 25200 | AB54: =D54+F54+H54+J54+L54+N54+P54+R54+T54+V54+X54+Z54 -> 9649.7 | AD54: =SUMIF($C$5:$Z$5,$AD$5,C54:Z54) -> 25200 | AE54: =SUMIF($C$5:$Z$5,$AD$5,D54:AA54) -> 9649.7 | AF54: =AA54-AD54 -> 0 | AG54: =AB54-AE54 -> 0
A55: 住宿费 | C55: 2500 | D55: 23915.22 | E55: 2500 | F55: 292.92 | G55: 2500 | H55: 3187.95 | I55: 2500 | J55: 1616.55 | K55: 2500 | L55: 511 | M55: 2500 | N55: -14.87 | O55: 2500 | P55: 797.55 | Q55: 2500 | R55: 303.92 | S55: 2500 | T55: 0 | U55: 2500 | W55: 2500 | Y55: 2500 | Z55: 380.8 | AA55: =C55+E55+G55+I55+K55+M55+O55+Q55+S55+U55+W55+Y55 -> 30000 | AB55: =D55+F55+H55+J55+L55+N55+P55+R55+T55+V55+X55+Z55 -> 30991.04 | AD55: =SUMIF($C$5:$Z$5,$AD$5,C55:Z55) -> 30000 | AE55: =SUMIF($C$5:$Z$5,$AD$5,D55:AA55) -> 30991.04 | AF55: =AA55-AD55 -> 0 | AG55: =AB55-AE55 -> 0
A56: 餐补 | C56: 675 | D56: 26603 | E56: 675 | F56: 131 | G56: 675 | H56: 1148.4 | I56: 675 | J56: 505 | K56: 675 | L56: 0 | M56: 675 | N56: 0 | O56: 675 | P56: 284 | Q56: 675 | R56: 252 | S56: 675 | T56: 0 | U56: 675 | W56: 675 | Y56: 675 | Z56: 115 | AA56: =C56+E56+G56+I56+K56+M56+O56+Q56+S56+U56+W56+Y56 -> 8100 | AB56: =D56+F56+H56+J56+L56+N56+P56+R56+T56+V56+X56+Z56 -> 29038.4 | AD56: =SUMIF($C$5:$Z$5,$AD$5,C56:Z56) -> 8100 | AE56: =SUMIF($C$5:$Z$5,$AD$5,D56:AA56) -> 29038.4 | AF56: =AA56-AD56 -> 0 | AG56: =AB56-AE56 -> 0
A57: 交通补助 | D57: 0 | F57: 0 | H57: 0 | J57: 0 | L57: 0 | N57: 0 | P57: 0 | R57: 0 | T57: 0 | Z57: 0 | AA57: =C57+E57+G57+I57+K57+M57+O57+Q57+S57+U57+W57+Y57 -> 0 | AB57: =D57+F57+H57+J57+L57+N57+P57+R57+T57+V57+X57+Z57 -> 0 | AD57: =SUMIF($C$5:$Z$5,$AD$5,C57:Z57) -> 0 | AE57: =SUMIF($C$5:$Z$5,$AD$5,D57:AA57) -> 0 | AF57: =AA57-AD57 -> 0 | AG57: =AB57-AE57 -> 0
A58: 通讯补助 | D58: 0 | F58: 0 | H58: 0 | J58: 0 | L58: 0 | N58: 0 | P58: 0 | R58: 0 | T58: 0 | Z58: 0 | AA58: =C58+E58+G58+I58+K58+M58+O58+Q58+S58+U58+W58+Y58 -> 0 | AB58: =D58+F58+H58+J58+L58+N58+P58+R58+T58+V58+X58+Z58 -> 0 | AD58: =SUMIF($C$5:$Z$5,$AD$5,C58:Z58) -> 0 | AE58: =SUMIF($C$5:$Z$5,$AD$5,D58:AA58) -> 0 | AF58: =AA58-AD58 -> 0 | AG58: =AB58-AE58 -> 0
A59: 招待费 | C59: 2000 | D59: 3247.7 | E59: 2000 | F59: 1040 | G59: 2000 | H59: 1706 | I59: 2000 | J59: 1755.7 | K59: 2000 | L59: 0 | M59: 2000 | N59: 1442 | O59: 2000 | P59: 794.42 | Q59: 2000 | R59: 0 | S59: 2000 | T59: 0 | U59: 2000 | W59: 2000 | Y59: 2000 | Z59: 446 | AA59: =C59+E59+G59+I59+K59+M59+O59+Q59+S59+U59+W59+Y59 -> 24000 | AB59: =D59+F59+H59+J59+L59+N59+P59+R59+T59+V59+X59+Z59 -> 10431.82 | AD59: =SUMIF($C$5:$Z$5,$AD$5,C59:Z59) -> 24000 | AE59: =SUMIF($C$5:$Z$5,$AD$5,D59:AA59) -> 10431.82 | AF59: =AA59-AD59 -> 0 | AG59: =AB59-AE59 -> 0
A60: 通讯费 | D60: 0 | F60: 0 | H60: 0 | J60: 0 | L60: 0 | P60: 0 | R60: 0 | T60: 0 | Z60: 0 | AA60: =C60+E60+G60+I60+K60+M60+O60+Q60+S60+U60+W60+Y60 -> 0 | AB60: =D60+F60+H60+J60+L60+N60+P60+R60+T60+V60+X60+Z60 -> 0 | AD60: =SUMIF($C$5:$Z$5,$AD$5,C60:Z60) -> 0 | AE60: =SUMIF($C$5:$Z$5,$AD$5,D60:AA60) -> 0 | AF60: =AA60-AD60 -> 0 | AG60: =AB60-AE60 -> 0
A61: 网络费 | D61: 0 | F61: 0 | H61: 0 | J61: 0 | L61: 0 | P61: 0 | R61: 0 | T61: 0 | Z61: 0 | AA61: =C61+E61+G61+I61+K61+M61+O61+Q61+S61+U61+W61+Y61 -> 0 | AB61: =D61+F61+H61+J61+L61+N61+P61+R61+T61+V61+X61+Z61 -> 0 | AD61: =SUMIF($C$5:$Z$5,$AD$5,C61:Z61) -> 0 | AE61: =SUMIF($C$5:$Z$5,$AD$5,D61:AA61) -> 0 | AF61: =AA61-AD61 -> 0 | AG61: =AB61-AE61 -> 0
A62: 修理费 | D62: 0 | F62: 0 | H62: 0 | J62: 0 | L62: 0 | P62: 0 | R62: 0 | T62: 0 | Z62: 0 | AA62: =C62+E62+G62+I62+K62+M62+O62+Q62+S62+U62+W62+Y62 -> 0 | AB62: =D62+F62+H62+J62+L62+N62+P62+R62+T62+V62+X62+Z62 -> 0 | AD62: =SUMIF($C$5:$Z$5,$AD$5,C62:Z62) -> 0 | AE62: =SUMIF($C$5:$Z$5,$AD$5,D62:AA62) -> 0 | AF62: =AA62-AD62 -> 0 | AG62: =AB62-AE62 -> 0
A63: 车辆费 | D63: 0 | F63: 0 | H63: 0 | J63: 0 | L63: 0 | P63: 0 | R63: 0 | T63: 0 | Z63: 0 | AA63: =C63+E63+G63+I63+K63+M63+O63+Q63+S63+U63+W63+Y63 -> 0 | AB63: =D63+F63+H63+J63+L63+N63+P63+R63+T63+V63+X63+Z63 -> 0 | AD63: =SUMIF($C$5:$Z$5,$AD$5,C63:Z63) -> 0 | AE63: =SUMIF($C$5:$Z$5,$AD$5,D63:AA63) -> 0 | AF63: =AA63-AD63 -> 0 | AG63: =AB63-AE63 -> 0
A64: 租赁费 | H64: 0 | J64: 0 | L64: 0 | P64: 0 | R64: 0 | T64: 0 | Z64: 0 | AA64: =C64+E64+G64+I64+K64+M64+O64+Q64+S64+U64+W64+Y64 -> 0 | AB64: =D64+F64+H64+J64+L64+N64+P64+R64+T64+V64+X64+Z64 -> 0 | AD64: =SUMIF($C$5:$Z$5,$AD$5,C64:Z64) -> 0 | AE64: =SUMIF($C$5:$Z$5,$AD$5,D64:AA64) -> 0 | AF64: =AA64-AD64 -> 0 | AG64: =AB64-AE64 -> 0
A65: 能源费 | C65: =SUM(C66:C69) -> 0 | D65: =SUM(D66:D69) -> 0 | E65: =SUM(E66:E69) -> 0 | F65: =SUM(F66:F69) -> 0 | G65: =SUM(G66:G69) -> 0 | H65: =SUM(H66:H69) -> 0 | I65: =SUM(I66:I69) -> 0 | J65: =SUM(J66:J69) -> 0 | ... L65: =SUM(L66:L69) -> 0 | M65: 0 | N65: =SUM(N66:N69) -> 0 | O65: 0 | Q65: =SUM(Q66:Q69) -> 0 | U65: =SUM(U66:U69) -> 0 | V65: =SUM(V66:V69) -> 0 | W65: =SUM(W66:W69) -> 0 | X65: 0 | Y65: =SUM(Y66:Y69) -> 0 | Z65: =SUM(Z66:Z69) -> 0 | AA65: =C65+E65+G65+I65+K65+M65+O65+Q65+S65+U65+W65+Y65 -> 0 | AB65: =D65+F65+H65+J65+L65+N65+P65+R65+T65+V65+X65+Z65 -> 0 | AD65: =SUMIF($C$5:$Z$5,$AD$5,C65:Z65) -> 0 | AE65: =SUMIF($C$5:$Z$5,$AD$5,D65:AA65) -> 0 | AF65: =AA65-AD65 -> 0 | AG65: =AB65-AE65 -> 0
A66: 水费 | D66: 0 | F66: 0 | H66: 0 | J66: 0 | L66: 0 | N66: 0 | P66: 0 | R66: 0 | T66: 0 | X66: 0 | AA66: =C66+E66+G66+I66+K66+M66+O66+Q66+S66+U66+W66+Y66 -> 0 | AB66: =D66+F66+H66+J66+L66+N66+P66+R66+T66+V66+X66+Z66 -> 0 | AD66: =SUMIF($C$5:$Z$5,$AD$5,C66:Z66) -> 0 | AE66: =SUMIF($C$5:$Z$5,$AD$5,D66:AA66) -> 0 | AF66: =AA66-AD66 -> 0 | AG66: =AB66-AE66 -> 0
A67: 电费 | D67: 0 | F67: 0 | H67: 0 | J67: 0 | L67: 0 | N67: 0 | P67: 0 | R67: 0 | T67: 0 | X67: 0 | AA67: =C67+E67+G67+I67+K67+M67+O67+Q67+S67+U67+W67+Y67 -> 0 | AB67: =D67+F67+H67+J67+L67+N67+P67+R67+T67+V67+X67+Z67 -> 0 | AD67: =SUMIF($C$5:$Z$5,$AD$5,C67:Z67) -> 0 | AE67: =SUMIF($C$5:$Z$5,$AD$5,D67:AA67) -> 0 | AF67: =AA67-AD67 -> 0 | AG67: =AB67-AE67 -> 0
A68: 燃气费 | D68: 0 | F68: 0 | H68: 0 | J68: 0 | L68: 0 | N68: 0 | P68: 0 | R68: 0 | T68: 0 | X68: 0 | AA68: =C68+E68+G68+I68+K68+M68+O68+Q68+S68+U68+W68+Y68 -> 0 | AB68: =D68+F68+H68+J68+L68+N68+P68+R68+T68+V68+X68+Z68 -> 0 | AD68: =SUMIF($C$5:$Z$5,$AD$5,C68:Z68) -> 0 | AE68: =SUMIF($C$5:$Z$5,$AD$5,D68:AA68) -> 0 | AF68: =AA68-AD68 -> 0 | AG68: =AB68-AE68 -> 0
A69: 蒸汽费 | D69: 0 | F69: 0 | H69: 0 | J69: 0 | L69: 0 | N69: 0 | P69: 0 | R69: 0 | T69: 0 | X69: 0 | AA69: =C69+E69+G69+I69+K69+M69+O69+Q69+S69+U69+W69+Y69 -> 0 | AB69: =D69+F69+H69+J69+L69+N69+P69+R69+T69+V69+X69+Z69 -> 0 | AD69: =SUMIF($C$5:$Z$5,$AD$5,C69:Z69) -> 0 | AE69: =SUMIF($C$5:$Z$5,$AD$5,D69:AA69) -> 0 | AF69: =AA69-AD69 -> 0 | AG69: =AB69-AE69 -> 0
A70: 物业费 | D70: 0 | F70: 0 | H70: 0 | J70: 0 | L70: 0 | N70: 0 | P70: 0 | R70: 0 | T70: 0 | X70: 0 | AA70: =C70+E70+G70+I70+K70+M70+O70+Q70+S70+U70+W70+Y70 -> 0 | AB70: =D70+F70+H70+J70+L70+N70+P70+R70+T70+V70+X70+Z70 -> 0 | AD70: =SUMIF($C$5:$Z$5,$AD$5,C70:Z70) -> 0 | AE70: =SUMIF($C$5:$Z$5,$AD$5,D70:AA70) -> 0 | AF70: =AA70-AD70 -> 0 | AG70: =AB70-AE70 -> 0
A71: 劳动保护费 | C71: 0 | D71: 0 | E71: 0 | F71: 0 | G71: 300 | H71: 0 | I71: 0 | J71: 0 | K71: 0 | L71: 0 | M71: 0 | N71: 0 | O71: 0 | P71: 0 | Q71: 0 | R71: 0 | S71: 0 | T71: 0 | U71: 0 | W71: 0 | X71: 0 | AA71: =C71+E71+G71+I71+K71+M71+O71+Q71+S71+U71+W71+Y71 -> 300 | AB71: =D71+F71+H71+J71+L71+N71+P71+R71+T71+V71+X71+Z71 -> 0 | AD71: =SUMIF($C$5:$Z$5,$AD$5,C71:Z71) -> 300 | AE71: =SUMIF($C$5:$Z$5,$AD$5,D71:AA71) -> 0 | AF71: =AA71-AD71 -> 0 | AG71: =AB71-AE71 -> 0
A72: 顾问费 | D72: 0 | F72: 0 | H72: 0 | J72: 0 | L72: 0 | N72: 0 | P72: 0 | R72: 0 | T72: 0 | X72: 0 | AA72: =C72+E72+G72+I72+K72+M72+O72+Q72+S72+U72+W72+Y72 -> 0 | AB72: =D72+F72+H72+J72+L72+N72+P72+R72+T72+V72+X72+Z72 -> 0 | AD72: =SUMIF($C$5:$Z$5,$AD$5,C72:Z72) -> 0 | AE72: =SUMIF($C$5:$Z$5,$AD$5,D72:AA72) -> 0 | AF72: =AA72-AD72 -> 0 | AG72: =AB72-AE72 -> 0
A73: 快递费 | C73: 100 | D73: 143.87 | E73: 100 | F73: 63.55 | G73: 100 | H73: 97.54 | I73: 100 | J73: 462.26 | K73: 100 | L73: 30.19 | M73: 100 | N73: 79.05 | O73: 100 | P73: 15.28 | Q73: 100 | R73: 63.02 | S73: 100 | T73: 10 | U73: 100 | V73: 26.04 | W73: 100 | X73: 11.32 | Y73: 100 | AA73: =C73+E73+G73+I73+K73+M73+O73+Q73+S73+U73+W73+Y73 -> 1200 | AB73: =D73+F73+H73+J73+L73+N73+P73+R73+T73+V73+X73+Z73 -> 1002.12 | AD73: =SUMIF($C$5:$Z$5,$AD$5,C73:Z73) -> 1200 | AE73: =SUMIF($C$5:$Z$5,$AD$5,D73:AA73) -> 1002.12 | AF73: =AA73-AD73 -> 0 | AG73: =AB73-AE73 -> 0
A74: 诉讼费 | D74: 0 | F74: 0 | H74: 0 | J74: 0 | L74: 0 | N74: 0 | P74: 0 | R74: 0 | T74: 0 | X74: 0 | AA74: =C74+E74+G74+I74+K74+M74+O74+Q74+S74+U74+W74+Y74 -> 0 | AB74: =D74+F74+H74+J74+L74+N74+P74+R74+T74+V74+X74+Z74 -> 0 | AD74: =SUMIF($C$5:$Z$5,$AD$5,C74:Z74) -> 0 | AE74: =SUMIF($C$5:$Z$5,$AD$5,D74:AA74) -> 0 | AF74: =AA74-AD74 -> 0 | AG74: =AB74-AE74 -> 0
A75: 会员费 | D75: 0 | F75: 0 | H75: 0 | J75: 0 | L75: 0 | N75: 0 | P75: 0 | R75: 0 | T75: 0 | X75: 0 | AA75: =C75+E75+G75+I75+K75+M75+O75+Q75+S75+U75+W75+Y75 -> 0 | AB75: =D75+F75+H75+J75+L75+N75+P75+R75+T75+V75+X75+Z75 -> 0 | AD75: =SUMIF($C$5:$Z$5,$AD$5,C75:Z75) -> 0 | AE75: =SUMIF($C$5:$Z$5,$AD$5,D75:AA75) -> 0 | AF75: =AA75-AD75 -> 0 | AG75: =AB75-AE75 -> 0
A76: 广告宣传费 | D76: 0 | F76: 0 | H76: 0 | J76: 0 | L76: 0 | N76: 0 | P76: 0 | R76: 0 | T76: 0 | X76: 0 | AA76: =C76+E76+G76+I76+K76+M76+O76+Q76+S76+U76+W76+Y76 -> 0 | AB76: =D76+F76+H76+J76+L76+N76+P76+R76+T76+V76+X76+Z76 -> 0 | AD76: =SUMIF($C$5:$Z$5,$AD$5,C76:Z76) -> 0 | AE76: =SUMIF($C$5:$Z$5,$AD$5,D76:AA76) -> 0 | AF76: =AA76-AD76 -> 0 | AG76: =AB76-AE76 -> 0
A77: 会务费 | C77: 4500 | D77: 30000 | E77: 4500 | F77: 0 | G77: 4500 | H77: 0 | I77: 4500 | J77: 0 | K77: 4500 | L77: 0 | M77: 4500 | N77: 0 | O77: 4500 | P77: 0 | Q77: 4500 | R77: 0 | S77: 4500 | T77: 0 | U77: 4500 | W77: 4500 | X77: 0 | Y77: 4500 | AA77: =C77+E77+G77+I77+K77+M77+O77+Q77+S77+U77+W77+Y77 -> 54000 | AB77: =D77+F77+H77+J77+L77+N77+P77+R77+T77+V77+X77+Z77 -> 30000 | AD77: =SUMIF($C$5:$Z$5,$AD$5,C77:Z77) -> 54000 | AE77: =SUMIF($C$5:$Z$5,$AD$5,D77:AA77) -> 30000 | AF77: =AA77-AD77 -> 0 | AG77: =AB77-AE77 -> 0
A78: 装修费 | D78: 0 | F78: 0 | H78: 0 | J78: 0 | L78: 0 | N78: 0 | P78: 0 | R78: 0 | T78: 0 | X78: 0 | AA78: =C78+E78+G78+I78+K78+M78+O78+Q78+S78+U78+W78+Y78 -> 0 | AB78: =D78+F78+H78+J78+L78+N78+P78+R78+T78+V78+X78+Z78 -> 0 | AD78: =SUMIF($C$5:$Z$5,$AD$5,C78:Z78) -> 0 | AE78: =SUMIF($C$5:$Z$5,$AD$5,D78:AA78) -> 0 | AF78: =AA78-AD78 -> 0 | AG78: =AB78-AE78 -> 0
A79: 推广费 | D79: 0 | F79: 0 | H79: 0 | J79: 0 | L79: 0 | N79: 0 | P79: 0 | R79: 0 | T79: 0 | X79: 0 | AA79: =C79+E79+G79+I79+K79+M79+O79+Q79+S79+U79+W79+Y79 -> 0 | AB79: =D79+F79+H79+J79+L79+N79+P79+R79+T79+V79+X79+Z79 -> 0 | AD79: =SUMIF($C$5:$Z$5,$AD$5,C79:Z79) -> 0 | AE79: =SUMIF($C$5:$Z$5,$AD$5,D79:AA79) -> 0 | AF79: =AA79-AD79 -> 0 | AG79: =AB79-AE79 -> 0
A80: 展会费 | D80: 0 | F80: 0 | H80: 672.6 | J80: 0 | L80: 0 | N80: 0 | P80: 0 | R80: 0 | T80: 0 | X80: 0 | AA80: =C80+E80+G80+I80+K80+M80+O80+Q80+S80+U80+W80+Y80 -> 0 | AB80: =D80+F80+H80+J80+L80+N80+P80+R80+T80+V80+X80+Z80 -> 672.6 | AD80: =SUMIF($C$5:$Z$5,$AD$5,C80:Z80) -> 0 | AE80: =SUMIF($C$5:$Z$5,$AD$5,D80:AA80) -> 672.6 | AF80: =AA80-AD80 -> 0 | AG80: =AB80-AE80 -> 0
A81: 设计费 | D81: 0 | F81: 0 | H81: 0 | J81: 0 | L81: 0 | N81: 0 | P81: 0 | R81: 0 | T81: 0 | X81: 0 | AA81: =C81+E81+G81+I81+K81+M81+O81+Q81+S81+U81+W81+Y81 -> 0 | AB81: =D81+F81+H81+J81+L81+N81+P81+R81+T81+V81+X81+Z81 -> 0 | AD81: =SUMIF($C$5:$Z$5,$AD$5,C81:Z81) -> 0 | AE81: =SUMIF($C$5:$Z$5,$AD$5,D81:AA81) -> 0 | AF81: =AA81-AD81 -> 0 | AG81: =AB81-AE81 -> 0
A82: 折旧费 | D82: 0 | F82: 0 | H82: 0 | J82: 0 | L82: 0 | N82: 0 | P82: 0 | R82: 0 | T82: 0 | X82: 0 | AA82: =C82+E82+G82+I82+K82+M82+O82+Q82+S82+U82+W82+Y82 -> 0 | AB82: =D82+F82+H82+J82+L82+N82+P82+R82+T82+V82+X82+Z82 -> 0 | AD82: =SUMIF($C$5:$Z$5,$AD$5,C82:Z82) -> 0 | AE82: =SUMIF($C$5:$Z$5,$AD$5,D82:AA82) -> 0 | AF82: =AA82-AD82 -> 0 | AG82: =AB82-AE82 -> 0
A83: 认证费 | D83: 0 | F83: 0 | H83: 0 | J83: 0 | L83: 0 | N83: 0 | P83: 0 | R83: 0 | T83: 0 | X83: 0 | AA83: =C83+E83+G83+I83+K83+M83+O83+Q83+S83+U83+W83+Y83 -> 0 | AB83: =D83+F83+H83+J83+L83+N83+P83+R83+T83+V83+X83+Z83 -> 0 | AD83: =SUMIF($C$5:$Z$5,$AD$5,C83:Z83) -> 0 | AE83: =SUMIF($C$5:$Z$5,$AD$5,D83:AA83) -> 0 | AF83: =AA83-AD83 -> 0 | AG83: =AB83-AE83 -> 0
A84: 样品费 | C84: 500 | D84: 974.65 | E84: 500 | F84: 185.47 | G84: 500 | H84: 47.82 | I84: 500 | J84: 383.14 | K84: 500 | L84: 104.18 | M84: 500 | N84: 179.47 | O84: 500 | P84: 19.07 | Q84: 500 | R84: 228.24 | S84: 500 | T84: 76.81 | U84: 500 | V84: 65.81 | W84: 500 | X84: 117.6 | Y84: 500 | AA84: =C84+E84+G84+I84+K84+M84+O84+Q84+S84+U84+W84+Y84 -> 6000 | AB84: =D84+F84+H84+J84+L84+N84+P84+R84+T84+V84+X84+Z84 -> 2382.26 | AD84: =SUMIF($C$5:$Z$5,$AD$5,C84:Z84) -> 6000 | AE84: =SUMIF($C$5:$Z$5,$AD$5,D84:AA84) -> 2382.26 | AF84: =AA84-AD84 -> 0 | AG84: =AB84-AE84 -> 0
A85: 劳务费 | D85: 0 | E85: 0 | F85: 0 | H85: 0 | J85: 0 | L85: 0 | N85: 0 | O85: 0 | P85: 0 | Q85: 0 | R85: 0 | S85: 0 | T85: 0 | U85: 0 | W85: 0 | X85: 0 | AA85: =C85+E85+G85+I85+K85+M85+O85+Q85+S85+U85+W85+Y85 -> 0 | AB85: =D85+F85+H85+J85+L85+N85+P85+R85+T85+V85+X85+Z85 -> 0 | AD85: =SUMIF($C$5:$Z$5,$AD$5,C85:Z85) -> 0 | AE85: =SUMIF($C$5:$Z$5,$AD$5,D85:AA85) -> 0 | AF85: =AA85-AD85 -> 0 | AG85: =AB85-AE85 -> 0
A86: 销售佣金 | D86: 0 | F86: 0 | G86: 0 | H86: 0 | J86: 0 | L86: 0 | N86: 0 | P86: 0 | R86: 0 | S86: 0 | T86: 0 | X86: 0 | AA86: =C86+E86+G86+I86+K86+M86+O86+Q86+S86+U86+W86+Y86 -> 0 | AB86: =D86+F86+H86+J86+L86+N86+P86+R86+T86+V86+X86+Z86 -> 0 | AD86: =SUMIF($C$5:$Z$5,$AD$5,C86:Z86) -> 0 | AE86: =SUMIF($C$5:$Z$5,$AD$5,D86:AA86) -> 0 | AF86: =AA86-AD86 -> 0 | AG86: =AB86-AE86 -> 0
A87: 检测费 | D87: 0 | F87: 0 | H87: 0 | J87: 304.72 | L87: 0 | N87: 0 | P87: 0 | R87: 0 | T87: 0 | X87: 0 | AA87: =C87+E87+G87+I87+K87+M87+O87+Q87+S87+U87+W87+Y87 -> 0 | AB87: =D87+F87+H87+J87+L87+N87+P87+R87+T87+V87+X87+Z87 -> 304.72 | AD87: =SUMIF($C$5:$Z$5,$AD$5,C87:Z87) -> 0 | AE87: =SUMIF($C$5:$Z$5,$AD$5,D87:AA87) -> 304.72 | AF87: =AA87-AD87 -> 0 | AG87: =AB87-AE87 -> 0
A88: 质量赔偿 | D88: 0 | F88: 0 | H88: 0 | J88: 0 | L88: 0 | N88: 0 | P88: 0 | R88: 0 | T88: 0 | X88: 0 | AA88: =C88+E88+G88+I88+K88+M88+O88+Q88+S88+U88+W88+Y88 -> 0 | AB88: =D88+F88+H88+J88+L88+N88+P88+R88+T88+V88+X88+Z88 -> 0 | AD88: =SUMIF($C$5:$Z$5,$AD$5,C88:Z88) -> 0 | AE88: =SUMIF($C$5:$Z$5,$AD$5,D88:AA88) -> 0 | AF88: =AA88-AD88 -> 0 | AG88: =AB88-AE88 -> 0
A89: 保险费 | D89: 0 | F89: 0 | H89: 0 | J89: 0 | L89: 0 | N89: 0 | P89: 0 | R89: 0 | T89: 0 | X89: 0 | AA89: =C89+E89+G89+I89+K89+M89+O89+Q89+S89+U89+W89+Y89 -> 0 | AB89: =D89+F89+H89+J89+L89+N89+P89+R89+T89+V89+X89+Z89 -> 0 | AD89: =SUMIF($C$5:$Z$5,$AD$5,C89:Z89) -> 0 | AE89: =SUMIF($C$5:$Z$5,$AD$5,D89:AA89) -> 0 | AF89: =AA89-AD89 -> 0 | AG89: =AB89-AE89 -> 0
A90: 清洁费 | D90: 0 | F90: 0 | H90: 0 | J90: 0 | L90: 0 | N90: 0 | P90: 0 | R90: 0 | T90: 0 | X90: 0 | AA90: =C90+E90+G90+I90+K90+M90+O90+Q90+S90+U90+W90+Y90 -> 0 | AB90: =D90+F90+H90+J90+L90+N90+P90+R90+T90+V90+X90+Z90 -> 0 | AD90: =SUMIF($C$5:$Z$5,$AD$5,C90:Z90) -> 0 | AE90: =SUMIF($C$5:$Z$5,$AD$5,D90:AA90) -> 0 | AF90: =AA90-AD90 -> 0 | AG90: =AB90-AE90 -> 0
A91: 低值易耗品 | D91: 0 | F91: 0 | H91: 0 | J91: -6670 | L91: 0 | N91: 0 | P91: 0 | R91: 0 | T91: 0 | X91: 0 | AA91: =C91+E91+G91+I91+K91+M91+O91+Q91+S91+U91+W91+Y91 -> 0 | AB91: =D91+F91+H91+J91+L91+N91+P91+R91+T91+V91+X91+Z91 -> -6670 | AD91: =SUMIF($C$5:$Z$5,$AD$5,C91:Z91) -> 0 | AE91: =SUMIF($C$5:$Z$5,$AD$5,D91:AA91) -> -6670 | AF91: =AA91-AD91 -> 0 | AG91: =AB91-AE91 -> 0
A92: 物料消耗 | D92: 0 | F92: 0 | H92: 0 | J92: 0 | L92: 18.41 | N92: 0 | P92: 0 | R92: 16.81 | T92: 0 | X92: 0 | AA92: =C92+E92+G92+I92+K92+M92+O92+Q92+S92+U92+W92+Y92 -> 0 | AB92: =D92+F92+H92+J92+L92+N92+P92+R92+T92+V92+X92+Z92 -> 35.22 | AD92: =SUMIF($C$5:$Z$5,$AD$5,C92:Z92) -> 0 | AE92: =SUMIF($C$5:$Z$5,$AD$5,D92:AA92) -> 35.22 | AF92: =AA92-AD92 -> 0 | AG92: =AB92-AE92 -> 0
A93: 盘盈盘亏 | D93: 0 | F93: 0 | H93: 0 | J93: 0 | L93: 0 | N93: 0 | P93: 0 | R93: 0 | T93: 0 | X93: 0 | AA93: =C93+E93+G93+I93+K93+M93+O93+Q93+S93+U93+W93+Y93 -> 0 | AB93: =D93+F93+H93+J93+L93+N93+P93+R93+T93+V93+X93+Z93 -> 0 | AD93: =SUMIF($C$5:$Z$5,$AD$5,C93:Z93) -> 0 | AE93: =SUMIF($C$5:$Z$5,$AD$5,D93:AA93) -> 0 | AF93: =AA93-AD93 -> 0 | AG93: =AB93-AE93 -> 0
A94: 平台服务费 | D94: 990.1 | F94: 990.1 | H94: 990.1 | J94: 990.1 | L94: 990.1 | N94: 990.1 | P94: 990.1 | R94: 990.1 | T94: 990.09 | X94: 0 | AA94: =C94+E94+G94+I94+K94+M94+O94+Q94+S94+U94+W94+Y94 -> 0 | AB94: =D94+F94+H94+J94+L94+N94+P94+R94+T94+V94+X94+Z94 -> 8910.89 | AD94: =SUMIF($C$5:$Z$5,$AD$5,C94:Z94) -> 0 | AE94: =SUMIF($C$5:$Z$5,$AD$5,D94:AA94) -> 8910.89 | AF94: =AA94-AD94 -> 0 | AG94: =AB94-AE94 -> 0
A95: 无形资产摊销 | D95: 0 | F95: 0 | H95: 0 | J95: 0 | L95: 0 | N95: 0 | P95: 0 | R95: 0 | T95: 0 | X95: 0 | AA95: =C95+E95+G95+I95+K95+M95+O95+Q95+S95+U95+W95+Y95 -> 0 | AB95: =D95+F95+H95+J95+L95+N95+P95+R95+T95+V95+X95+Z95 -> 0 | AD95: =SUMIF($C$5:$Z$5,$AD$5,C95:Z95) -> 0 | AE95: =SUMIF($C$5:$Z$5,$AD$5,D95:AA95) -> 0 | AF95: =AA95-AD95 -> 0 | AG95: =AB95-AE95 -> 0
A96: 研发材料 | D96: 0 | F96: 0 | H96: 0 | J96: 0 | L96: 0 | N96: 0 | P96: 0 | R96: 0 | T96: 0 | X96: 0 | AA96: =C96+E96+G96+I96+K96+M96+O96+Q96+S96+U96+W96+Y96 -> 0 | AB96: =D96+F96+H96+J96+L96+N96+P96+R96+T96+V96+X96+Z96 -> 0 | AD96: =SUMIF($C$5:$Z$5,$AD$5,C96:Z96) -> 0 | AE96: =SUMIF($C$5:$Z$5,$AD$5,D96:AA96) -> 0 | AF96: =AA96-AD96 -> 0 | AG96: =AB96-AE96 -> 0
A97: 项目名称 | D97: 0 | F97: 0 | H97: 0 | J97: 0 | L97: 0 | N97: 0 | P97: 0 | R97: 0 | T97: 0 | X97: 0 | AA97: =C97+E97+G97+I97+K97+M97+O97+Q97+S97+U97+W97+Y97 -> 0 | AB97: =D97+F97+H97+J97+L97+N97+P97+R97+T97+V97+X97+Z97 -> 0 | AD97: =SUMIF($C$5:$Z$5,$AD$5,C97:Z97) -> 0 | AE97: =SUMIF($C$5:$Z$5,$AD$5,D97:AA97) -> 0 | AF97: =AA97-AD97 -> 0 | AG97: =AB97-AE97 -> 0
A98: 研发费 | D98: 0 | F98: 0 | H98: 0 | J98: 0 | L98: 0 | N98: 0 | P98: 0 | R98: 0 | T98: 0 | X98: 0 | AA98: =C98+E98+G98+I98+K98+M98+O98+Q98+S98+U98+W98+Y98 -> 0 | AB98: =D98+F98+H98+J98+L98+N98+P98+R98+T98+V98+X98+Z98 -> 0 | AD98: =SUMIF($C$5:$Z$5,$AD$5,C98:Z98) -> 0 | AE98: =SUMIF($C$5:$Z$5,$AD$5,D98:AA98) -> 0 | AF98: =AA98-AD98 -> 0 | AG98: =AB98-AE98 -> 0
A99: 残保金 | D99: 0 | F99: 0 | H99: 0 | J99: 0 | L99: 0 | P99: 0 | R99: 0 | T99: 0 | X99: 0 | AA99: =C99+E99+G99+I99+K99+M99+O99+Q99+S99+U99+W99+Y99 -> 0 | AB99: =D99+F99+H99+J99+L99+N99+P99+R99+T99+V99+X99+Z99 -> 0 | AD99: =SUMIF($C$5:$Z$5,$AD$5,C99:Z99) -> 0 | AE99: =SUMIF($C$5:$Z$5,$AD$5,D99:AA99) -> 0 | AF99: =AA99-AD99 -> 0 | AG99: =AB99-AE99 -> 0
A100: 环保费 | D100: 0 | F100: 0 | H100: 0 | J100: 0 | L100: 0 | P100: 0 | R100: 0 | T100: 0 | X100: 0 | AA100: =C100+E100+G100+I100+K100+M100+O100+Q100+S100+U100+W100+Y100 -> 0 | AB100: =D100+F100+H100+J100+L100+N100+P100+R100+T100+V100+X100+Z100 -> 0 | AD100: =SUMIF($C$5:$Z$5,$AD$5,C100:Z100) -> 0 | AE100: =SUMIF($C$5:$Z$5,$AD$5,D100:AA100) -> 0 | AF100: =AA100-AD100 -> 0 | AG100: =AB100-AE100 -> 0
...

Sheet 2025年江苏分部利润表
A1: 江苏分部利润表
A2: 46021 | AB2: 会企01表
A3: 编制单位：江苏美鑫食品科技有限公司 | AB3: 单位：元
A4: 项 目 | B4: 行次 | C4: 45658 | E4: 45689 | G4: 45717 | I4: 45748 | K4: 45778 | M4: 45809 | O4: 45839 | Q4: 45870 | S4: 45901 | U4: 45931 | W4: 45962 | Y4: 45992 | AA4: 2025年合计 | AD4: 2025年合计逆向验证 | AF4: 检验结果
C5: 预算数 | D5: 本月实际 | E5: 预算数 | F5: 本月实际 | G5: 预算数 | H5: 本月实际 | I5: 预算数 | J5: 本月实际 | K5: 预算数 | L5: 本月实际 | M5: 预算数 | N5: 本月实际 | O5: 预算数 | P5: 本月实际 | Q5: 预算数 | R5: 本月实际 | S5: 预算数 | T5: 本月实际 | U5: 预算数 | V5: 本月实际 | W5: 预算数 | X5: 本月实际 | Y5: 预算数 | Z5: 本月实际 | AA5: 预算数 | AB5: 本年实际 | AD5: 预算数 | AE5: 本月实际 | AF5: 预算数 | AG5: 本月实际
A6: 一、营业收入 | B6: 1 | C6: =SUM(C7:C13,C15,-C14) -> 685500 | D6: =SUM(D7:D13,D15,-D14) -> 2304694.7 | E6: =SUM(E7:E13,E15,-E14) -> 816600 | F6: =SUM(F7:F13,F15,-F14) -> 1666193.9 | G6: =SUM(G7:G13,G15,-G14) -> 1474500 | H6: =SUM(H7:H13,H15,-H14) -> 1529599.9 | I6: =SUM(I7:I13,I15,-I14) -> 1730500 | J6: =SUM(J7:J13,J15,-J14) -> 2841384.8 | ... Z6: =SUM(Z7:Z13,Z15,-Z14) -> 3611166.2 | AA6: =C6+E6+G6+I6+K6+M6+O6+Q6+S6+U6+W6+Y6 -> 22214275 | AB6: =D6+F6+H6+J6+L6+N6+P6+R6+T6+V6+X6+Z6 -> 28400631 | AD6: =SUMIF($C$5:$Z$5,$AD$5,C6:Z6) -> 22214275 | AE6: =SUMIF($C$5:$Z$5,$AD$5,D6:AA6) -> 28400631 | AF6: =AA6-AD6 -> 0 | AG6: =AB6-AE6 -> 0
A7: 中式汤底 | C7: 0 | D7: 800959.01 | E7: 0 | F7: 559635.8 | G7: 0 | H7: 823085.9 | I7: 0 | J7: 1403217.1 | K7: 0 | L7: 928558.92 | M7: 0 | N7: 934831.56 | O7: 0 | P7: 934735.14 | Q7: 0 | R7: 736876.09 | S7: 0 | T7: 1052783.2 | U7: 0 | V7: 802792.29 | W7: 0 | X7: 808087.32 | Y7: 0 | Z7: 1014033.7 | AA7: =C7+E7+G7+I7+K7+M7+O7+Q7+S7+U7+W7+Y7 -> 0 | AB7: =D7+F7+H7+J7+L7+N7+P7+R7+T7+V7+X7+Z7 -> 10799596 | AC7: 1.08 | AD7: =SUMIF($C$5:$Z$5,$AD$5,C7:Z7) -> 0 | AE7: =SUMIF($C$5:$Z$5,$AD$5,D7:AA7) -> 10799596 | AF7: =AA7-AD7 -> 0 | AG7: =AB7-AE7 -> 0
A8: 酱料 | C8: 0 | D8: 695314.17 | E8: 0 | F8: 501857.43 | G8: 0 | H8: 464704.45 | I8: 0 | J8: 553023.35 | K8: 0 | L8: 426913.11 | M8: 0 | N8: 697937.44 | O8: 0 | P8: 510037.48 | Q8: 0 | R8: 435995.89 | S8: 0 | T8: 947977.93 | U8: 0 | V8: 391681.01 | W8: 0 | X8: 481054.01 | Y8: 0 | Z8: 1109896.8 | AA8: =C8+E8+G8+I8+K8+M8+O8+Q8+S8+U8+W8+Y8 -> 0 | AB8: =D8+F8+H8+J8+L8+N8+P8+R8+T8+V8+X8+Z8 -> 7216393.1 | AD8: =SUMIF($C$5:$Z$5,$AD$5,C8:Z8) -> 0 | AE8: =SUMIF($C$5:$Z$5,$AD$5,D8:AA8) -> 7216393.1 | AF8: =AA8-AD8 -> 0 | AG8: =AB8-AE8 -> 0
A9: 川味底料 | C9: 0 | D9: 695990.4 | E9: 0 | F9: 512165.49 | G9: 0 | H9: 116777.03 | I9: 0 | J9: 753915.49 | K9: 0 | L9: 613035.01 | M9: 0 | N9: 820808.34 | O9: 0 | P9: 785298.14 | Q9: 0 | R9: 686235.93 | S9: 0 | T9: 1038300.8 | U9: 0 | V9: 689867.13 | W9: 0 | X9: 749511.31 | Y9: 0 | Z9: 1336639.1 | AA9: =C9+E9+G9+I9+K9+M9+O9+Q9+S9+U9+W9+Y9 -> 0 | AB9: =D9+F9+H9+J9+L9+N9+P9+R9+T9+V9+X9+Z9 -> 8798544.2 | AD9: =SUMIF($C$5:$Z$5,$AD$5,C9:Z9) -> 0 | AE9: =SUMIF($C$5:$Z$5,$AD$5,D9:AA9) -> 8798544.2 | AF9: =AA9-AD9 -> 0 | AG9: =AB9-AE9 -> 0
A10: 调味汁 | C10: 0 | D10: 54132.862 | E10: 0 | F10: 69369.253 | G10: 0 | H10: 91492.232 | I10: 0 | J10: 107190.85 | K10: 0 | L10: 111737.47 | M10: 0 | N10: 132827.86 | O10: 0 | P10: 119773.72 | Q10: 0 | R10: 154881.74 | S10: 0 | T10: 111613.7 | U10: 0 | V10: 100357.61 | W10: 0 | X10: 104377.3 | Y10: 0 | Z10: 106275.62 | AA10: =C10+E10+G10+I10+K10+M10+O10+Q10+S10+U10+W10+Y10 -> 0 | AB10: =D10+F10+H10+J10+L10+N10+P10+R10+T10+V10+X10+Z10 -> 1264030.2 | AD10: =SUMIF($C$5:$Z$5,$AD$5,C10:Z10) -> 0 | AE10: =SUMIF($C$5:$Z$5,$AD$5,D10:AA10) -> 1264030.2 | AF10: =AA10-AD10 -> 0 | AG10: =AB10-AE10 -> 0
A11: 复合调味粉 | C11: 0 | D11: 34287.7 | E11: 0 | F11: 7708.4244 | G11: 0 | H11: 31542.988 | I11: 0 | J11: 53831.855 | K11: 0 | L11: 15210.418 | M11: 0 | N11: 44730.695 | O11: 0 | P11: 34762.252 | Q11: 0 | R11: 43747.398 | S11: 0 | T11: 54487.35 | U11: 0 | V11: 16231.633 | W11: 0 | X11: 40719.262 | Y11: 0 | Z11: 48218.771 | AA11: =C11+E11+G11+I11+K11+M11+O11+Q11+S11+U11+W11+Y11 -> 0 | AB11: =D11+F11+H11+J11+L11+N11+P11+R11+T11+V11+X11+Z11 -> 425478.74 | AD11: =SUMIF($C$5:$Z$5,$AD$5,C11:Z11) -> 0 | AE11: =SUMIF($C$5:$Z$5,$AD$5,D11:AA11) -> 425478.74 | AF11: =AA11-AD11 -> 0 | AG11: =AB11-AE11 -> 0
A12: 团餐 | C12: 0 | D12: 2568.0996 | E12: 0 | F12: 15457.478 | G12: 0 | H12: 692.9064 | I12: 0 | J12: 764.5968 | K12: 0 | L12: 1146.906 | M12: 0 | N12: 2432.4084 | O12: 0 | P12: 2246.0112 | Q12: 0 | R12: 0 | S12: 0 | T12: 0 | U12: 0 | V12: 716.8176 | W12: 0 | X12: 544.7736 | Y12: 0 | Z12: 7373.3436 | AA12: =C12+E12+G12+I12+K12+M12+O12+Q12+S12+U12+W12+Y12 -> 0 | AB12: =D12+F12+H12+J12+L12+N12+P12+R12+T12+V12+X12+Z12 -> 33943.342 | AD12: =SUMIF($C$5:$Z$5,$AD$5,C12:Z12) -> 0 | AE12: =SUMIF($C$5:$Z$5,$AD$5,D12:AA12) -> 33943.342 | AF12: =AA12-AD12 -> 0 | AG12: =AB12-AE12 -> 0
A13: 预制菜 | C13: 0 | D13: 21442.493 | E13: 0 | F13: 0 | G13: 0 | H13: 1304.4024 | I13: 0 | J13: 3114.2124 | K13: 0 | L13: 0 | M13: 0 | N13: 0 | O13: 0 | P13: 0 | Q13: 0 | R13: 45592.632 | S13: 0 | T13: 0 | U13: 0 | V13: 0 | W13: 0 | X13: 0 | Y13: 0 | Z13: 0 | AA13: =C13+E13+G13+I13+K13+M13+O13+Q13+S13+U13+W13+Y13 -> 0 | AB13: =D13+F13+H13+J13+L13+N13+P13+R13+T13+V13+X13+Z13 -> 71453.74 | AD13: =SUMIF($C$5:$Z$5,$AD$5,C13:Z13) -> 0 | AE13: =SUMIF($C$5:$Z$5,$AD$5,D13:AA13) -> 71453.74 | AF13: =AA13-AD13 -> 0 | AG13: =AB13-AE13 -> 0
A14: 返利 | J14: 33672.66 | L14: 25515.31 | N14: 27491.15 | O14: 3750 | P14: 43515.04 | Q14: 65409.28 | R14: 18647.15 | S14: 116015.72 | T14: 24663.72 | U14: 24725 | V14: 10222.19 | W14: 30600 | X14: 19119.65 | Y14: 45225 | Z14: 11271.1 | AA14: =C14+E14+G14+I14+K14+M14+O14+Q14+S14+U14+W14+Y14 -> 285725 | AB14: =D14+F14+H14+J14+L14+N14+P14+R14+T14+V14+X14+Z14 -> 214117.97 | AD14: =SUMIF($C$5:$Z$5,$AD$5,C14:Z14) -> 285725 | AE14: =SUMIF($C$5:$Z$5,$AD$5,D14:AA14) -> 214117.97 | AF14: =AA14-AD14 -> 0 | AG14: =AB14-AE14 -> 0
A15: 其他 | C15: 685500 | E15: 816600 | G15: 1474500 | I15: 1730500 | K15: 1505500 | M15: 1836000 | O15: 1952000 | Q15: 2009500 | R15: 5309.76 | S15: 2788300 | U15: 1801000 | W15: 2074100 | Y15: 3826500 | AA15: =C15+E15+G15+I15+K15+M15+O15+Q15+S15+U15+W15+Y15 -> 22500000 | AB15: =D15+F15+H15+J15+L15+N15+P15+R15+T15+V15+X15+Z15 -> 5309.76 | AD15: =SUMIF($C$5:$Z$5,$AD$5,C15:Z15) -> 22500000 | AE15: =SUMIF($C$5:$Z$5,$AD$5,D15:AA15) -> 5309.76 | AF15: =AA15-AD15 -> 0 | AG15: =AB15-AE15 -> 0
A16: 减：营业成本 | B16: 2 | C16: =SUM(C17:C25) -> 575284.07 | D16: =SUM(D17:D25) -> 1757570.1 | E16: =SUM(E17:E25) -> 680866.23 | F16: =SUM(F17:F25) -> 1319900.3 | G16: =SUM(G17:G25) -> 1223138 | H16: =SUM(H17:H25) -> 1175283.2 | I16: =SUM(I17:I25) -> 1432838.3 | J16: =SUM(J17:J25) -> 2308454.1 | ... Z16: =SUM(Z17:Z25) -> 2824682 | AA16: =C16+E16+G16+I16+K16+M16+O16+Q16+S16+U16+W16+Y16 -> 18078492 | AB16: =D16+F16+H16+J16+L16+N16+P16+R16+T16+V16+X16+Z16 -> 22545224 | AD16: =SUMIF($C$5:$Z$5,$AD$5,C16:Z16) -> 18078492 | AE16: =SUMIF($C$5:$Z$5,$AD$5,D16:AA16) -> 22545224 | AF16: =AA16-AD16 -> 0 | AG16: =AB16-AE16 -> 0
A17: 中式汤底 | C17: 0 | D17: 551543.48 | E17: 0 | F17: 416060.23 | G17: 0 | H17: 625749.66 | I17: 0 | J17: 1070676.4 | K17: 0 | L17: 696346.84 | M17: 0 | N17: 690721.73 | O17: 0 | P17: 701346.43 | Q17: 0 | R17: 524549.84 | S17: 0 | T17: 743015.57 | U17: 0 | V17: 580157.3 | W17: 0 | X17: 571421.84 | Y17: 0 | Z17: 713509.87 | AA17: =C17+E17+G17+I17+K17+M17+O17+Q17+S17+U17+W17+Y17 -> 0 | AB17: =D17+F17+H17+J17+L17+N17+P17+R17+T17+V17+X17+Z17 -> 7885099.2 | AC17: 1.04 | AD17: =SUMIF($C$5:$Z$5,$AD$5,C17:Z17) -> 0 | AE17: =SUMIF($C$5:$Z$5,$AD$5,D17:AA17) -> 7885099.2 | AF17: =AA17-AD17 -> 0 | AG17: =AB17-AE17 -> 0
A18: 酱料 | C18: 0 | D18: 534518.37 | E18: 0 | F18: 391183.62 | G18: 0 | H18: 379821.36 | I18: 0 | J18: 424963.17 | K18: 0 | L18: 336048.3 | M18: 0 | N18: 556336.84 | O18: 0 | P18: 385622.65 | Q18: 0 | R18: 320077.6 | S18: 0 | T18: 733699.65 | U18: 0 | V18: 293899.98 | W18: 0 | X18: 360267.62 | Y18: 0 | Z18: 843332.85 | AA18: =C18+E18+G18+I18+K18+M18+O18+Q18+S18+U18+W18+Y18 -> 0 | AB18: =D18+F18+H18+J18+L18+N18+P18+R18+T18+V18+X18+Z18 -> 5559772 | AD18: =SUMIF($C$5:$Z$5,$AD$5,C18:Z18) -> 0 | AE18: =SUMIF($C$5:$Z$5,$AD$5,D18:AA18) -> 5559772 | AF18: =AA18-AD18 -> 0 | AG18: =AB18-AE18 -> 0
A19: 川味底料 | C19: 0 | D19: 558409.26 | E19: 0 | F19: 414193.93 | G19: 0 | H19: 45234.738 | I19: 0 | J19: 640302.08 | K19: 0 | L19: 511377.1 | M19: 0 | N19: 679417.53 | O19: 0 | P19: 661449.27 | Q19: 0 | R19: 566733.87 | S19: 0 | T19: 827357.91 | U19: 0 | V19: 579285.5 | W19: 0 | X19: 622265.35 | Y19: 0 | Z19: 1100569.3 | AA19: =C19+E19+G19+I19+K19+M19+O19+Q19+S19+U19+W19+Y19 -> 0 | AB19: =D19+F19+H19+J19+L19+N19+P19+R19+T19+V19+X19+Z19 -> 7206595.8 | AD19: =SUMIF($C$5:$Z$5,$AD$5,C19:Z19) -> 0 | AE19: =SUMIF($C$5:$Z$5,$AD$5,D19:AA19) -> 7206595.8 | AF19: =AA19-AD19 -> 0 | AG19: =AB19-AE19 -> 0
A20: 调味汁 | C20: 0 | D20: 39028.142 | E20: 0 | F20: 53523.132 | G20: 0 | H20: 70943.007 | I20: 0 | J20: 82080.762 | K20: 0 | L20: 83000.237 | M20: 0 | N20: 97217.151 | O20: 0 | P20: 92227.689 | Q20: 0 | R20: 107714.91 | S20: 0 | T20: 80885.324 | U20: 0 | V20: 74632.646 | W20: 0 | X20: 73934.162 | Y20: 0 | Z20: 72433.286 | AA20: =C20+E20+G20+I20+K20+M20+O20+Q20+S20+U20+W20+Y20 -> 0 | AB20: =D20+F20+H20+J20+L20+N20+P20+R20+T20+V20+X20+Z20 -> 927620.45 | AD20: =SUMIF($C$5:$Z$5,$AD$5,C20:Z20) -> 0 | AE20: =SUMIF($C$5:$Z$5,$AD$5,D20:AA20) -> 927620.45 | AF20: =AA20-AD20 -> 0 | AG20: =AB20-AE20 -> 0
A21: 复合调味粉 | C21: 0 | D21: 21963.76 | E21: 0 | F21: 5607.8048 | G21: 0 | H21: 21502.988 | I21: 0 | J21: 37598.018 | K21: 0 | L21: 10185.874 | M21: 0 | N21: 33523.641 | O21: 0 | P21: 23111.026 | Q21: 0 | R21: 31992.802 | S21: 0 | T21: 36382.07 | U21: 0 | V21: 10864.121 | W21: 0 | X21: 26846.175 | Y21: 0 | Z21: 34051.607 | AA21: =C21+E21+G21+I21+K21+M21+O21+Q21+S21+U21+W21+Y21 -> 0 | AB21: =D21+F21+H21+J21+L21+N21+P21+R21+T21+V21+X21+Z21 -> 293629.89 | AD21: =SUMIF($C$5:$Z$5,$AD$5,C21:Z21) -> 0 | AE21: =SUMIF($C$5:$Z$5,$AD$5,D21:AA21) -> 293629.89 | AF21: =AA21-AD21 -> 0 | AG21: =AB21-AE21 -> 0
A22: 团餐 | C22: 0 | D22: 1408.1912 | E22: 0 | F22: 10499.871 | G22: 0 | H22: 379.444 | I22: 0 | J22: 424.5072 | K22: 0 | L22: 638.4144 | M22: 0 | N22: 1274.5304 | O22: 0 | P22: 1232.0672 | Q22: 0 | R22: 0 | S22: 0 | T22: 0 | U22: 0 | V22: 380.8688 | W22: 0 | X22: 232.7728 | Y22: 0 | Z22: 4722.2864 | AA22: =C22+E22+G22+I22+K22+M22+O22+Q22+S22+U22+W22+Y22 -> 0 | AB22: =D22+F22+H22+J22+L22+N22+P22+R22+T22+V22+X22+Z22 -> 21192.954 | AD22: =SUMIF($C$5:$Z$5,$AD$5,C22:Z22) -> 0 | AE22: =SUMIF($C$5:$Z$5,$AD$5,D22:AA22) -> 21192.954 | AF22: =AA22-AD22 -> 0 | AG22: =AB22-AE22 -> 0
A23: 预制菜 | C23: 0 | D23: 8325.044 | E23: 0 | F23: 0 | G23: 0 | H23: 1099.384 | I23: 0 | J23: 1618.916 | K23: 0 | L23: 0 | M23: 0 | N23: 0 | O23: 0 | P23: 0 | Q23: 0 | R23: 56375.966 | S23: 0 | T23: 0 | U23: 0 | V23: 0 | W23: 0 | X23: 0 | Y23: 0 | Z23: 0 | AA23: =C23+E23+G23+I23+K23+M23+O23+Q23+S23+U23+W23+Y23 -> 0 | AB23: =D23+F23+H23+J23+L23+N23+P23+R23+T23+V23+X23+Z23 -> 67419.31 | AD23: =SUMIF($C$5:$Z$5,$AD$5,C23:Z23) -> 0 | AE23: =SUMIF($C$5:$Z$5,$AD$5,D23:AA23) -> 67419.31 | AF23: =AA23-AD23 -> 0 | AG23: =AB23-AE23 -> 0
A24: 其他 | C24: 565070.12 | D24: 0 | E24: 668698.89 | F24: 0 | G24: 1201167.9 | H24: 0 | I24: 1407053.8 | J24: 0 | K24: 1221261.6 | L24: -1808.56 | M24: 1460721.6 | N24: -867.0792 | O24: 1536632.1 | P24: =(-2692.44)*1.04 -> -2800.1376 | Q24: 1566697.5 | R24: =(6687.45-7387.2+25550.42)*1.04 -> 25844.697 | S24: 2149830 | T24: =(-2846.96+2.38+49179.14)*1.04 -> 48187.942 | U24: 1434791.2 | V24: =(-1255.99+11026.02)*1.04 -> 10160.831 | W24: 1615837 | X24: =(-6011.68+9898.61)*1.04 -> 4042.4072 | Y24: 2915479.9 | Z24: =(-856.59+12798.14)*1.04 -> 12419.212 | AA24: =C24+E24+G24+I24+K24+M24+O24+Q24+S24+U24+W24+Y24 -> 17743242 | AB24: =D24+F24+H24+J24+L24+N24+P24+R24+T24+V24+X24+Z24 -> 95179.313 | AD24: =SUMIF($C$5:$Z$5,$AD$5,C24:Z24) -> 17743242 | AE24: =SUMIF($C$5:$Z$5,$AD$5,D24:AA24) -> 95179.313 | AF24: =AA24-AD24 -> 0 | AG24: =AB24-AE24 -> 0
A25: 运费 | C25: 10213.95 | D25: 42373.82 | E25: 12167.34 | F25: 28831.74 | G25: 21970.05 | H25: 30552.64 | I25: 25784.45 | J25: 50790.22 | K25: 22431.95 | L25: 37314.16 | M25: 27356.4 | N25: 45121.38 | O25: 29084.8 | P25: 44454.52 | Q25: 29941.55 | R25: 34293.8 | S25: 41545.67 | T25: 54081.12 | U25: 26834.9 | V25: 37939.25 | W25: 30904.09 | X25: 39318.75 | Y25: 57014.85 | Z25: 43643.56 | AA25: =C25+E25+G25+I25+K25+M25+O25+Q25+S25+U25+W25+Y25 -> 335250 | AB25: =D25+F25+H25+J25+L25+N25+P25+R25+T25+V25+X25+Z25 -> 488714.96 | AD25: =SUMIF($C$5:$Z$5,$AD$5,C25:Z25) -> 335250 | AE25: =SUMIF($C$5:$Z$5,$AD$5,D25:AA25) -> 488714.96 | AF25: =AA25-AD25 -> 0 | AG25: =AB25-AE25 -> 0
A26: 毛利 | B26: 3 | C26: =C6-C16 -> 110215.93 | D26: =D6-D16 -> 547124.67 | E26: =E6-E16 -> 135733.77 | F26: =F6-F16 -> 346293.57 | G26: =G6-G16 -> 251362.03 | H26: =H6-H16 -> 354316.68 | I26: =I6-I16 -> 297661.74 | J26: =J6-J16 -> 532930.77 | ... Z26: =Z6-Z16 -> 786484.27 | AA26: =C26+E26+G26+I26+K26+M26+O26+Q26+S26+U26+W26+Y26 -> 4135783.2 | AB26: =D26+F26+H26+J26+L26+N26+P26+R26+T26+V26+X26+Z26 -> 5855407.2 | AD26: =SUMIF($C$5:$Z$5,$AD$5,C26:Z26) -> 4135783.2 | AE26: =SUMIF($C$5:$Z$5,$AD$5,D26:AA26) -> 5855407.2 | AF26: =AD6-AD16-AA26 -> 0 | AG26: =AE6-AE16-AB26 -> 0
A27: 毛利率 | B27: 4 | C27: =C26/C6 -> 0.16078181 | D27: =D26/D6 -> 0.23739572 | E27: =E26/E6 -> 0.16621819 | F27: =F26/F6 -> 0.2078351 | G27: =G26/G6 -> 0.17047273 | H27: =H26/H6 -> 0.2316401 | I27: =I26/I6 -> 0.17200909 | J27: =J26/J6 -> 0.18756022 | ... AB27: =AB26/AB6 -> 0.20617173 | AD27: =AD26/AD6 -> 0.18617683 | AE27: =AE26/AE6 -> 0.20617173 | AF27: =AA27-AD27 -> 0 | AG27: =AB27-AE27 -> 0
A28: 税金及附加 | B28: 5 | C28: =ROUND(C6*0.88%+C6*0.07%,2) -> 6512.25 | D28: =ROUND(D6*0.88%+D6*0.07%,2) -> 21894.6 | E28: =ROUND(E6*0.88%+E6*0.07%,2) -> 7757.7 | F28: =ROUND(F6*0.88%+F6*0.07%,2) -> 15828.84 | G28: =ROUND(G6*0.88%+G6*0.07%,2) -> 14007.75 | H28: =ROUND(H6*0.88%+H6*0.07%,2) -> 14531.2 | I28: =ROUND(I6*0.88%+I6*0.07%,2) -> 16439.75 | J28: =ROUND(J6*0.88%+J6*0.07%,2) -> 26993.16 | ... N28: =ROUND(N6*0.88%+N6*0.07%,2) -> 24757.73 | O28: 18544 | P28: =ROUND(P6*0.88%+P6*0.07%,2) -> 22261.71 | Q28: 19090.25 | R28: =ROUND(R6*0.88%+R6*0.07%,2) -> 19854.93 | S28: 26488.85 | T28: =ROUND(T6*0.88%+T6*0.07%,2) -> 30214.74 | U28: 17109.5 | V28: =ROUND(V6*0.88%+V6*0.07%,2) -> 18918.53 | W28: 19703.95 | X28: =ROUND(X6*0.88%+X6*0.07%,2) -> 20569.16 | Y28: 36351.75 | Z28: =ROUND(Z6*0.88%+Z6*0.07%,2) -> 34306.08 | AA28: =C28+E28+G28+I28+K28+M28+O28+Q28+S28+U28+W28+Y28 -> 213750 | AB28: =D28+F28+H28+J28+L28+N28+P28+R28+T28+V28+X28+Z28 -> 269806 | AD28: =SUMIF($C$5:$Z$5,$AD$5,C28:Z28) -> 213750 | AE28: =SUMIF($C$5:$Z$5,$AD$5,D28:AA28) -> 269806 | AF28: =AA28-AD28 -> 0 | AG28: =AB28-AE28 -> 0
A29: 销售费用 | B29: 6 | C29: =SUM(C30:C101)-C30-C33-C42-C53-C65 -> 139702.59 | D29: =SUM(D30:D101)-D30-D33-D42-D53-D65 -> 150436.4 | E29: =SUM(E30:E101)-E30-E33-E42-E53-E65 -> 120071.81 | F29: =SUM(F30:F101)-F30-F33-F42-F53-F65 -> 120457.7 | G29: =SUM(G30:G101)-G30-G33-G42-G53-G65 -> 157470.64 | H29: =SUM(H30:H101)-H30-H33-H42-H53-H65 -> 148748.8 | I29: =SUM(I30:I101)-I30-I33-I42-I53-I65 -> 148978.89 | J29: =SUM(J30:J101)-J30-J33-J42-J53-J65 -> 197574.83 | ... Z29: =SUM(Z30:Z101)-Z30-Z33-Z42-Z53-Z65 -> 161742.56 | AA29: =C29+E29+G29+I29+K29+M29+O29+Q29+S29+U29+W29+Y29 -> 1861656.8 | AB29: =D29+F29+H29+J29+L29+N29+P29+R29+T29+V29+X29+Z29 -> 1814288.2 | AD29: =SUMIF($C$5:$Z$5,$AD$5,C29:Z29) -> 1861656.8 | AE29: =SUMIF($C$5:$Z$5,$AD$5,D29:AA29) -> 1814288.2 | AF29: =AD29-(SUM(AA30:AA101)-SUM(AA30,AA33,AA42,AA53,AA65)) -> 0 | AG29: =AE29-(SUM(AB30:AB101)-SUM(AB30,AB33,AB42,AB53,AB65)) -> 0
A30: 职工薪酬 | C30: =SUM(C31:C32) -> 86510.19 | D30: =SUM(D31:D32) -> 105348.29 | E30: =SUM(E31:E32) -> 68499.41 | F30: =SUM(F31:F32) -> 67696.36 | G30: =SUM(G31:G32) -> 82668.24 | H30: =SUM(H31:H32) -> 85581.5 | I30: =SUM(I31:I32) -> 93704.49 | J30: =SUM(J31:J32) -> 114203.5 | ... Z30: =SUM(Z31:Z32) -> 87808.5 | AA30: =C30+E30+G30+I30+K30+M30+O30+Q30+S30+U30+W30+Y30 -> 1165940 | AB30: =D30+F30+H30+J30+L30+N30+P30+R30+T30+V30+X30+Z30 -> 1081819.2 | AD30: =SUMIF($C$5:$Z$5,$AD$5,C30:Z30) -> 1165940 | AE30: =SUMIF($C$5:$Z$5,$AD$5,D30:AA30) -> 1081819.2 | AF30: =AA30-AD30 -> 0 | AG30: =AB30-AE30 -> 0
A31: 工资 | C31: 42127.5 | D31: 38308.14 | E31: 42127.5 | F31: 40967.36 | G31: 42127.5 | H31: 42127.5 | I31: 46767.5 | J31: 40427.5 | K31: 46867.5 | L31: 43527.5 | M31: 46867.5 | N31: 54159.37 | O31: 46867.5 | P31: 53227.5 | Q31: 46967.5 | R31: 48037.18 | S31: 47167.5 | T31: 38427.5 | U31: 47167.5 | V31: 41027.5 | W31: 47167.5 | X31: 42627.5 | Y31: 47217.5 | Z31: 44708.5 | AA31: =C31+E31+G31+I31+K31+M31+O31+Q31+S31+U31+W31+Y31 -> 549440 | AB31: =D31+F31+H31+J31+L31+N31+P31+R31+T31+V31+X31+Z31 -> 527573.05 | AD31: =SUMIF($C$5:$Z$5,$AD$5,C31:Z31) -> 549440 | AE31: =SUMIF($C$5:$Z$5,$AD$5,D31:AA31) -> 527573.05 | AF31: =AA31-AD31 -> 0 | AG31: =AB31-AE31 -> 0
A32: 奖金及提成 | C32: 44382.69 | D32: =95096.15-28056 -> 67040.15 | E32: 26371.91 | F32: =37965-11236 -> 26729 | G32: 40540.74 | H32: =46822-3368 -> 43454 | I32: 46936.99 | J32: =87127-13351 -> 73776 | K32: 43612.78 | L32: =68787-15857 -> 52930 | M32: 46596.68 | N32: =71065-4236-6785-10469+11201-29661 -> 31115 | O32: 49747.42 | P32: =47331+5416-8685 -> 44062 | Q32: 54715.03 | R32: =28636+8685 -> 37321 | S32: 66970.63 | T32: =69214-13008 -> 56206 | U32: 54833.44 | V32: =36191+1348-659 -> 36880 | W32: 59529.09 | X32: =47015-5382 -> 41633 | Y32: 82262.59 | Z32: =26250-3559+38296-17887 -> 43100 | AA32: =C32+E32+G32+I32+K32+M32+O32+Q32+S32+U32+W32+Y32 -> 616499.99 | AB32: =D32+F32+H32+J32+L32+N32+P32+R32+T32+V32+X32+Z32 -> 554246.15 | AD32: =SUMIF($C$5:$Z$5,$AD$5,C32:Z32) -> 616499.99 | AE32: =SUMIF($C$5:$Z$5,$AD$5,D32:AA32) -> 554246.15 | AF32: =AA32-AD32 -> 0 | AG32: =AB32-AE32 -> 0
A33: 社保 | C33: =SUM(C34:C38) -> 7550.4 | D33: =SUM(D34:D38) -> 6063.1 | E33: =SUM(E34:E38) -> 7550.4 | F33: =SUM(F34:F38) -> 6063.1 | G33: =SUM(G34:G38) -> 7550.4 | H33: =SUM(H34:H38) -> 6063.1 | I33: =SUM(I34:I38) -> 7550.4 | J33: =SUM(J34:J38) -> 6063.1 | ... Z33: =SUM(Z34:Z38) -> 7538.82 | AA33: =C33+E33+G33+I33+K33+M33+O33+Q33+S33+U33+W33+Y33 -> 90604.8 | AB33: =D33+F33+H33+J33+L33+N33+P33+R33+T33+V33+X33+Z33 -> 79690.93 | AD33: =SUMIF($C$5:$Z$5,$AD$5,C33:Z33) -> 90604.8 | AE33: =SUMIF($C$5:$Z$5,$AD$5,D33:AA33) -> 79690.93 | AF33: =AA33-AD33 -> 0 | AG33: =AB33-AE33 -> 0
A34: 养老 | C34: 4680 | D34: 3849.6 | E34: 4680 | F34: 3849.6 | G34: 4680 | H34: 3849.6 | I34: 4680 | J34: 3849.6 | K34: 4680 | L34: 3849.6 | M34: 4680 | N34: 4619.52 | O34: 4680 | P34: 4619.52 | Q34: 4680 | R34: 4619.52 | S34: 4680 | T34: 5102.4 | U34: 4680 | V34: 3988.8 | W34: 4680 | X34: 3988.8 | Y34: 4680 | Z34: 4786.56 | AA34: =C34+E34+G34+I34+K34+M34+O34+Q34+S34+U34+W34+Y34 -> 56160 | AB34: =D34+F34+H34+J34+L34+N34+P34+R34+T34+V34+X34+Z34 -> 50973.12 | AD34: =SUMIF($C$5:$Z$5,$AD$5,C34:Z34) -> 56160 | AE34: =SUMIF($C$5:$Z$5,$AD$5,D34:AA34) -> 50973.12 | AF34: =AA34-AD34 -> 0 | AG34: =AB34-AE34 -> 0
A35: 医疗 | C35: 2496 | D35: 2045.1 | E35: 2496 | F35: 2045.1 | G35: 2496 | H35: 2045.1 | I35: 2496 | J35: 2045.1 | K35: 2496 | L35: 2045.1 | M35: 2496 | N35: 2454.12 | O35: 2496 | P35: 2454.12 | Q35: 2496 | R35: 2454.12 | S35: 2496 | T35: 2119.05 | U35: 2496 | V35: 2119.05 | W35: 2496 | X35: 2119.05 | Y35: 2496 | Z35: 2542.86 | AA35: =C35+E35+G35+I35+K35+M35+O35+Q35+S35+U35+W35+Y35 -> 29952 | AB35: =D35+F35+H35+J35+L35+N35+P35+R35+T35+V35+X35+Z35 -> 26487.87 | AD35: =SUMIF($C$5:$Z$5,$AD$5,C35:Z35) -> 29952 | AE35: =SUMIF($C$5:$Z$5,$AD$5,D35:AA35) -> 26487.87 | AF35: =AA35-AD35 -> 0 | AG35: =AB35-AE35 -> 0
A36: 工伤 | C36: 62.4 | D36: 48.1 | E36: 62.4 | F36: 48.1 | G36: 62.4 | H36: 48.1 | I36: 62.4 | J36: 48.1 | K36: 62.4 | L36: 48.1 | M36: 62.4 | N36: 57.72 | O36: 62.4 | P36: 57.72 | Q36: 62.4 | R36: 57.72 | S36: 62.4 | T36: 63.85 | U36: 62.4 | V36: 49.85 | W36: 62.4 | X36: 49.85 | Y36: 62.4 | Z36: 59.82 | AA36: =C36+E36+G36+I36+K36+M36+O36+Q36+S36+U36+W36+Y36 -> 748.8 | AB36: =D36+F36+H36+J36+L36+N36+P36+R36+T36+V36+X36+Z36 -> 637.03 | AD36: =SUMIF($C$5:$Z$5,$AD$5,C36:Z36) -> 748.8 | AE36: =SUMIF($C$5:$Z$5,$AD$5,D36:AA36) -> 637.03 | AF36: =AA36-AD36 -> 0 | AG36: =AB36-AE36 -> 0
A37: 失业 | C37: 156 | D37: 120.3 | E37: 156 | F37: 120.3 | G37: 156 | H37: 120.3 | I37: 156 | J37: 120.3 | K37: 156 | L37: 120.3 | M37: 156 | N37: 144.36 | O37: 156 | P37: 144.36 | Q37: 156 | R37: 144.36 | S37: 156 | T37: 159.45 | U37: 156 | V37: 124.65 | W37: 156 | X37: 124.65 | Y37: 156 | Z37: 149.58 | AA37: =C37+E37+G37+I37+K37+M37+O37+Q37+S37+U37+W37+Y37 -> 1872 | AB37: =D37+F37+H37+J37+L37+N37+P37+R37+T37+V37+X37+Z37 -> 1592.91 | AD37: =SUMIF($C$5:$Z$5,$AD$5,C37:Z37) -> 1872 | AE37: =SUMIF($C$5:$Z$5,$AD$5,D37:AA37) -> 1592.91 | AF37: =AA37-AD37 -> 0 | AG37: =AB37-AE37 -> 0
A38: 生育 | C38: 156 | D38: 0 | E38: 156 | F38: 0 | G38: 156 | H38: 0 | I38: 156 | J38: 0 | K38: 156 | L38: 0 | M38: 156 | N38: 0 | O38: 156 | P38: 0 | Q38: 156 | R38: 0 | S38: 156 | T38: 0 | U38: 156 | V38: 0 | W38: 156 | X38: 0 | Y38: 156 | Z38: 0 | AA38: =C38+E38+G38+I38+K38+M38+O38+Q38+S38+U38+W38+Y38 -> 1872 | AB38: =D38+F38+H38+J38+L38+N38+P38+R38+T38+V38+X38+Z38 -> 0 | AD38: =SUMIF($C$5:$Z$5,$AD$5,C38:Z38) -> 1872 | AE38: =SUMIF($C$5:$Z$5,$AD$5,D38:AA38) -> 0 | AF38: =AA38-AD38 -> 0 | AG38: =AB38-AE38 -> 0
A39: 公积金 | C39: 1614 | D39: 1345 | E39: 1614 | F39: 1345 | G39: 1614 | H39: 1345 | I39: 1614 | J39: 1345 | K39: 1614 | L39: 1345 | M39: 1614 | N39: 1345 | O39: 1614 | P39: 1345 | Q39: 1614 | R39: 1345 | S39: 1614 | T39: 1345 | U39: 1614 | V39: 1345 | W39: 1614 | X39: 1345 | Y39: 1614 | Z39: 1614 | AA39: =C39+E39+G39+I39+K39+M39+O39+Q39+S39+U39+W39+Y39 -> 19368 | AB39: =D39+F39+H39+J39+L39+N39+P39+R39+T39+V39+X39+Z39 -> 16409 | AD39: =SUMIF($C$5:$Z$5,$AD$5,C39:Z39) -> 19368 | AE39: =SUMIF($C$5:$Z$5,$AD$5,D39:AA39) -> 16409 | AF39: =AA39-AD39 -> 0 | AG39: =AB39-AE39 -> 0
A40: 工会经费 | D40: 0 | F40: 0 | H40: 0 | J40: 0 | L40: 0 | N40: 0 | P40: 0 | R40: 0 | T40: 0 | V40: 0 | X40: 0 | Z40: 0 | AA40: =C40+E40+G40+I40+K40+M40+O40+Q40+S40+U40+W40+Y40 -> 0 | AB40: =D40+F40+H40+J40+L40+N40+P40+R40+T40+V40+X40+Z40 -> 0 | AD40: =SUMIF($C$5:$Z$5,$AD$5,C40:Z40) -> 0 | AE40: =SUMIF($C$5:$Z$5,$AD$5,D40:AA40) -> 0 | AF40: =AA40-AD40 -> 0 | AG40: =AB40-AE40 -> 0
A41: 职工教育经费 | D41: 0 | F41: 0 | H41: 0 | J41: 0 | L41: 0 | N41: 0 | P41: 0 | R41: 0 | T41: 0 | V41: 0 | X41: 0 | Z41: 0 | AA41: =C41+E41+G41+I41+K41+M41+O41+Q41+S41+U41+W41+Y41 -> 0 | AB41: =D41+F41+H41+J41+L41+N41+P41+R41+T41+V41+X41+Z41 -> 0 | AD41: =SUMIF($C$5:$Z$5,$AD$5,C41:Z41) -> 0 | AE41: =SUMIF($C$5:$Z$5,$AD$5,D41:AA41) -> 0 | AF41: =AA41-AD41 -> 0 | AG41: =AB41-AE41 -> 0
A42: 福利费 | C42: =SUM(C43:C49) -> 1620 | D42: =SUM(D43:D49) -> 1368 | E42: =SUM(E43:E49) -> 0 | F42: =SUM(F43:F49) -> 2157.49 | G42: =SUM(G43:G49) -> 430 | H42: =SUM(H43:H49) -> 1067 | I42: =SUM(I43:I49) -> 420 | J42: =SUM(J43:J49) -> 120.01 | ... Z42: =SUM(Z43:Z49) -> 110.77 | AA42: =C42+E42+G42+I42+K42+M42+O42+Q42+S42+U42+W42+Y42 -> 4510 | AB42: =D42+F42+H42+J42+L42+N42+P42+R42+T42+V42+X42+Z42 -> 8281.49 | AD42: =SUMIF($C$5:$Z$5,$AD$5,C42:Z42) -> 4510 | AE42: =SUMIF($C$5:$Z$5,$AD$5,D42:AA42) -> 8281.49 | AF42: =AA42-AD42 -> 0 | AG42: =AB42-AE42 -> 0
A43: 职工房租 | D43: 0 | F43: 0 | H43: 0 | J43: 0 | L43: 0 | N43: 0 | P43: 0 | R43: 0 | T43: 0 | V43: 0 | X43: 0 | Z43: 0 | AA43: =C43+E43+G43+I43+K43+M43+O43+Q43+S43+U43+W43+Y43 -> 0 | AB43: =D43+F43+H43+J43+L43+N43+P43+R43+T43+V43+X43+Z43 -> 0 | AD43: =SUMIF($C$5:$Z$5,$AD$5,C43:Z43) -> 0 | AE43: =SUMIF($C$5:$Z$5,$AD$5,D43:AA43) -> 0 | AF43: =AA43-AD43 -> 0 | AG43: =AB43-AE43 -> 0
A44: 水电物业费 | D44: 168 | F44: 157.49 | H44: 67 | J44: 120.01 | L44: 37 | N44: 116.44 | P44: 98.15 | R44: 245.39 | T44: 167.46 | V44: 195.78 | X44: 46 | Z44: 110.77 | AA44: =C44+E44+G44+I44+K44+M44+O44+Q44+S44+U44+W44+Y44 -> 0 | AB44: =D44+F44+H44+J44+L44+N44+P44+R44+T44+V44+X44+Z44 -> 1529.49 | AD44: =SUMIF($C$5:$Z$5,$AD$5,C44:Z44) -> 0 | AE44: =SUMIF($C$5:$Z$5,$AD$5,D44:AA44) -> 1529.49 | AF44: =AA44-AD44 -> 0 | AG44: =AB44-AE44 -> 0
A45: 员工餐 | D45: 0 | F45: 0 | H45: 0 | J45: 0 | L45: 0 | N45: 0 | P45: 0 | R45: 0 | T45: 0 | V45: 0 | X45: 0 | Z45: 0 | AA45: =C45+E45+G45+I45+K45+M45+O45+Q45+S45+U45+W45+Y45 -> 0 | AB45: =D45+F45+H45+J45+L45+N45+P45+R45+T45+V45+X45+Z45 -> 0 | AD45: =SUMIF($C$5:$Z$5,$AD$5,C45:Z45) -> 0 | AE45: =SUMIF($C$5:$Z$5,$AD$5,D45:AA45) -> 0 | AF45: =AA45-AD45 -> 0 | AG45: =AB45-AE45 -> 0
A46: 节日礼品 | C46: 1200 | D46: 1200 | F46: 0 | G46: 100 | H46: 0 | J46: 0 | L46: 0 | N46: 0 | P46: 0 | R46: 0 | T46: 1000 | U46: 1200 | V46: 0 | X46: 0 | Z46: 0 | AA46: =C46+E46+G46+I46+K46+M46+O46+Q46+S46+U46+W46+Y46 -> 2500 | AB46: =D46+F46+H46+J46+L46+N46+P46+R46+T46+V46+X46+Z46 -> 2200 | AD46: =SUMIF($C$5:$Z$5,$AD$5,C46:Z46) -> 2500 | AE46: =SUMIF($C$5:$Z$5,$AD$5,D46:AA46) -> 2200 | AF46: =AA46-AD46 -> 0 | AG46: =AB46-AE46 -> 0
A47: 生日礼品 | D47: 0 | F47: 0 | G47: 330 | H47: 0 | J47: 0 | L47: 0 | N47: 0 | P47: 0 | R47: 0 | T47: 0 | V47: 0 | X47: 0 | Z47: 0 | AA47: =C47+E47+G47+I47+K47+M47+O47+Q47+S47+U47+W47+Y47 -> 330 | AB47: =D47+F47+H47+J47+L47+N47+P47+R47+T47+V47+X47+Z47 -> 0 | AD47: =SUMIF($C$5:$Z$5,$AD$5,C47:Z47) -> 330 | AE47: =SUMIF($C$5:$Z$5,$AD$5,D47:AA47) -> 0 | AF47: =AA47-AD47 -> 0 | AG47: =AB47-AE47 -> 0
A48: 体检 | D48: 0 | F48: 2000 | H48: 0 | J48: 0 | L48: 0 | N48: 0 | P48: 0 | R48: 0 | T48: 0 | V48: 0 | X48: 0 | Z48: 0 | AA48: =C48+E48+G48+I48+K48+M48+O48+Q48+S48+U48+W48+Y48 -> 0 | AB48: =D48+F48+H48+J48+L48+N48+P48+R48+T48+V48+X48+Z48 -> 2000 | AD48: =SUMIF($C$5:$Z$5,$AD$5,C48:Z48) -> 0 | AE48: =SUMIF($C$5:$Z$5,$AD$5,D48:AA48) -> 2000 | AF48: =AA48-AD48 -> 0 | AG48: =AB48-AE48 -> 0
